Workbook
Name ARA_Threshold: #REF!
Name ARP_Threshold: #REF!
Name DiffAmtHeader: #REF!
Name DiffPercentHeader: #REF!
Name MP: #REF!
Name Population: #REF!
Name S_Adjust_Data: #REF!
Name S_Adjust_GT: #REF!
Name S_AJE_Tot_Data: #REF!
Name S_AJE_Tot_GT: #REF!
Name S_CY_Beg_Data: #REF!
Name S_CY_Beg_GT: #REF!
Name S_CY_End_Data: #REF!
Name S_CY_End_GT: #REF!
Name S_Headings: #REF!
Name S_KeyValue: #REF!
Name S_PY_End_Data: #REF!
Name S_PY_End_GT: #REF!
Name S_RJE_Tot_Data: #REF!
Name S_RJE_Tot_GT: #REF!
Name TextRefCopy1: #REF!
Name TextRefCopy10: #REF!
Name TextRefCopy11: #REF!
Name TextRefCopy12: #REF!
Name TextRefCopy13: #REF!
Name TextRefCopy14: #REF!
Name TextRefCopy15: #REF!
Name TextRefCopy16: #REF!
Name TextRefCopy17: #REF!
Name TextRefCopy19: #REF!
Name TextRefCopy20: #REF!
Name TextRefCopy21: #REF!
Name TextRefCopy22: #REF!
Name TextRefCopy23: #REF!
Name TextRefCopy25: #REF!
Name TextRefCopy26: #REF!
Name TextRefCopy27: #REF!
Name TextRefCopy28: #REF!
Name TextRefCopy29: #REF!
Name TextRefCopy30: #REF!
Name TextRefCopy31: #REF!
Name TextRefCopy32: #REF!
Name TextRefCopy33: #REF!
Name TextRefCopy34: #REF!
Name TextRefCopy35: #REF!
Name TextRefCopy36: #REF!
Name TextRefCopy37: #REF!
Name TextRefCopy38: #REF!
Name TextRefCopy39: #REF!
Name TextRefCopy40: #REF!
Name TextRefCopy41: #REF!
Name TextRefCopy42: #REF!
Name TextRefCopy43: #REF!
Name TextRefCopy44: #REF!
Name TextRefCopy45: #REF!
Name TextRefCopy46: #REF!
Name TextRefCopy47: #REF!
Name TextRefCopy48: #REF!
Name TextRefCopy49: #REF!
Name TextRefCopy5: #REF!

Sheet YearlyAlif
A3: GLAcctDisp | B3: GLAcctDesc | C3: Y2014 | D3: Y2015 | E3: Y2016 | F3: Y2017 | G3: Y2018 | H3: Y2019 | I3: Y2020 | J3: Y2021 | K3: Y2022 | L3: Y2023 | M3: Y2024 | N3: Y2025 | O3: Acnt Group | P3: Expense Group
A4: 110001 | B4: LAND | C4: =SUMIF(ALIF_Y2014!$A:$A,$A4,ALIF_Y2014!$F:$F) -> 0 | D4: =SUMIF(ALIF_Y2015!$A:$A,$A4,ALIF_Y2015!$F:$F) -> 0 | E4: =SUMIF(ALIF_Y2016!$A:$A,$A4,ALIF_Y2016!$F:$F) -> 0 | F4: =SUMIF(ALIF_Y2017!$A:$A,$A4,ALIF_Y2017!$F:$F) -> 0 | G4: =SUMIF(ALIF_Y2018!$A:$A,$A4,ALIF_Y2018!$F:$F) -> 0 | H4: =SUMIF(ALIF_Y2019!$A:$A,$A4,ALIF_Y2019!$F:$F) -> 0 | I4: =SUMIF(ALIF_Y2020!$A:$A,$A4,ALIF_Y2020!$F:$F) -> 0 | J4: =SUMIF(ALIF_Y2021!$A:$A,$A4,ALIF_Y2021!$F:$F) -> 0 | K4: =SUMIF(ALIF_Y2022!$A:$A,$A4,ALIF_Y2022!$F:$F) -> 0 | L4: =SUMIF(ALIF_Y2023!$A:$A,$A4,ALIF_Y2023!$F:$F) -> 0 | M4: =SUMIF(ALIF_Y2024!$A:$A,$A4,ALIF_Y2024!$F:$F) -> 0 | N4: =SUMIF(ALIF_Y2025!$A:$A,$A4,ALIF_Y2025!$F:$F) -> 0 | O4: =_xlfn.XLOOKUP(A4,Map!A:A,Map!E:E) -> Property, plant and equipment | P4: =_xlfn.XLOOKUP(A4,Map!A:A,Map!D:D) -> Non-Current Assets
A5: 110002 | B5: BUILDINGS | C5: =SUMIF(ALIF_Y2014!$A:$A,$A5,ALIF_Y2014!$F:$F) -> 249682 | D5: =SUMIF(ALIF_Y2015!$A:$A,$A5,ALIF_Y2015!$F:$F) -> 249682 | E5: =SUMIF(ALIF_Y2016!$A:$A,$A5,ALIF_Y2016!$F:$F) -> 249682 | F5: =SUMIF(ALIF_Y2017!$A:$A,$A5,ALIF_Y2017!$F:$F) -> 249682 | G5: =SUMIF(ALIF_Y2018!$A:$A,$A5,ALIF_Y2018!$F:$F) -> 1.06505e+08 | H5: =SUMIF(ALIF_Y2019!$A:$A,$A5,ALIF_Y2019!$F:$F) -> 1.06505e+08 | I5: =SUMIF(ALIF_Y2020!$A:$A,$A5,ALIF_Y2020!$F:$F) -> 1.06505e+08 | J5: =SUMIF(ALIF_Y2021!$A:$A,$A5,ALIF_Y2021!$F:$F) -> 1.06505e+08 | K5: =SUMIF(ALIF_Y2022!$A:$A,$A5,ALIF_Y2022!$F:$F) -> 1.06505e+08 | L5: =SUMIF(ALIF_Y2023!$A:$A,$A5,ALIF_Y2023!$F:$F) -> 1.06505e+08 | M5: =SUMIF(ALIF_Y2024!$A:$A,$A5,ALIF_Y2024!$F:$F) -> 1.072962e+08 | N5: =SUMIF(ALIF_Y2025!$A:$A,$A5,ALIF_Y2025!$F:$F) -> 1.072962e+08 | O5: =_xlfn.XLOOKUP(A5,Map!A:A,Map!E:E) -> Property, plant and equipment | P5: =_xlfn.XLOOKUP(A5,Map!A:A,Map!D:D) -> Non-Current Assets
A6: 110003 | B6: DECORS AND INSTALLATIONS | C6: =SUMIF(ALIF_Y2014!$A:$A,$A6,ALIF_Y2014!$F:$F) -> 1765393.8 | D6: =SUMIF(ALIF_Y2015!$A:$A,$A6,ALIF_Y2015!$F:$F) -> 1773233.8 | E6: =SUMIF(ALIF_Y2016!$A:$A,$A6,ALIF_Y2016!$F:$F) -> 1773233.8 | F6: =SUMIF(ALIF_Y2017!$A:$A,$A6,ALIF_Y2017!$F:$F) -> 1773233.8 | G6: =SUMIF(ALIF_Y2018!$A:$A,$A6,ALIF_Y2018!$F:$F) -> 1824603.8 | H6: =SUMIF(ALIF_Y2019!$A:$A,$A6,ALIF_Y2019!$F:$F) -> 1920201.8 | I6: =SUMIF(ALIF_Y2020!$A:$A,$A6,ALIF_Y2020!$F:$F) -> 1765393.8 | J6: =SUMIF(ALIF_Y2021!$A:$A,$A6,ALIF_Y2021!$F:$F) -> 1765393.8 | K6: =SUMIF(ALIF_Y2022!$A:$A,$A6,ALIF_Y2022!$F:$F) -> 1765393.8 | L6: =SUMIF(ALIF_Y2023!$A:$A,$A6,ALIF_Y2023!$F:$F) -> 1765393.8 | M6: =SUMIF(ALIF_Y2024!$A:$A,$A6,ALIF_Y2024!$F:$F) -> 1765393.8 | N6: =SUMIF(ALIF_Y2025!$A:$A,$A6,ALIF_Y2025!$F:$F) -> 2296738 | O6: =_xlfn.XLOOKUP(A6,Map!A:A,Map!E:E) -> Property, plant and equipment | P6: =_xlfn.XLOOKUP(A6,Map!A:A,Map!D:D) -> Non-Current Assets
A7: 110004 | B7: MACHINERY AND EQUIPMENTS | C7: =SUMIF(ALIF_Y2014!$A:$A,$A7,ALIF_Y2014!$F:$F) -> 38561941 | D7: =SUMIF(ALIF_Y2015!$A:$A,$A7,ALIF_Y2015!$F:$F) -> 39518811 | E7: =SUMIF(ALIF_Y2016!$A:$A,$A7,ALIF_Y2016!$F:$F) -> 39914308 | F7: =SUMIF(ALIF_Y2017!$A:$A,$A7,ALIF_Y2017!$F:$F) -> 43898751 | G7: =SUMIF(ALIF_Y2018!$A:$A,$A7,ALIF_Y2018!$F:$F) -> 62879993 | H7: =SUMIF(ALIF_Y2019!$A:$A,$A7,ALIF_Y2019!$F:$F) -> 66375893 | I7: =SUMIF(ALIF_Y2020!$A:$A,$A7,ALIF_Y2020!$F:$F) -> 71133086 | J7: =SUMIF(ALIF_Y2021!$A:$A,$A7,ALIF_Y2021!$F:$F) -> 72216302 | K7: =SUMIF(ALIF_Y2022!$A:$A,$A7,ALIF_Y2022!$F:$F) -> 80282872 | L7: =SUMIF(ALIF_Y2023!$A:$A,$A7,ALIF_Y2023!$F:$F) -> 72478281 | M7: =SUMIF(ALIF_Y2024!$A:$A,$A7,ALIF_Y2024!$F:$F) -> 81812316 | N7: =SUMIF(ALIF_Y2025!$A:$A,$A7,ALIF_Y2025!$F:$F) -> 93774591 | O7: =_xlfn.XLOOKUP(A7,Map!A:A,Map!E:E) -> Property, plant and equipment | P7: =_xlfn.XLOOKUP(A7,Map!A:A,Map!D:D) -> Non-Current Assets
A8: 110006 | B8: VEHICLES | C8: =SUMIF(ALIF_Y2014!$A:$A,$A8,ALIF_Y2014!$F:$F) -> 1446052.1 | D8: =SUMIF(ALIF_Y2015!$A:$A,$A8,ALIF_Y2015!$F:$F) -> 1446052.1 | E8: =SUMIF(ALIF_Y2016!$A:$A,$A8,ALIF_Y2016!$F:$F) -> 1548852.1 | F8: =SUMIF(ALIF_Y2017!$A:$A,$A8,ALIF_Y2017!$F:$F) -> 1891752.1 | G8: =SUMIF(ALIF_Y2018!$A:$A,$A8,ALIF_Y2018!$F:$F) -> 2495208.5 | H8: =SUMIF(ALIF_Y2019!$A:$A,$A8,ALIF_Y2019!$F:$F) -> 2791352.1 | I8: =SUMIF(ALIF_Y2020!$A:$A,$A8,ALIF_Y2020!$F:$F) -> 2602761 | J8: =SUMIF(ALIF_Y2021!$A:$A,$A8,ALIF_Y2021!$F:$F) -> 2675451 | K8: =SUMIF(ALIF_Y2022!$A:$A,$A8,ALIF_Y2022!$F:$F) -> 3033459.7 | L8: =SUMIF(ALIF_Y2023!$A:$A,$A8,ALIF_Y2023!$F:$F) -> 3090755.7 | M8: =SUMIF(ALIF_Y2024!$A:$A,$A8,ALIF_Y2024!$F:$F) -> 3327255.7 | N8: =SUMIF(ALIF_Y2025!$A:$A,$A8,ALIF_Y2025!$F:$F) -> 3650255.2 | O8: =_xlfn.XLOOKUP(A8,Map!A:A,Map!E:E) -> Property, plant and equipment | P8: =_xlfn.XLOOKUP(A8,Map!A:A,Map!D:D) -> Non-Current Assets
A9: 110007 | B9: OFFICE EQUIPMENTS& COMPUTR PROGRAMS INSTALLATIONS | C9: =SUMIF(ALIF_Y2014!$A:$A,$A9,ALIF_Y2014!$F:$F) -> 798523.45 | D9: =SUMIF(ALIF_Y2015!$A:$A,$A9,ALIF_Y2015!$F:$F) -> 798523.45 | E9: =SUMIF(ALIF_Y2016!$A:$A,$A9,ALIF_Y2016!$F:$F) -> 798523.45 | F9: =SUMIF(ALIF_Y2017!$A:$A,$A9,ALIF_Y2017!$F:$F) -> 798523.45 | G9: =SUMIF(ALIF_Y2018!$A:$A,$A9,ALIF_Y2018!$F:$F) -> 876515.95 | H9: =SUMIF(ALIF_Y2019!$A:$A,$A9,ALIF_Y2019!$F:$F) -> 876515.95 | I9: =SUMIF(ALIF_Y2020!$A:$A,$A9,ALIF_Y2020!$F:$F) -> 1191638.9 | J9: =SUMIF(ALIF_Y2021!$A:$A,$A9,ALIF_Y2021!$F:$F) -> 2056841.1 | K9: =SUMIF(ALIF_Y2022!$A:$A,$A9,ALIF_Y2022!$F:$F) -> 2100287.9 | L9: =SUMIF(ALIF_Y2023!$A:$A,$A9,ALIF_Y2023!$F:$F) -> 2100287.9 | M9: =SUMIF(ALIF_Y2024!$A:$A,$A9,ALIF_Y2024!$F:$F) -> 2269918.4 | N9: =SUMIF(ALIF_Y2025!$A:$A,$A9,ALIF_Y2025!$F:$F) -> 2677196.3 | O9: =_xlfn.XLOOKUP(A9,Map!A:A,Map!E:E) -> Property, plant and equipment | P9: =_xlfn.XLOOKUP(A9,Map!A:A,Map!D:D) -> Non-Current Assets
A10: 110008 | B10: FURNITURE AND FITTINGS | C10: =SUMIF(ALIF_Y2014!$A:$A,$A10,ALIF_Y2014!$F:$F) -> 191765.4 | D10: =SUMIF(ALIF_Y2015!$A:$A,$A10,ALIF_Y2015!$F:$F) -> 191765.4 | E10: =SUMIF(ALIF_Y2016!$A:$A,$A10,ALIF_Y2016!$F:$F) -> 191765.4 | F10: =SUMIF(ALIF_Y2017!$A:$A,$A10,ALIF_Y2017!$F:$F) -> 191765.4 | G10: =SUMIF(ALIF_Y2018!$A:$A,$A10,ALIF_Y2018!$F:$F) -> 533547.4 | H10: =SUMIF(ALIF_Y2019!$A:$A,$A10,ALIF_Y2019!$F:$F) -> 616788.35 | I10: =SUMIF(ALIF_Y2020!$A:$A,$A10,ALIF_Y2020!$F:$F) -> 961301.68 | J10: =SUMIF(ALIF_Y2021!$A:$A,$A10,ALIF_Y2021!$F:$F) -> 1015678.5 | K10: =SUMIF(ALIF_Y2022!$A:$A,$A10,ALIF_Y2022!$F:$F) -> 1101801 | L10: =SUMIF(ALIF_Y2023!$A:$A,$A10,ALIF_Y2023!$F:$F) -> 1101801 | M10: =SUMIF(ALIF_Y2024!$A:$A,$A10,ALIF_Y2024!$F:$F) -> 1134240.1 | N10: =SUMIF(ALIF_Y2025!$A:$A,$A10,ALIF_Y2025!$F:$F) -> 1155192.2 | O10: =_xlfn.XLOOKUP(A10,Map!A:A,Map!E:E) -> Property, plant and equipment | P10: =_xlfn.XLOOKUP(A10,Map!A:A,Map!D:D) -> Non-Current Assets
A11: 111009 | B11: RIGHT OF USE ASSETS | C11: =SUMIF(ALIF_Y2014!$A:$A,$A11,ALIF_Y2014!$F:$F) -> 0 | D11: =SUMIF(ALIF_Y2015!$A:$A,$A11,ALIF_Y2015!$F:$F) -> 0 | E11: =SUMIF(ALIF_Y2016!$A:$A,$A11,ALIF_Y2016!$F:$F) -> 0 | F11: =SUMIF(ALIF_Y2017!$A:$A,$A11,ALIF_Y2017!$F:$F) -> 0 | G11: =SUMIF(ALIF_Y2018!$A:$A,$A11,ALIF_Y2018!$F:$F) -> 0 | H11: =SUMIF(ALIF_Y2019!$A:$A,$A11,ALIF_Y2019!$F:$F) -> 2020135 | I11: =SUMIF(ALIF_Y2020!$A:$A,$A11,ALIF_Y2020!$F:$F) -> 2020135 | J11: =SUMIF(ALIF_Y2021!$A:$A,$A11,ALIF_Y2021!$F:$F) -> 2020135 | K11: =SUMIF(ALIF_Y2022!$A:$A,$A11,ALIF_Y2022!$F:$F) -> 2020135 | L11: =SUMIF(ALIF_Y2023!$A:$A,$A11,ALIF_Y2023!$F:$F) -> 2020135 | M11: =SUMIF(ALIF_Y2024!$A:$A,$A11,ALIF_Y2024!$F:$F) -> 2020135 | N11: =SUMIF(ALIF_Y2025!$A:$A,$A11,ALIF_Y2025!$F:$F) -> 3674470.8 | O11: =_xlfn.XLOOKUP(A11,Map!A:A,Map!E:E) -> Right of use | P11: =_xlfn.XLOOKUP(A11,Map!A:A,Map!D:D) -> Non-Current Assets
A12: 111010 | B12: INSTALLATION IN PROGRESS | C12: =SUMIF(ALIF_Y2014!$A:$A,$A12,ALIF_Y2014!$F:$F) -> 0 | D12: =SUMIF(ALIF_Y2015!$A:$A,$A12,ALIF_Y2015!$F:$F) -> 0 | E12: =SUMIF(ALIF_Y2016!$A:$A,$A12,ALIF_Y2016!$F:$F) -> 0 | F12: =SUMIF(ALIF_Y2017!$A:$A,$A12,ALIF_Y2017!$F:$F) -> 0 | G12: =SUMIF(ALIF_Y2018!$A:$A,$A12,ALIF_Y2018!$F:$F) -> 0 | H12: =SUMIF(ALIF_Y2019!$A:$A,$A12,ALIF_Y2019!$F:$F) -> 0 | I12: =SUMIF(ALIF_Y2020!$A:$A,$A12,ALIF_Y2020!$F:$F) -> 0 | J12: =SUMIF(ALIF_Y2021!$A:$A,$A12,ALIF_Y2021!$F:$F) -> 0 | K12: =SUMIF(ALIF_Y2022!$A:$A,$A12,ALIF_Y2022!$F:$F) -> 0 | L12: =SUMIF(ALIF_Y2023!$A:$A,$A12,ALIF_Y2023!$F:$F) -> 0 | M12: =SUMIF(ALIF_Y2024!$A:$A,$A12,ALIF_Y2024!$F:$F) -> 0 | N12: =SUMIF(ALIF_Y2025!$A:$A,$A12,ALIF_Y2025!$F:$F) -> 17130501 | O12: =_xlfn.XLOOKUP(A12,Map!A:A,Map!E:E) -> Property, plant and equipment | P12: =_xlfn.XLOOKUP(A12,Map!A:A,Map!D:D) -> Non-Current Assets
A13: 111013 | B13: INSTALLATION IN PROGRESS JEDDAH PROJECT | C13: =SUMIF(ALIF_Y2014!$A:$A,$A13,ALIF_Y2014!$F:$F) -> 0 | D13: =SUMIF(ALIF_Y2015!$A:$A,$A13,ALIF_Y2015!$F:$F) -> 10769235 | E13: =SUMIF(ALIF_Y2016!$A:$A,$A13,ALIF_Y2016!$F:$F) -> 99946347 | F13: =SUMIF(ALIF_Y2017!$A:$A,$A13,ALIF_Y2017!$F:$F) -> 1.022654e+08 | G13: =SUMIF(ALIF_Y2018!$A:$A,$A13,ALIF_Y2018!$F:$F) -> 5140199 | H13: =SUMIF(ALIF_Y2019!$A:$A,$A13,ALIF_Y2019!$F:$F) -> 8976734.2 | I13: =SUMIF(ALIF_Y2020!$A:$A,$A13,ALIF_Y2020!$F:$F) -> 0 | J13: =SUMIF(ALIF_Y2021!$A:$A,$A13,ALIF_Y2021!$F:$F) -> 0 | K13: =SUMIF(ALIF_Y2022!$A:$A,$A13,ALIF_Y2022!$F:$F) -> 0 | L13: =SUMIF(ALIF_Y2023!$A:$A,$A13,ALIF_Y2023!$F:$F) -> 569470.02 | M13: =SUMIF(ALIF_Y2024!$A:$A,$A13,ALIF_Y2024!$F:$F) -> 3661922.8 | N13: =SUMIF(ALIF_Y2025!$A:$A,$A13,ALIF_Y2025!$F:$F) -> -543176.42 | O13: =_xlfn.XLOOKUP(A13,Map!A:A,Map!E:E) -> Property, plant and equipment | P13: =_xlfn.XLOOKUP(A13,Map!A:A,Map!D:D) -> Non-Current Assets
A14: 111099 | B14: Fixed Assets Clearing Accounts | C14: =SUMIF(ALIF_Y2014!$A:$A,$A14,ALIF_Y2014!$F:$F) -> 0 | D14: =SUMIF(ALIF_Y2015!$A:$A,$A14,ALIF_Y2015!$F:$F) -> 0 | E14: =SUMIF(ALIF_Y2016!$A:$A,$A14,ALIF_Y2016!$F:$F) -> 0 | F14: =SUMIF(ALIF_Y2017!$A:$A,$A14,ALIF_Y2017!$F:$F) -> 0 | G14: =SUMIF(ALIF_Y2018!$A:$A,$A14,ALIF_Y2018!$F:$F) -> 0 | H14: =SUMIF(ALIF_Y2019!$A:$A,$A14,ALIF_Y2019!$F:$F) -> 0 | I14: =SUMIF(ALIF_Y2020!$A:$A,$A14,ALIF_Y2020!$F:$F) -> 0 | J14: =SUMIF(ALIF_Y2021!$A:$A,$A14,ALIF_Y2021!$F:$F) -> 0 | K14: =SUMIF(ALIF_Y2022!$A:$A,$A14,ALIF_Y2022!$F:$F) -> 0 | L14: =SUMIF(ALIF_Y2023!$A:$A,$A14,ALIF_Y2023!$F:$F) -> 0 | M14: =SUMIF(ALIF_Y2024!$A:$A,$A14,ALIF_Y2024!$F:$F) -> 220102.93 | N14: =SUMIF(ALIF_Y2025!$A:$A,$A14,ALIF_Y2025!$F:$F) -> 135753.14 | O14: =_xlfn.XLOOKUP(A14,Map!A:A,Map!E:E) -> Property, plant and equipment | P14: =_xlfn.XLOOKUP(A14,Map!A:A,Map!D:D) -> Non-Current Assets
A15: 120001 | B15: ACCUM DEPR BUILDINGS | C15: =SUMIF(ALIF_Y2014!$A:$A,$A15,ALIF_Y2014!$F:$F) -> -227682.83 | D15: =SUMIF(ALIF_Y2015!$A:$A,$A15,ALIF_Y2015!$F:$F) -> -242695.31 | E15: =SUMIF(ALIF_Y2016!$A:$A,$A15,ALIF_Y2016!$F:$F) -> -249150.34 | F15: =SUMIF(ALIF_Y2017!$A:$A,$A15,ALIF_Y2017!$F:$F) -> -249682.01 | G15: =SUMIF(ALIF_Y2018!$A:$A,$A15,ALIF_Y2018!$F:$F) -> -694867.69 | H15: =SUMIF(ALIF_Y2019!$A:$A,$A15,ALIF_Y2019!$F:$F) -> -2186446.3 | I15: =SUMIF(ALIF_Y2020!$A:$A,$A15,ALIF_Y2020!$F:$F) -> -3753290.5 | J15: =SUMIF(ALIF_Y2021!$A:$A,$A15,ALIF_Y2021!$F:$F) -> -5320134.7 | K15: =SUMIF(ALIF_Y2022!$A:$A,$A15,ALIF_Y2022!$F:$F) -> -6886978.9 | L15: =SUMIF(ALIF_Y2023!$A:$A,$A15,ALIF_Y2023!$F:$F) -> -8453823.1 | M15: =SUMIF(ALIF_Y2024!$A:$A,$A15,ALIF_Y2024!$F:$F) -> -10037151 | N15: =SUMIF(ALIF_Y2025!$A:$A,$A15,ALIF_Y2025!$F:$F) -> -11630035 | O15: =_xlfn.XLOOKUP(A15,Map!A:A,Map!E:E) -> Property, plant and equipment | P15: =_xlfn.XLOOKUP(A15,Map!A:A,Map!D:D) -> Non-Current Assets
... A269: 800002 | B269: AIMS HOLDING EXP OF CURRENT ACC | C269: =SUMIF(ALIF_Y2014!$A:$A,$A269,ALIF_Y2014!$F:$F) -> 0 | D269: =SUMIF(ALIF_Y2015!$A:$A,$A269,ALIF_Y2015!$F:$F) -> 0 | E269: =SUMIF(ALIF_Y2016!$A:$A,$A269,ALIF_Y2016!$F:$F) -> 0 | F269: =SUMIF(ALIF_Y2017!$A:$A,$A269,ALIF_Y2017!$F:$F) -> 0 | G269: =SUMIF(ALIF_Y2018!$A:$A,$A269,ALIF_Y2018!$F:$F) -> 0 | H269: =SUMIF(ALIF_Y2019!$A:$A,$A269,ALIF_Y2019!$F:$F) -> 0 | I269: =SUMIF(ALIF_Y2020!$A:$A,$A269,ALIF_Y2020!$F:$F) -> 0 | J269: =SUMIF(ALIF_Y2021!$A:$A,$A269,ALIF_Y2021!$F:$F) -> 0 | K269: =SUMIF(ALIF_Y2022!$A:$A,$A269,ALIF_Y2022!$F:$F) -> 700886 | L269: =SUMIF(ALIF_Y2023!$A:$A,$A269,ALIF_Y2023!$F:$F) -> 0 | M269: =SUMIF(ALIF_Y2024!$A:$A,$A269,ALIF_Y2024!$F:$F) -> 0 | N269: =SUMIF(ALIF_Y2025!$A:$A,$A269,ALIF_Y2025!$F:$F) -> 0 | O269: =_xlfn.XLOOKUP(A269,Map!A:A,Map!E:E) -> AIMS expenses | P269: =_xlfn.XLOOKUP(A269,Map!A:A,Map!D:D) -> General and Admin
C271: =SUBTOTAL(9,C4:C270) -> 3603438.5 | D271: =SUBTOTAL(9,D4:D270) -> 1318911.2 | E271: =SUBTOTAL(9,E4:E270) -> 3619649 | F271: =SUBTOTAL(9,F4:F270) -> 3261022.8 | G271: =SUBTOTAL(9,G4:G270) -> 485044.33 | H271: =SUBTOTAL(9,H4:H270) -> 1089346.1 | I271: =SUBTOTAL(9,I4:I270) -> 1237901.3 | J271: =SUBTOTAL(9,J4:J270) -> 1339380.2 | ... N271: =SUBTOTAL(9,N4:N270) -> -1566334.4

Sheet BS
A1: AIMS INDUSTRIAL
A2: Balance Sheet
A3: 31 December 2025 | F3: 1 | L3: 2
D5: Y2014 | E5: Y2015 | F5: Y2016 | G5: Y2017 | H5: Y2018 | I5: Y2019 | J5: Y2020 | K5: Y2021 | L5: Y2022 | M5: Y2023 | N5: Y2024 | O5: Y2025
B6: Current assets
B7: Cash and cash equivalents | D7: =SUMIF(ALIF_Y2014!$I:$I,$B7,ALIF_Y2014!$F:$F) -> 11085979 | E7: =SUMIF(ALIF_Y2015!$I:$I,$B7,ALIF_Y2015!$F:$F) -> 4470130.8 | F7: =SUMIF(ALIF_Y2016!$I:$I,$B7,ALIF_Y2016!$F:$F) -> 4689654.8 | G7: =SUMIF(ALIF_Y2017!$I:$I,$B7,ALIF_Y2017!$F:$F) -> 7257276.1 | H7: =SUMIF(ALIF_Y2018!$I:$I,$B7,ALIF_Y2018!$F:$F) -> 8817544.4 | I7: =SUMIF(ALIF_Y2019!$I:$I,$B7,ALIF_Y2019!$F:$F) -> 6590030 | J7: =SUMIF(ALIF_Y2020!$I:$I,$B7,ALIF_Y2020!$F:$F) -> 40745293 | K7: =SUMIF(ALIF_Y2021!$I:$I,$B7,ALIF_Y2021!$F:$F) -> 10651132 | L7: =SUMIF(ALIF_Y2022!$I:$I,$B7,ALIF_Y2022!$F:$F) -> 13695029 | M7: =SUMIF(ALIF_Y2023!$I:$I,$B7,ALIF_Y2023!$F:$F) -> 4063524.4 | N7: =SUMIF(ALIF_Y2024!$I:$I,$B7,ALIF_Y2024!$F:$F) -> 1103703.9 | O7: =SUMIF(ALIF_Y2025!$I:$I,$B7,ALIF_Y2025!$F:$F) -> 1510705
B8: Trade receivables | D8: =SUMIF(ALIF_Y2014!$I:$I,$B8,ALIF_Y2014!$F:$F) -> 34778327 | E8: =SUMIF(ALIF_Y2015!$I:$I,$B8,ALIF_Y2015!$F:$F) -> 35513977 | F8: =SUMIF(ALIF_Y2016!$I:$I,$B8,ALIF_Y2016!$F:$F) -> 36110502 | G8: =SUMIF(ALIF_Y2017!$I:$I,$B8,ALIF_Y2017!$F:$F) -> 35801104 | H8: =SUMIF(ALIF_Y2018!$I:$I,$B8,ALIF_Y2018!$F:$F) -> 34900866 | I8: =SUMIF(ALIF_Y2019!$I:$I,$B8,ALIF_Y2019!$F:$F) -> 40286632 | J8: =SUMIF(ALIF_Y2020!$I:$I,$B8,ALIF_Y2020!$F:$F) -> 35451877 | K8: =SUMIF(ALIF_Y2021!$I:$I,$B8,ALIF_Y2021!$F:$F) -> 59814195 | L8: =SUMIF(ALIF_Y2022!$I:$I,$B8,ALIF_Y2022!$F:$F) -> 69444422 | M8: =SUMIF(ALIF_Y2023!$I:$I,$B8,ALIF_Y2023!$F:$F) -> 32974816 | N8: =SUMIF(ALIF_Y2024!$I:$I,$B8,ALIF_Y2024!$F:$F) -> 45208932 | O8: =SUMIF(ALIF_Y2025!$I:$I,$B8,ALIF_Y2025!$F:$F) -> 34614828
B9: Prepaid expenses | D9: =SUMIF(ALIF_Y2014!$I:$I,$B9,ALIF_Y2014!$F:$F) -> 8670708.6 | E9: =SUMIF(ALIF_Y2015!$I:$I,$B9,ALIF_Y2015!$F:$F) -> 7700042.4 | F9: =SUMIF(ALIF_Y2016!$I:$I,$B9,ALIF_Y2016!$F:$F) -> 6566761.5 | G9: =SUMIF(ALIF_Y2017!$I:$I,$B9,ALIF_Y2017!$F:$F) -> 13100548 | H9: =SUMIF(ALIF_Y2018!$I:$I,$B9,ALIF_Y2018!$F:$F) -> 10942639 | I9: =SUMIF(ALIF_Y2019!$I:$I,$B9,ALIF_Y2019!$F:$F) -> 8522666 | J9: =SUMIF(ALIF_Y2020!$I:$I,$B9,ALIF_Y2020!$F:$F) -> 3692329.5 | K9: =SUMIF(ALIF_Y2021!$I:$I,$B9,ALIF_Y2021!$F:$F) -> 5210137.9 | L9: =SUMIF(ALIF_Y2022!$I:$I,$B9,ALIF_Y2022!$F:$F) -> 1107166 | M9: =SUMIF(ALIF_Y2023!$I:$I,$B9,ALIF_Y2023!$F:$F) -> 4772239.2 | N9: =SUMIF(ALIF_Y2024!$I:$I,$B9,ALIF_Y2024!$F:$F) -> 14758204 | O9: =SUMIF(ALIF_Y2025!$I:$I,$B9,ALIF_Y2025!$F:$F) -> 10384903
B10: Inventories | D10: =SUMIF(ALIF_Y2014!$I:$I,$B10,ALIF_Y2014!$F:$F) -> 34065376 | E10: =SUMIF(ALIF_Y2015!$I:$I,$B10,ALIF_Y2015!$F:$F) -> 28412734 | F10: =SUMIF(ALIF_Y2016!$I:$I,$B10,ALIF_Y2016!$F:$F) -> 31557771 | G10: =SUMIF(ALIF_Y2017!$I:$I,$B10,ALIF_Y2017!$F:$F) -> 25847131 | H10: =SUMIF(ALIF_Y2018!$I:$I,$B10,ALIF_Y2018!$F:$F) -> 65632734 | I10: =SUMIF(ALIF_Y2019!$I:$I,$B10,ALIF_Y2019!$F:$F) -> 63336468 | J10: =SUMIF(ALIF_Y2020!$I:$I,$B10,ALIF_Y2020!$F:$F) -> 45810721 | K10: =SUMIF(ALIF_Y2021!$I:$I,$B10,ALIF_Y2021!$F:$F) -> 60639675 | L10: =SUMIF(ALIF_Y2022!$I:$I,$B10,ALIF_Y2022!$F:$F) -> 93415465 | M10: =SUMIF(ALIF_Y2023!$I:$I,$B10,ALIF_Y2023!$F:$F) -> 45411605 | N10: =SUMIF(ALIF_Y2024!$I:$I,$B10,ALIF_Y2024!$F:$F) -> 59932685 | O10: =SUMIF(ALIF_Y2025!$I:$I,$B10,ALIF_Y2025!$F:$F) -> 1.1802975e+08
B11: Total current assets | D11: =SUM(D7:D10) -> 88600391 | E11: =SUM(E7:E10) -> 76096885 | F11: =SUM(F7:F10) -> 78924689 | G11: =SUM(G7:G10) -> 82006058 | H11: =SUM(H7:H10) -> 1.2029378e+08 | I11: =SUM(I7:I10) -> 1.187358e+08 | J11: =SUM(J7:J10) -> 1.2570022e+08 | K11: =SUM(K7:K10) -> 1.3631514e+08 | ... O11: =SUM(O7:O10) -> 1.6454018e+08
B13: Non-current assets
B14: Due from RP | D14: =SUMIF(ALIF_Y2014!$I:$I,$B14,ALIF_Y2014!$F:$F) -> 0 | E14: =SUMIF(ALIF_Y2015!$I:$I,$B14,ALIF_Y2015!$F:$F) -> 0 | F14: =SUMIF(ALIF_Y2016!$I:$I,$B14,ALIF_Y2016!$F:$F) -> 0 | G14: =SUMIF(ALIF_Y2017!$I:$I,$B14,ALIF_Y2017!$F:$F) -> 0 | H14: =SUMIF(ALIF_Y2018!$I:$I,$B14,ALIF_Y2018!$F:$F) -> 0 | I14: =SUMIF(ALIF_Y2019!$I:$I,$B14,ALIF_Y2019!$F:$F) -> 0 | J14: =SUMIF(ALIF_Y2020!$I:$I,$B14,ALIF_Y2020!$F:$F) -> 0 | K14: =SUMIF(ALIF_Y2021!$I:$I,$B14,ALIF_Y2021!$F:$F) -> 0 | L14: =SUMIF(ALIF_Y2022!$I:$I,$B14,ALIF_Y2022!$F:$F) -> 0 | M14: =SUMIF(ALIF_Y2023!$I:$I,$B14,ALIF_Y2023!$F:$F) -> 0 | N14: =SUMIF(ALIF_Y2024!$I:$I,$B14,ALIF_Y2024!$F:$F) -> 0 | O14: =SUMIF(ALIF_Y2025!$I:$I,$B14,ALIF_Y2025!$F:$F) -> 0
B15: Property, plant and equipment | D15: =SUMIF(ALIF_Y2014!$I:$I,$B15,ALIF_Y2014!$F:$F) -> 19388806 | E15: =SUMIF(ALIF_Y2015!$I:$I,$B15,ALIF_Y2015!$F:$F) -> 27222646 | F15: =SUMIF(ALIF_Y2016!$I:$I,$B15,ALIF_Y2016!$F:$F) -> 1.1316719e+08 | G15: =SUMIF(ALIF_Y2017!$I:$I,$B15,ALIF_Y2017!$F:$F) -> 1.160029e+08 | H15: =SUMIF(ALIF_Y2018!$I:$I,$B15,ALIF_Y2018!$F:$F) -> 1.4038536e+08 | I15: =SUMIF(ALIF_Y2019!$I:$I,$B15,ALIF_Y2019!$F:$F) -> 1.4278867e+08 | J15: =SUMIF(ALIF_Y2020!$I:$I,$B15,ALIF_Y2020!$F:$F) -> 1.3888052e+08 | K15: =SUMIF(ALIF_Y2021!$I:$I,$B15,ALIF_Y2021!$F:$F) -> 1.3563953e+08 | L15: =SUMIF(ALIF_Y2022!$I:$I,$B15,ALIF_Y2022!$F:$F) -> 1.3826324e+08 | M15: =SUMIF(ALIF_Y2023!$I:$I,$B15,ALIF_Y2023!$F:$F) -> 1.3128693e+08 | N15: =SUMIF(ALIF_Y2024!$I:$I,$B15,ALIF_Y2024!$F:$F) -> 1.3864062e+08 | O15: =SUMIF(ALIF_Y2025!$I:$I,$B15,ALIF_Y2025!$F:$F) -> 1.5813975e+08
B16: Right of use | D16: =SUMIF(ALIF_Y2014!$I:$I,$B16,ALIF_Y2014!$F:$F) -> 0 | E16: =SUMIF(ALIF_Y2015!$I:$I,$B16,ALIF_Y2015!$F:$F) -> 0 | F16: =SUMIF(ALIF_Y2016!$I:$I,$B16,ALIF_Y2016!$F:$F) -> 0 | G16: =SUMIF(ALIF_Y2017!$I:$I,$B16,ALIF_Y2017!$F:$F) -> 0 | H16: =SUMIF(ALIF_Y2018!$I:$I,$B16,ALIF_Y2018!$F:$F) -> 0 | I16: =SUMIF(ALIF_Y2019!$I:$I,$B16,ALIF_Y2019!$F:$F) -> 1995348 | J16: =SUMIF(ALIF_Y2020!$I:$I,$B16,ALIF_Y2020!$F:$F) -> 1846625.5 | K16: =SUMIF(ALIF_Y2021!$I:$I,$B16,ALIF_Y2021!$F:$F) -> 1686512.5 | L16: =SUMIF(ALIF_Y2022!$I:$I,$B16,ALIF_Y2022!$F:$F) -> 1537181.1 | M16: =SUMIF(ALIF_Y2023!$I:$I,$B16,ALIF_Y2023!$F:$F) -> 1374274.1 | N16: =SUMIF(ALIF_Y2024!$I:$I,$B16,ALIF_Y2024!$F:$F) -> 1225552.5 | O16: =SUMIF(ALIF_Y2025!$I:$I,$B16,ALIF_Y2025!$F:$F) -> 2545644.4
B17: Total non-current assets | D17: =SUM(D14:D16) -> 19388806 | E17: =SUM(E14:E16) -> 27222646 | F17: =SUM(F14:F16) -> 1.1316719e+08 | G17: =SUM(G14:G16) -> 1.160029e+08 | H17: =SUM(H14:H16) -> 1.4038536e+08 | I17: =SUM(I14:I16) -> 1.4478402e+08 | J17: =SUM(J14:J16) -> 1.4072714e+08 | K17: =SUM(K14:K16) -> 1.3732605e+08 | ... O17: =SUM(O14:O16) -> 1.6068539e+08
B19: TOTAL ASSETS | D19: =D11+D17 -> 1.079892e+08 | E19: =E11+E17 -> 1.0331953e+08 | F19: =F11+F17 -> 1.9209188e+08 | G19: =G11+G17 -> 1.9800896e+08 | H19: =H11+H17 -> 2.6067914e+08 | I19: =I11+I17 -> 2.6351982e+08 | J19: =J11+J17 -> 2.6642736e+08 | K19: =K11+K17 -> 2.7364119e+08 | ... O19: =O11+O17 -> 3.2522557e+08
B21: LIABILITIES AND SHAREHOLDERS' EQUITY
B22: Current liabilities
B23: Short-term Murabaha loans | D23: =-SUMIF(ALIF_Y2014!$I:$I,$B23,ALIF_Y2014!$F:$F) -> 24897662 | E23: =-SUMIF(ALIF_Y2015!$I:$I,$B23,ALIF_Y2015!$F:$F) -> 11975999 | F23: =-SUMIF(ALIF_Y2016!$I:$I,$B23,ALIF_Y2016!$F:$F) -> 26152571 | G23: =-SUMIF(ALIF_Y2017!$I:$I,$B23,ALIF_Y2017!$F:$F) -> 0 | H23: =-SUMIF(ALIF_Y2018!$I:$I,$B23,ALIF_Y2018!$F:$F) -> 60835098 | I23: =-SUMIF(ALIF_Y2019!$I:$I,$B23,ALIF_Y2019!$F:$F) -> 67558357 | J23: =-SUMIF(ALIF_Y2020!$I:$I,$B23,ALIF_Y2020!$F:$F) -> 87069638 | K23: =-SUMIF(ALIF_Y2021!$I:$I,$B23,ALIF_Y2021!$F:$F) -> 93444858 | L23: =-SUMIF(ALIF_Y2022!$I:$I,$B23,ALIF_Y2022!$F:$F) -> 1.2918116e+08 | M23: =-SUMIF(ALIF_Y2023!$I:$I,$B23,ALIF_Y2023!$F:$F) -> 83699243 | N23: =-SUMIF(ALIF_Y2024!$I:$I,$B23,ALIF_Y2024!$F:$F) -> 1.1139247e+08 | O23: =-SUMIF(ALIF_Y2025!$I:$I,$B23,ALIF_Y2025!$F:$F) -> 1.9339682e+08
B24: Lease liability - current portion | D24: =-SUMIF(ALIF_Y2014!$I:$I,$B24,ALIF_Y2014!$F:$F) -> 0 | E24: =-SUMIF(ALIF_Y2015!$I:$I,$B24,ALIF_Y2015!$F:$F) -> 0 | F24: =-SUMIF(ALIF_Y2016!$I:$I,$B24,ALIF_Y2016!$F:$F) -> 0 | G24: =-SUMIF(ALIF_Y2017!$I:$I,$B24,ALIF_Y2017!$F:$F) -> 0 | H24: =-SUMIF(ALIF_Y2018!$I:$I,$B24,ALIF_Y2018!$F:$F) -> 0 | I24: =-SUMIF(ALIF_Y2019!$I:$I,$B24,ALIF_Y2019!$F:$F) -> 0 | J24: =-SUMIF(ALIF_Y2020!$I:$I,$B24,ALIF_Y2020!$F:$F) -> 0 | K24: =-SUMIF(ALIF_Y2021!$I:$I,$B24,ALIF_Y2021!$F:$F) -> 0 | L24: =-SUMIF(ALIF_Y2022!$I:$I,$B24,ALIF_Y2022!$F:$F) -> 0 | M24: =-SUMIF(ALIF_Y2023!$I:$I,$B24,ALIF_Y2023!$F:$F) -> 0 | N24: =-SUMIF(ALIF_Y2024!$I:$I,$B24,ALIF_Y2024!$F:$F) -> 0 | O24: =-SUMIF(ALIF_Y2025!$I:$I,$B24,ALIF_Y2025!$F:$F) -> 0
B25: Zakat provision | D25: =-SUMIF(ALIF_Y2014!$I:$I,$B25,ALIF_Y2014!$F:$F) -> 1537200 | E25: =-SUMIF(ALIF_Y2015!$I:$I,$B25,ALIF_Y2015!$F:$F) -> 1365110 | F25: =-SUMIF(ALIF_Y2016!$I:$I,$B25,ALIF_Y2016!$F:$F) -> 1200000 | G25: =-SUMIF(ALIF_Y2017!$I:$I,$B25,ALIF_Y2017!$F:$F) -> 1119039 | H25: =-SUMIF(ALIF_Y2018!$I:$I,$B25,ALIF_Y2018!$F:$F) -> 1150000.5 | I25: =-SUMIF(ALIF_Y2019!$I:$I,$B25,ALIF_Y2019!$F:$F) -> 983057 | J25: =-SUMIF(ALIF_Y2020!$I:$I,$B25,ALIF_Y2020!$F:$F) -> 644386 | K25: =-SUMIF(ALIF_Y2021!$I:$I,$B25,ALIF_Y2021!$F:$F) -> 0 | L25: =-SUMIF(ALIF_Y2022!$I:$I,$B25,ALIF_Y2022!$F:$F) -> 0 | M25: =-SUMIF(ALIF_Y2023!$I:$I,$B25,ALIF_Y2023!$F:$F) -> 968047.97 | N25: =-SUMIF(ALIF_Y2024!$I:$I,$B25,ALIF_Y2024!$F:$F) -> 0 | O25: =-SUMIF(ALIF_Y2025!$I:$I,$B25,ALIF_Y2025!$F:$F) -> 0
B26: Tade payables and Accuals & other credit balances | D26: =-SUMIF(ALIF_Y2014!$I:$I,$B26,ALIF_Y2014!$F:$F) -> 2507261 | E26: =-SUMIF(ALIF_Y2015!$I:$I,$B26,ALIF_Y2015!$F:$F) -> 6283439 | F26: =-SUMIF(ALIF_Y2016!$I:$I,$B26,ALIF_Y2016!$F:$F) -> 5444461 | G26: =-SUMIF(ALIF_Y2017!$I:$I,$B26,ALIF_Y2017!$F:$F) -> 6914829 | H26: =-SUMIF(ALIF_Y2018!$I:$I,$B26,ALIF_Y2018!$F:$F) -> 8339707 | I26: =-SUMIF(ALIF_Y2019!$I:$I,$B26,ALIF_Y2019!$F:$F) -> 6947242 | J26: =-SUMIF(ALIF_Y2020!$I:$I,$B26,ALIF_Y2020!$F:$F) -> 9755293 | K26: =-SUMIF(ALIF_Y2021!$I:$I,$B26,ALIF_Y2021!$F:$F) -> 6517602.2 | L26: =-SUMIF(ALIF_Y2022!$I:$I,$B26,ALIF_Y2022!$F:$F) -> 6436834.9 | M26: =-SUMIF(ALIF_Y2023!$I:$I,$B26,ALIF_Y2023!$F:$F) -> 6572651 | N26: =-SUMIF(ALIF_Y2024!$I:$I,$B26,ALIF_Y2024!$F:$F) -> 13430273 | O26: =-SUMIF(ALIF_Y2025!$I:$I,$B26,ALIF_Y2025!$F:$F) -> 24407376
B27: Total current liabilities | D27: =SUM(D23:D26) -> 28942123 | E27: =SUM(E23:E26) -> 19624548 | F27: =SUM(F23:F26) -> 32797032 | G27: =SUM(G23:G26) -> 8033868 | H27: =SUM(H23:H26) -> 70324806 | I27: =SUM(I23:I26) -> 75488656 | J27: =SUM(J23:J26) -> 97469317 | K27: =SUM(K23:K26) -> 99962460 | ... O27: =SUM(O23:O26) -> 2.1780419e+08
B29: Non-current liabilities
B30: Lease liabilities non-current | D30: =-SUMIF(ALIF_Y2014!$I:$I,$B30,ALIF_Y2014!$F:$F) -> 0 | E30: =-SUMIF(ALIF_Y2015!$I:$I,$B30,ALIF_Y2015!$F:$F) -> 0 | F30: =-SUMIF(ALIF_Y2016!$I:$I,$B30,ALIF_Y2016!$F:$F) -> 0 | G30: =-SUMIF(ALIF_Y2017!$I:$I,$B30,ALIF_Y2017!$F:$F) -> 0 | H30: =-SUMIF(ALIF_Y2018!$I:$I,$B30,ALIF_Y2018!$F:$F) -> 0 | I30: =-SUMIF(ALIF_Y2019!$I:$I,$B30,ALIF_Y2019!$F:$F) -> 1874374 | J30: =-SUMIF(ALIF_Y2020!$I:$I,$B30,ALIF_Y2020!$F:$F) -> 1823243.6 | K30: =-SUMIF(ALIF_Y2021!$I:$I,$B30,ALIF_Y2021!$F:$F) -> 1711827 | L30: =-SUMIF(ALIF_Y2022!$I:$I,$B30,ALIF_Y2022!$F:$F) -> 1596797 | M30: =-SUMIF(ALIF_Y2023!$I:$I,$B30,ALIF_Y2023!$F:$F) -> 1505845.1 | N30: =-SUMIF(ALIF_Y2024!$I:$I,$B30,ALIF_Y2024!$F:$F) -> 1399831.1 | O30: =-SUMIF(ALIF_Y2025!$I:$I,$B30,ALIF_Y2025!$F:$F) -> 2585822
B31: Due to related parties | D31: =-SUMIF(ALIF_Y2014!$I:$I,$B31,ALIF_Y2014!$F:$F) -> 0 | E31: =-SUMIF(ALIF_Y2015!$I:$I,$B31,ALIF_Y2015!$F:$F) -> 0 | F31: =-SUMIF(ALIF_Y2016!$I:$I,$B31,ALIF_Y2016!$F:$F) -> 0 | G31: =-SUMIF(ALIF_Y2017!$I:$I,$B31,ALIF_Y2017!$F:$F) -> 31714782 | H31: =-SUMIF(ALIF_Y2018!$I:$I,$B31,ALIF_Y2018!$F:$F) -> 7696296.2 | I31: =-SUMIF(ALIF_Y2019!$I:$I,$B31,ALIF_Y2019!$F:$F) -> 502289.05 | J31: =-SUMIF(ALIF_Y2020!$I:$I,$B31,ALIF_Y2020!$F:$F) -> 277914.95 | K31: =-SUMIF(ALIF_Y2021!$I:$I,$B31,ALIF_Y2021!$F:$F) -> -146154.66 | L31: =-SUMIF(ALIF_Y2022!$I:$I,$B31,ALIF_Y2022!$F:$F) -> 1098996.6 | M31: =-SUMIF(ALIF_Y2023!$I:$I,$B31,ALIF_Y2023!$F:$F) -> -16923360 | N31: =-SUMIF(ALIF_Y2024!$I:$I,$B31,ALIF_Y2024!$F:$F) -> 16103933 | O31: =-SUMIF(ALIF_Y2025!$I:$I,$B31,ALIF_Y2025!$F:$F) -> 30600617
B32: End-of-service indemnities | D32: =-SUMIF(ALIF_Y2014!$I:$I,$B32,ALIF_Y2014!$F:$F) -> 2925857.7 | E32: =-SUMIF(ALIF_Y2015!$I:$I,$B32,ALIF_Y2015!$F:$F) -> 2992687.9 | F32: =-SUMIF(ALIF_Y2016!$I:$I,$B32,ALIF_Y2016!$F:$F) -> 4649375 | G32: =-SUMIF(ALIF_Y2017!$I:$I,$B32,ALIF_Y2017!$F:$F) -> 4847761 | H32: =-SUMIF(ALIF_Y2018!$I:$I,$B32,ALIF_Y2018!$F:$F) -> 4633898 | I32: =-SUMIF(ALIF_Y2019!$I:$I,$B32,ALIF_Y2019!$F:$F) -> 4294641 | J32: =-SUMIF(ALIF_Y2020!$I:$I,$B32,ALIF_Y2020!$F:$F) -> 4405440 | K32: =-SUMIF(ALIF_Y2021!$I:$I,$B32,ALIF_Y2021!$F:$F) -> 3891962 | L32: =-SUMIF(ALIF_Y2022!$I:$I,$B32,ALIF_Y2022!$F:$F) -> 4434767 | M32: =-SUMIF(ALIF_Y2023!$I:$I,$B32,ALIF_Y2023!$F:$F) -> 5799270.3 | N32: =-SUMIF(ALIF_Y2024!$I:$I,$B32,ALIF_Y2024!$F:$F) -> 3409950.9 | O32: =-SUMIF(ALIF_Y2025!$I:$I,$B32,ALIF_Y2025!$F:$F) -> 4431984.9
B33: Provision for evacuation | D33: =-SUMIF(ALIF_Y2014!$I:$I,$B33,ALIF_Y2014!$F:$F) -> 0 | E33: =-SUMIF(ALIF_Y2015!$I:$I,$B33,ALIF_Y2015!$F:$F) -> 0 | F33: =-SUMIF(ALIF_Y2016!$I:$I,$B33,ALIF_Y2016!$F:$F) -> 0 | G33: =-SUMIF(ALIF_Y2017!$I:$I,$B33,ALIF_Y2017!$F:$F) -> 0 | H33: =-SUMIF(ALIF_Y2018!$I:$I,$B33,ALIF_Y2018!$F:$F) -> 4000000 | I33: =-SUMIF(ALIF_Y2019!$I:$I,$B33,ALIF_Y2019!$F:$F) -> 4120000 | J33: =-SUMIF(ALIF_Y2020!$I:$I,$B33,ALIF_Y2020!$F:$F) -> 4214760 | K33: =-SUMIF(ALIF_Y2021!$I:$I,$B33,ALIF_Y2021!$F:$F) -> 4329893.2 | L33: =-SUMIF(ALIF_Y2022!$I:$I,$B33,ALIF_Y2022!$F:$F) -> 4426579.7 | M33: =-SUMIF(ALIF_Y2023!$I:$I,$B33,ALIF_Y2023!$F:$F) -> 4698371.7 | N33: =-SUMIF(ALIF_Y2024!$I:$I,$B33,ALIF_Y2024!$F:$F) -> 4807655.8 | O33: =-SUMIF(ALIF_Y2025!$I:$I,$B33,ALIF_Y2025!$F:$F) -> 4862172.9
B34: Total non-current liabilities | D34: =SUM(D30:D33) -> 2925857.7 | E34: =SUM(E30:E33) -> 2992687.9 | F34: =SUM(F30:F33) -> 4649375 | G34: =SUM(G30:G33) -> 36562543 | H34: =SUM(H30:H33) -> 16330194 | I34: =SUM(I30:I33) -> 10791304 | J34: =SUM(J30:J33) -> 10721359 | K34: =SUM(K30:K33) -> 9787527.6 | ... O34: =SUM(O30:O33) -> 42480597
B35: TOTAL LIABILITES | D35: =D34+D27 -> 31867981 | E35: =E34+E27 -> 22617235 | F35: =F34+F27 -> 37446407 | G35: =G34+G27 -> 44596411 | H35: =H34+H27 -> 86655000 | I35: =I34+I27 -> 86279960 | J35: =J34+J27 -> 1.0819068e+08 | K35: =K34+K27 -> 1.0974999e+08 | ... O35: =O34+O27 -> 2.6028479e+08
B37: Shareholders' equity
B38: Share capital | D38: =-SUMIF(ALIF_Y2014!$I:$I,$B38,ALIF_Y2014!$F:$F) -> 33568250 | E38: =-SUMIF(ALIF_Y2015!$I:$I,$B38,ALIF_Y2015!$F:$F) -> 33568250 | F38: =-SUMIF(ALIF_Y2016!$I:$I,$B38,ALIF_Y2016!$F:$F) -> 33568250 | G38: =-SUMIF(ALIF_Y2017!$I:$I,$B38,ALIF_Y2017!$F:$F) -> 33568250 | H38: =-SUMIF(ALIF_Y2018!$I:$I,$B38,ALIF_Y2018!$F:$F) -> 33568250 | I38: =-SUMIF(ALIF_Y2019!$I:$I,$B38,ALIF_Y2019!$F:$F) -> 33568250 | J38: =-SUMIF(ALIF_Y2020!$I:$I,$B38,ALIF_Y2020!$F:$F) -> 35335000 | K38: =-SUMIF(ALIF_Y2021!$I:$I,$B38,ALIF_Y2021!$F:$F) -> 35335000 | L38: =-SUMIF(ALIF_Y2022!$I:$I,$B38,ALIF_Y2022!$F:$F) -> 35335000 | M38: =-SUMIF(ALIF_Y2023!$I:$I,$B38,ALIF_Y2023!$F:$F) -> 35335000 | N38: =-SUMIF(ALIF_Y2024!$I:$I,$B38,ALIF_Y2024!$F:$F) -> 35335000 | O38: =-SUMIF(ALIF_Y2025!$I:$I,$B38,ALIF_Y2025!$F:$F) -> 35335000
B39: Statutory reserve | D39: =-SUMIF(ALIF_Y2014!$I:$I,$B39,ALIF_Y2014!$F:$F) -> 3512480 | E39: =-SUMIF(ALIF_Y2015!$I:$I,$B39,ALIF_Y2015!$F:$F) -> 4856327 | F39: =-SUMIF(ALIF_Y2016!$I:$I,$B39,ALIF_Y2016!$F:$F) -> 5627620 | G39: =-SUMIF(ALIF_Y2017!$I:$I,$B39,ALIF_Y2017!$F:$F) -> 5627620 | H39: =-SUMIF(ALIF_Y2018!$I:$I,$B39,ALIF_Y2018!$F:$F) -> 6053397 | I39: =-SUMIF(ALIF_Y2019!$I:$I,$B39,ALIF_Y2019!$F:$F) -> 6684528 | J39: =-SUMIF(ALIF_Y2020!$I:$I,$B39,ALIF_Y2020!$F:$F) -> 6684528 | K39: =-SUMIF(ALIF_Y2021!$I:$I,$B39,ALIF_Y2021!$F:$F) -> 7202958 | L39: =-SUMIF(ALIF_Y2022!$I:$I,$B39,ALIF_Y2022!$F:$F) -> 7846137 | M39: =-SUMIF(ALIF_Y2023!$I:$I,$B39,ALIF_Y2023!$F:$F) -> 7846137 | N39: =-SUMIF(ALIF_Y2024!$I:$I,$B39,ALIF_Y2024!$F:$F) -> 7846137 | O39: =-SUMIF(ALIF_Y2025!$I:$I,$B39,ALIF_Y2025!$F:$F) -> 7846137
B40: Retained earnings | D40: =-SUMIF(ALIF_Y2014!$I:$I,$B40,ALIF_Y2014!$F:$F)-SUMIF(ALIF_Y2014!$G:$G,"IS",ALIF_Y2014!$F:$F) -> 35437048 | E40: =-SUMIF(ALIF_Y2015!$I:$I,$B40,ALIF_Y2015!$F:$F)-SUMIF(ALIF_Y2015!$G:$G,"IS",ALIF_Y2015!$F:$F) -> 40958807 | F40: =-SUMIF(ALIF_Y2016!$I:$I,$B40,ALIF_Y2016!$F:$F)-SUMIF(ALIF_Y2016!$G:$G,"IS",ALIF_Y2016!$F:$F) -> 25963821 | G40: =-SUMIF(ALIF_Y2017!$I:$I,$B40,ALIF_Y2017!$F:$F)-SUMIF(ALIF_Y2017!$G:$G,"IS",ALIF_Y2017!$F:$F) -> 25089527 | H40: =-SUMIF(ALIF_Y2018!$I:$I,$B40,ALIF_Y2018!$F:$F)-SUMIF(ALIF_Y2018!$G:$G,"IS",ALIF_Y2018!$F:$F) -> 31662134 | I40: =-SUMIF(ALIF_Y2019!$I:$I,$B40,ALIF_Y2019!$F:$F)-SUMIF(ALIF_Y2019!$G:$G,"IS",ALIF_Y2019!$F:$F) -> 33642416 | J40: =-SUMIF(ALIF_Y2020!$I:$I,$B40,ALIF_Y2020!$F:$F)-SUMIF(ALIF_Y2020!$G:$G,"IS",ALIF_Y2020!$F:$F) -> 12723944 | K40: =-SUMIF(ALIF_Y2021!$I:$I,$B40,ALIF_Y2021!$F:$F)-SUMIF(ALIF_Y2021!$G:$G,"IS",ALIF_Y2021!$F:$F) -> 17758545 | L40: =-SUMIF(ALIF_Y2022!$I:$I,$B40,ALIF_Y2022!$F:$F)-SUMIF(ALIF_Y2022!$G:$G,"IS",ALIF_Y2022!$F:$F) -> 24425366 | M40: =-SUMIF(ALIF_Y2023!$I:$I,$B40,ALIF_Y2023!$F:$F)-SUMIF(ALIF_Y2023!$G:$G,"IS",ALIF_Y2023!$F:$F) -> -11949183 | N40: =-SUMIF(ALIF_Y2024!$I:$I,$B40,ALIF_Y2024!$F:$F)-SUMIF(ALIF_Y2024!$G:$G,"IS",ALIF_Y2024!$F:$F) -> -30717238 | O40: =-SUMIF(ALIF_Y2025!$I:$I,$B40,ALIF_Y2025!$F:$F)-SUMIF(ALIF_Y2025!$G:$G,"IS",ALIF_Y2025!$F:$F) -> -78929334
B41: Additional contribution from shareholders | D41: =-SUMIF(ALIF_Y2014!$I:$I,$B41,ALIF_Y2014!$F:$F) -> 0 | E41: =-SUMIF(ALIF_Y2015!$I:$I,$B41,ALIF_Y2015!$F:$F) -> 0 | F41: =-SUMIF(ALIF_Y2016!$I:$I,$B41,ALIF_Y2016!$F:$F) -> 85866130 | G41: =-SUMIF(ALIF_Y2017!$I:$I,$B41,ALIF_Y2017!$F:$F) -> 85866130 | H41: =-SUMIF(ALIF_Y2018!$I:$I,$B41,ALIF_Y2018!$F:$F) -> 1.0225532e+08 | I41: =-SUMIF(ALIF_Y2019!$I:$I,$B41,ALIF_Y2019!$F:$F) -> 1.0225532e+08 | J41: =-SUMIF(ALIF_Y2020!$I:$I,$B41,ALIF_Y2020!$F:$F) -> 1.0225532e+08 | K41: =-SUMIF(ALIF_Y2021!$I:$I,$B41,ALIF_Y2021!$F:$F) -> 1.0225532e+08 | L41: =-SUMIF(ALIF_Y2022!$I:$I,$B41,ALIF_Y2022!$F:$F) -> 1.0225532e+08 | M41: =-SUMIF(ALIF_Y2023!$I:$I,$B41,ALIF_Y2023!$F:$F) -> 1.0225532e+08 | N41: =-SUMIF(ALIF_Y2024!$I:$I,$B41,ALIF_Y2024!$F:$F) -> 1.0225532e+08 | O41: =-SUMIF(ALIF_Y2025!$I:$I,$B41,ALIF_Y2025!$F:$F) -> 1.0225532e+08
B42: Total shareholders’ equity | D42: =SUM(D38:D41) -> 72517778 | E42: =SUM(E38:E41) -> 79383384 | F42: =SUM(F38:F41) -> 1.5102582e+08 | G42: =SUM(G38:G41) -> 1.5015153e+08 | H42: =SUM(H38:H41) -> 1.735391e+08 | I42: =SUM(I38:I41) -> 1.7615051e+08 | J42: =SUM(J38:J41) -> 1.5699879e+08 | K42: =SUM(K38:K41) -> 1.6255182e+08 | ... O42: =SUM(O38:O41) -> 66507118
B44: TOTAL LIABILITIES AND EQUITY | D44: =D27+D34+D42 -> 1.0438576e+08 | E44: =E27+E34+E42 -> 1.0200062e+08 | F44: =F27+F34+F42 -> 1.8847223e+08 | G44: =G27+G34+G42 -> 1.9474794e+08 | H44: =H27+H34+H42 -> 2.601941e+08 | I44: =I27+I34+I42 -> 2.6243047e+08 | J44: =J27+J34+J42 -> 2.6518946e+08 | K44: =K27+K34+K42 -> 2.7230181e+08 | ... O44: =O27+O34+O42 -> 3.2679191e+08
D46: =D44-D19 -> -3603438.5 | E46: =E44-E19 -> -1318911.2 | F46: =F44-F19 -> -3619649 | G46: =G44-G19 -> -3261022.8 | H46: =H44-H19 -> -485044.33 | I46: =I44-I19 -> -1089346.1 | J46: =J44-J19 -> -1237901.3 | K46: =K44-K19 -> -1339380.2 | ... O46: =O44-O19 -> 1566334.4
B48: Working capital | D48: =D11-D27 -> 59658268 | E48: =E11-E27 -> 56472337 | F48: =F11-F27 -> 46127657 | G48: =G11-G27 -> 73972190 | H48: =H11-H27 -> 49968978 | I48: =I11-I27 -> 43247140 | J48: =J11-J27 -> 28230903 | K48: =K11-K27 -> 36352680 | ... O48: =O11-O27 -> -53264010
B49: Current ratio | D49: =D11/D27 -> 3.0612955 | E49: =E11/E27 -> 3.8776377 | F49: =F11/F27 -> 2.4064583 | G49: =G11/G27 -> 10.207544 | H49: =H11/H27 -> 1.7105455 | I49: =I11/I27 -> 1.5728959 | J49: =J11/J27 -> 1.2896389 | K49: =K11/K27 -> 1.3636633 | ... O49: =O11/O27 -> 0.75545003
B50: Leverage ratio | D50: =D35/D42 -> 0.4394506 | E50: =E35/E42 -> 0.28491146 | F50: =F35/F42 -> 0.24794705 | G50: =G35/G42 -> 0.29700937 | H50: =H35/H42 -> 0.49933993 | I50: =I35/I42 -> 0.48980818 | J50: =J35/J42 -> 0.68911791 | K50: =K35/K42 -> 0.67516924 | ... O50: =O35/O42 -> 3.9136381
B53: Days Sales Outstanding | D53: =D8/'P&L_2014-2025'!C8*365 -> 94.749388 | E53: =E8/'P&L_2014-2025'!D8*365 -> 118.44033 | F53: =F8/'P&L_2014-2025'!E8*365 -> 150.17303 | G53: =G8/'P&L_2014-2025'!F8*365 -> 140.39105 | H53: =H8/'P&L_2014-2025'!G8*365 -> 118.59988 | I53: =I8/'P&L_2014-2025'!H8*365 -> 100.66022 | J53: =J8/'P&L_2014-2025'!I8*365 -> 102.20889 | K53: =K8/'P&L_2014-2025'!J8*365 -> 119.5506 | ... O53: =O8/'P&L_2014-2025'!N8*365 -> 81.568562
B54: Days Inventory Outstanding | D54: =D10/'P&L_2014-2025'!C22*365 -> 116.49164 | E54: =E10/'P&L_2014-2025'!D22*365 -> 119.48181 | F54: =F10/'P&L_2014-2025'!E22*365 -> 157.6427 | G54: =G10/'P&L_2014-2025'!F22*365 -> 118.93276 | H54: =H10/'P&L_2014-2025'!G22*365 -> 269.03537 | I54: =I10/'P&L_2014-2025'!H22*365 -> 185.58915 | J54: =J10/'P&L_2014-2025'!I22*365 -> 135.73794 | K54: =K10/'P&L_2014-2025'!J22*365 -> 139.52277 | ... O54: =O10/'P&L_2014-2025'!N22*365 -> 274.69933
B55: Days Payable Outstanding | D55: =D26/'P&L_2014-2025'!C22*365 -> 8.5739532 | E55: =E26/'P&L_2014-2025'!D22*365 -> 26.423245 | F55: =F26/'P&L_2014-2025'!E22*365 -> 27.19709 | G55: =G26/'P&L_2014-2025'!F22*365 -> 31.817835 | H55: =H26/'P&L_2014-2025'!G22*365 -> 34.185323 | I55: =I26/'P&L_2014-2025'!H22*365 -> 20.356878 | J55: =J26/'P&L_2014-2025'!I22*365 -> 28.905099 | K55: =K26/'P&L_2014-2025'!J22*365 -> 14.996023 | ... O55: =O26/'P&L_2014-2025'!N22*365 -> 56.805084
B56: Working Capital Cycle | D56: =D53+D54-D55 -> 202.66707 | E56: =E53+E54-E55 -> 211.49889 | F56: =F53+F54-F55 -> 280.61864 | G56: =G53+G54-G55 -> 227.50598 | H56: =H53+H54-H55 -> 353.44993 | I56: =I53+I54-I55 -> 265.89249 | J56: =J53+J54-J55 -> 209.04173 | K56: =K53+K54-K55 -> 244.07735 | ... O56: =O53+O54-O55 -> 299.46281

Sheet Charts_BS

Sheet Charts_P&L

Sheet P&L_2014-2025
A1: AIMS INDUSTRIAL
A2: Profit & Loss
A3: Y2014 - Y2025 | C3: 2 | D3: 3 | E3: 4 | F3: 5 | G3: 6 | H3: 7 | I3: 8 | J3: 9 | K3: 10 | L3: 11
C5: Y2014 | D5: Y2015 | E5: Y2016 | F5: Y2017 | G5: Y2018 | H5: Y2019 | I5: Y2020 | J5: Y2021 | K5: Y2022 | L5: Y2023 | M5: Y2024 | N5: Y2025
A6: Tons | C6: =C8/C7 -> 23036.583 | D6: 31426 | E6: 32014 | F6: 29528 | G6: 28812 | H6: 38145 | I6: 36751 | J6: 37605 | K6: 37298 | L6: 24159 | M6: 35702 | N6: 45159
A7: Price | C7: 5815.7681 | D7: =D8/D6 -> 3482.599 | E7: =E8/E6 -> 2741.5394 | F7: =F8/F6 -> 3152.215 | G7: =G8/G6 -> 3727.9615 | H7: =H8/H6 -> 3829.6435 | I7: =I8/I6 -> 3444.8813 | J7: =J8/J6 -> 4856.2358 | K7: =K8/K6 -> 5951.1168 | ... N7: =N8/N6 -> 3429.951
A8: Sales | C8: =-SUMIF(ALIF_Y2014!I:I,A8,ALIF_Y2014!F:F) -> 1.3397542e+08 | D8: =-SUMIF(ALIF_Y2015!I:I,A8,ALIF_Y2015!F:F) -> 1.0944416e+08 | E8: =-SUMIF(ALIF_Y2016!I:I,A8,ALIF_Y2016!F:F) -> 87767643 | F8: =-SUMIF(ALIF_Y2017!I:I,A8,ALIF_Y2017!F:F) -> 93078605 | G8: =-SUMIF(ALIF_Y2018!I:I,A8,ALIF_Y2018!F:F) -> 1.0741003e+08 | H8: =-SUMIF(ALIF_Y2019!I:I,A8,ALIF_Y2019!F:F) -> 1.4608175e+08 | I8: =-SUMIF(ALIF_Y2020!I:I,A8,ALIF_Y2020!F:F) -> 1.2660283e+08 | J8: =-SUMIF(ALIF_Y2021!I:I,A8,ALIF_Y2021!F:F) -> 1.8261875e+08 | K8: =-SUMIF(ALIF_Y2022!I:I,A8,ALIF_Y2022!F:F) -> 2.2196476e+08 | L8: =-SUMIF(ALIF_Y2023!I:I,A8,ALIF_Y2023!F:F) -> 1.0420051e+08 | M8: =-SUMIF(ALIF_Y2024!I:I,A8,ALIF_Y2024!F:F) -> 1.3521087e+08 | N8: =-SUMIF(ALIF_Y2025!I:I,A8,ALIF_Y2025!F:F) -> 1.5489316e+08
A10: Raw materials | C10: =SUMIF(ALIF_Y2014!I:I,A10,ALIF_Y2014!F:F) -> 81941049 | D10: =SUMIF(ALIF_Y2015!I:I,A10,ALIF_Y2015!F:F) -> 65904068 | E10: =SUMIF(ALIF_Y2016!I:I,A10,ALIF_Y2016!F:F) -> 55179706 | F10: =SUMIF(ALIF_Y2017!I:I,A10,ALIF_Y2017!F:F) -> 58214236 | G10: =SUMIF(ALIF_Y2018!I:I,A10,ALIF_Y2018!F:F) -> 75159713 | H10: =SUMIF(ALIF_Y2019!I:I,A10,ALIF_Y2019!F:F) -> 1.0180015e+08 | I10: =SUMIF(ALIF_Y2020!I:I,A10,ALIF_Y2020!F:F) -> 1.0098846e+08 | J10: =SUMIF(ALIF_Y2021!I:I,A10,ALIF_Y2021!F:F) -> 1.2845715e+08 | K10: =SUMIF(ALIF_Y2022!I:I,A10,ALIF_Y2022!F:F) -> 1.5899362e+08 | L10: =SUMIF(ALIF_Y2023!I:I,A10,ALIF_Y2023!F:F) -> 86519534 | M10: =SUMIF(ALIF_Y2024!I:I,A10,ALIF_Y2024!F:F) -> 1.0646571e+08 | N10: =SUMIF(ALIF_Y2025!I:I,A10,ALIF_Y2025!F:F) -> 1.1426246e+08
A11: Direct Labor | C11: =SUMIF(ALIF_Y2014!I:I,A11,ALIF_Y2014!F:F) -> 10110578 | D11: =SUMIF(ALIF_Y2015!I:I,A11,ALIF_Y2015!F:F) -> 4964584.6 | E11: =SUMIF(ALIF_Y2016!I:I,A11,ALIF_Y2016!F:F) -> 2752188.9 | F11: =SUMIF(ALIF_Y2017!I:I,A11,ALIF_Y2017!F:F) -> 8076733.4 | G11: =SUMIF(ALIF_Y2018!I:I,A11,ALIF_Y2018!F:F) -> 4690498.9 | H11: =SUMIF(ALIF_Y2019!I:I,A11,ALIF_Y2019!F:F) -> 4737194 | I11: =SUMIF(ALIF_Y2020!I:I,A11,ALIF_Y2020!F:F) -> 4616680.1 | J11: =SUMIF(ALIF_Y2021!I:I,A11,ALIF_Y2021!F:F) -> 6113549 | K11: =SUMIF(ALIF_Y2022!I:I,A11,ALIF_Y2022!F:F) -> 7571448.7 | L11: =SUMIF(ALIF_Y2023!I:I,A11,ALIF_Y2023!F:F) -> 4537898.5 | M11: =SUMIF(ALIF_Y2024!I:I,A11,ALIF_Y2024!F:F) -> 5342594.8 | N11: =SUMIF(ALIF_Y2025!I:I,A11,ALIF_Y2025!F:F) -> 14662273
A12: Freight expenses | C12: =SUMIF(ALIF_Y2014!I:I,A12,ALIF_Y2014!F:F) -> 2673874.8 | D12: =SUMIF(ALIF_Y2015!I:I,A12,ALIF_Y2015!F:F) -> 2734734.3 | E12: =SUMIF(ALIF_Y2016!I:I,A12,ALIF_Y2016!F:F) -> 2666816.5 | F12: =SUMIF(ALIF_Y2017!I:I,A12,ALIF_Y2017!F:F) -> 2233233.6 | G12: =SUMIF(ALIF_Y2018!I:I,A12,ALIF_Y2018!F:F) -> 3256415.5 | H12: =SUMIF(ALIF_Y2019!I:I,A12,ALIF_Y2019!F:F) -> 3483379.7 | I12: =SUMIF(ALIF_Y2020!I:I,A12,ALIF_Y2020!F:F) -> 2692057.3 | J12: =SUMIF(ALIF_Y2021!I:I,A12,ALIF_Y2021!F:F) -> 2800211.2 | K12: =SUMIF(ALIF_Y2022!I:I,A12,ALIF_Y2022!F:F) -> 2728489.4 | L12: =SUMIF(ALIF_Y2023!I:I,A12,ALIF_Y2023!F:F) -> 2712576.4 | M12: =SUMIF(ALIF_Y2024!I:I,A12,ALIF_Y2024!F:F) -> 2003043.6 | N12: =SUMIF(ALIF_Y2025!I:I,A12,ALIF_Y2025!F:F) -> 2233578.2
A13: Customs duties and clearances | C13: =SUMIF(ALIF_Y2014!I:I,A13,ALIF_Y2014!F:F) -> 0 | D13: =SUMIF(ALIF_Y2015!I:I,A13,ALIF_Y2015!F:F) -> 0 | E13: =SUMIF(ALIF_Y2016!I:I,A13,ALIF_Y2016!F:F) -> 0 | F13: =SUMIF(ALIF_Y2017!I:I,A13,ALIF_Y2017!F:F) -> 0 | G13: =SUMIF(ALIF_Y2018!I:I,A13,ALIF_Y2018!F:F) -> 0 | H13: =SUMIF(ALIF_Y2019!I:I,A13,ALIF_Y2019!F:F) -> 0 | I13: =SUMIF(ALIF_Y2020!I:I,A13,ALIF_Y2020!F:F) -> 0 | J13: =SUMIF(ALIF_Y2021!I:I,A13,ALIF_Y2021!F:F) -> 0 | K13: =SUMIF(ALIF_Y2022!I:I,A13,ALIF_Y2022!F:F) -> 0 | L13: =SUMIF(ALIF_Y2023!I:I,A13,ALIF_Y2023!F:F) -> 0 | M13: =SUMIF(ALIF_Y2024!I:I,A13,ALIF_Y2024!F:F) -> 0 | N13: =SUMIF(ALIF_Y2025!I:I,A13,ALIF_Y2025!F:F) -> -1.3969839e-09
A14: Depreciation - Machines | C14: =SUMIF(ALIF_Y2014!I:I,A14,ALIF_Y2014!F:F) -> 2954190.5 | D14: =SUMIF(ALIF_Y2015!I:I,A14,ALIF_Y2015!F:F) -> 3165403.4 | E14: =SUMIF(ALIF_Y2016!I:I,A14,ALIF_Y2016!F:F) -> 3435007.7 | F14: =SUMIF(ALIF_Y2017!I:I,A14,ALIF_Y2017!F:F) -> 3533037.4 | G14: =SUMIF(ALIF_Y2018!I:I,A14,ALIF_Y2018!F:F) -> 2198099 | H14: =SUMIF(ALIF_Y2019!I:I,A14,ALIF_Y2019!F:F) -> 3638104.1 | I14: =SUMIF(ALIF_Y2020!I:I,A14,ALIF_Y2020!F:F) -> 3256640.8 | J14: =SUMIF(ALIF_Y2021!I:I,A14,ALIF_Y2021!F:F) -> 3446969.6 | K14: =SUMIF(ALIF_Y2022!I:I,A14,ALIF_Y2022!F:F) -> 3787622.1 | L14: =SUMIF(ALIF_Y2023!I:I,A14,ALIF_Y2023!F:F) -> 3892923.1 | M14: =SUMIF(ALIF_Y2024!I:I,A14,ALIF_Y2024!F:F) -> 4522894.6 | N14: =SUMIF(ALIF_Y2025!I:I,A14,ALIF_Y2025!F:F) -> 7355690.5
A15: Overhead - Labor Cost | C15: =SUMIF(ALIF_Y2014!I:I,A15,ALIF_Y2014!F:F) -> 2434320.9 | D15: =SUMIF(ALIF_Y2015!I:I,A15,ALIF_Y2015!F:F) -> 2420064 | E15: =SUMIF(ALIF_Y2016!I:I,A15,ALIF_Y2016!F:F) -> 2254831.1 | F15: =SUMIF(ALIF_Y2017!I:I,A15,ALIF_Y2017!F:F) -> 2034286.4 | G15: =SUMIF(ALIF_Y2018!I:I,A15,ALIF_Y2018!F:F) -> 1095147.3 | H15: =SUMIF(ALIF_Y2019!I:I,A15,ALIF_Y2019!F:F) -> 3949079.1 | I15: =SUMIF(ALIF_Y2020!I:I,A15,ALIF_Y2020!F:F) -> 4120005 | J15: =SUMIF(ALIF_Y2021!I:I,A15,ALIF_Y2021!F:F) -> 6548586.4 | K15: =SUMIF(ALIF_Y2022!I:I,A15,ALIF_Y2022!F:F) -> 7463313.9 | L15: =SUMIF(ALIF_Y2023!I:I,A15,ALIF_Y2023!F:F) -> 5122044.2 | M15: =SUMIF(ALIF_Y2024!I:I,A15,ALIF_Y2024!F:F) -> 4990962.7 | N15: =SUMIF(ALIF_Y2025!I:I,A15,ALIF_Y2025!F:F) -> 2551484.3
A16: Overhead - Consumables & SP | C16: =SUMIF(ALIF_Y2014!I:I,A16,ALIF_Y2014!F:F) -> 3476434.1 | D16: =SUMIF(ALIF_Y2015!I:I,A16,ALIF_Y2015!F:F) -> 4063793.3 | E16: =SUMIF(ALIF_Y2016!I:I,A16,ALIF_Y2016!F:F) -> 3017957.2 | F16: =SUMIF(ALIF_Y2017!I:I,A16,ALIF_Y2017!F:F) -> 2258622.4 | G16: =SUMIF(ALIF_Y2018!I:I,A16,ALIF_Y2018!F:F) -> 1475017.7 | H16: =SUMIF(ALIF_Y2019!I:I,A16,ALIF_Y2019!F:F) -> 3632906.7 | I16: =SUMIF(ALIF_Y2020!I:I,A16,ALIF_Y2020!F:F) -> 4290617.2 | J16: =SUMIF(ALIF_Y2021!I:I,A16,ALIF_Y2021!F:F) -> 6410977.4 | K16: =SUMIF(ALIF_Y2022!I:I,A16,ALIF_Y2022!F:F) -> 9548411.9 | L16: =SUMIF(ALIF_Y2023!I:I,A16,ALIF_Y2023!F:F) -> 4461814.3 | M16: =SUMIF(ALIF_Y2024!I:I,A16,ALIF_Y2024!F:F) -> 2688304.1 | N16: =SUMIF(ALIF_Y2025!I:I,A16,ALIF_Y2025!F:F) -> 1875073.1
A17: Overhead - Utility | C17: =SUMIF(ALIF_Y2014!I:I,A17,ALIF_Y2014!F:F) -> 1517090.9 | D17: =SUMIF(ALIF_Y2015!I:I,A17,ALIF_Y2015!F:F) -> 1890240.9 | E17: =SUMIF(ALIF_Y2016!I:I,A17,ALIF_Y2016!F:F) -> 2206670.1 | F17: =SUMIF(ALIF_Y2017!I:I,A17,ALIF_Y2017!F:F) -> 1979114.8 | G17: =SUMIF(ALIF_Y2018!I:I,A17,ALIF_Y2018!F:F) -> 878697.03 | H17: =SUMIF(ALIF_Y2019!I:I,A17,ALIF_Y2019!F:F) -> 2551280.2 | I17: =SUMIF(ALIF_Y2020!I:I,A17,ALIF_Y2020!F:F) -> 2434106.6 | J17: =SUMIF(ALIF_Y2021!I:I,A17,ALIF_Y2021!F:F) -> 2828304.4 | K17: =SUMIF(ALIF_Y2022!I:I,A17,ALIF_Y2022!F:F) -> 2591967.2 | L17: =SUMIF(ALIF_Y2023!I:I,A17,ALIF_Y2023!F:F) -> 1657016 | M17: =SUMIF(ALIF_Y2024!I:I,A17,ALIF_Y2024!F:F) -> 2070169 | N17: =SUMIF(ALIF_Y2025!I:I,A17,ALIF_Y2025!F:F) -> 2881316.6
A18: Overhead - R&M | C18: =SUMIF(ALIF_Y2014!I:I,A18,ALIF_Y2014!F:F) -> 257436.95 | D18: =SUMIF(ALIF_Y2015!I:I,A18,ALIF_Y2015!F:F) -> 138250 | E18: =SUMIF(ALIF_Y2016!I:I,A18,ALIF_Y2016!F:F) -> 63418 | F18: =SUMIF(ALIF_Y2017!I:I,A18,ALIF_Y2017!F:F) -> 203768.74 | G18: =SUMIF(ALIF_Y2018!I:I,A18,ALIF_Y2018!F:F) -> 78876.841 | H18: =SUMIF(ALIF_Y2019!I:I,A18,ALIF_Y2019!F:F) -> 307100.91 | I18: =SUMIF(ALIF_Y2020!I:I,A18,ALIF_Y2020!F:F) -> 466866.55 | J18: =SUMIF(ALIF_Y2021!I:I,A18,ALIF_Y2021!F:F) -> 1765300 | K18: =SUMIF(ALIF_Y2022!I:I,A18,ALIF_Y2022!F:F) -> 1776877.6 | L18: =SUMIF(ALIF_Y2023!I:I,A18,ALIF_Y2023!F:F) -> 285381.59 | M18: =SUMIF(ALIF_Y2024!I:I,A18,ALIF_Y2024!F:F) -> 1285902.7 | N18: =SUMIF(ALIF_Y2025!I:I,A18,ALIF_Y2025!F:F) -> 7264252.2
A19: Overhead - Rent | C19: =SUMIF(ALIF_Y2014!I:I,A19,ALIF_Y2014!F:F) -> 1371118.4 | D19: =SUMIF(ALIF_Y2015!I:I,A19,ALIF_Y2015!F:F) -> 1515740.4 | E19: =SUMIF(ALIF_Y2016!I:I,A19,ALIF_Y2016!F:F) -> 1491085.3 | F19: =SUMIF(ALIF_Y2017!I:I,A19,ALIF_Y2017!F:F) -> 790799.6 | G19: =SUMIF(ALIF_Y2018!I:I,A19,ALIF_Y2018!F:F) -> 211393.9 | H19: =SUMIF(ALIF_Y2019!I:I,A19,ALIF_Y2019!F:F) -> 465257.95 | I19: =SUMIF(ALIF_Y2020!I:I,A19,ALIF_Y2020!F:F) -> 319821.65 | J19: =SUMIF(ALIF_Y2021!I:I,A19,ALIF_Y2021!F:F) -> 265999.92 | K19: =SUMIF(ALIF_Y2022!I:I,A19,ALIF_Y2022!F:F) -> 275000 | L19: =SUMIF(ALIF_Y2023!I:I,A19,ALIF_Y2023!F:F) -> 277040 | M19: =SUMIF(ALIF_Y2024!I:I,A19,ALIF_Y2024!F:F) -> 244841.6 | N19: =SUMIF(ALIF_Y2025!I:I,A19,ALIF_Y2025!F:F) -> 413654.01
A20: Overhead - Rent Labor | C20: =SUMIF(ALIF_Y2014!I:I,A20,ALIF_Y2014!F:F) -> 0 | D20: =SUMIF(ALIF_Y2015!I:I,A20,ALIF_Y2015!F:F) -> 0 | E20: =SUMIF(ALIF_Y2016!I:I,A20,ALIF_Y2016!F:F) -> 0 | F20: =SUMIF(ALIF_Y2017!I:I,A20,ALIF_Y2017!F:F) -> 0 | G20: =SUMIF(ALIF_Y2018!I:I,A20,ALIF_Y2018!F:F) -> 0 | H20: =SUMIF(ALIF_Y2019!I:I,A20,ALIF_Y2019!F:F) -> 0 | I20: =SUMIF(ALIF_Y2020!I:I,A20,ALIF_Y2020!F:F) -> 0 | J20: =SUMIF(ALIF_Y2021!I:I,A20,ALIF_Y2021!F:F) -> 0 | K20: =SUMIF(ALIF_Y2022!I:I,A20,ALIF_Y2022!F:F) -> 0 | L20: =SUMIF(ALIF_Y2023!I:I,A20,ALIF_Y2023!F:F) -> 518208 | M20: =SUMIF(ALIF_Y2024!I:I,A20,ALIF_Y2024!F:F) -> 2924648.8 | N20: =SUMIF(ALIF_Y2025!I:I,A20,ALIF_Y2025!F:F) -> 3329353.6
A22: Cost of Sales | C22: =SUM(C10:C21) -> 1.0673609e+08 | D22: =SUM(D10:D21) -> 86796879 | E22: =SUM(E10:E21) -> 73067681 | F22: =SUM(F10:F21) -> 79323832 | G22: =SUM(G10:G21) -> 89043859 | H22: =SUM(H10:H21) -> 1.2456445e+08 | I22: =SUM(I10:I21) -> 1.2318526e+08 | J22: =SUM(J10:J21) -> 1.5863705e+08 | ... N22: =SUM(N10:N21) -> 1.5682913e+08
A24: GROSS PROFIT | C24: =C8-C22 -> 27239331 | D24: =D8-D22 -> 22647279 | E24: =E8-E22 -> 14699962 | F24: =F8-F22 -> 13754773 | G24: =G8-G22 -> 18366166 | H24: =H8-H22 -> 21517296 | I24: =I8-I22 -> 3417578.8 | J24: =J8-J22 -> 23981696 | ... N24: =N8-N22 -> -1935975.4
C25: =C24/C8 -> 0.20331588 | D25: =D24/D8 -> 0.20692999 | E25: =E24/E8 -> 0.16748726 | F25: =F24/F8 -> 0.14777588 | G25: =G24/G8 -> 0.17099117 | H25: =H24/H8 -> 0.14729627 | I25: =I24/I8 -> 0.026994489 | J25: =J24/J8 -> 0.13132111 | ... N25: =N24/N8 -> -0.012498779
A27: Advertising and promotion expenses | C27: =SUMIF(ALIF_Y2014!I:I,A27,ALIF_Y2014!F:F) -> 10844 | D27: =SUMIF(ALIF_Y2015!I:I,A27,ALIF_Y2015!F:F) -> 67555 | E27: =SUMIF(ALIF_Y2016!I:I,A27,ALIF_Y2016!F:F) -> 5162 | F27: =SUMIF(ALIF_Y2017!I:I,A27,ALIF_Y2017!F:F) -> 35415.37 | G27: =SUMIF(ALIF_Y2018!I:I,A27,ALIF_Y2018!F:F) -> 82674.032 | H27: =SUMIF(ALIF_Y2019!I:I,A27,ALIF_Y2019!F:F) -> 48665.419 | I27: =SUMIF(ALIF_Y2020!I:I,A27,ALIF_Y2020!F:F) -> 4000 | J27: =SUMIF(ALIF_Y2021!I:I,A27,ALIF_Y2021!F:F) -> 245 | K27: =SUMIF(ALIF_Y2022!I:I,A27,ALIF_Y2022!F:F) -> 95633.99 | L27: =SUMIF(ALIF_Y2023!I:I,A27,ALIF_Y2023!F:F) -> 127136.29 | M27: =SUMIF(ALIF_Y2024!I:I,A27,ALIF_Y2024!F:F) -> 173026.79 | N27: =SUMIF(ALIF_Y2025!I:I,A27,ALIF_Y2025!F:F) -> 52325.74
A28: Exhibitions | C28: =SUMIF(ALIF_Y2014!I:I,A28,ALIF_Y2014!F:F) -> 0 | D28: =SUMIF(ALIF_Y2015!I:I,A28,ALIF_Y2015!F:F) -> 0 | E28: =SUMIF(ALIF_Y2016!I:I,A28,ALIF_Y2016!F:F) -> 0 | F28: =SUMIF(ALIF_Y2017!I:I,A28,ALIF_Y2017!F:F) -> 0 | G28: =SUMIF(ALIF_Y2018!I:I,A28,ALIF_Y2018!F:F) -> 0 | H28: =SUMIF(ALIF_Y2019!I:I,A28,ALIF_Y2019!F:F) -> 38150 | I28: =SUMIF(ALIF_Y2020!I:I,A28,ALIF_Y2020!F:F) -> 0 | J28: =SUMIF(ALIF_Y2021!I:I,A28,ALIF_Y2021!F:F) -> 1315 | K28: =SUMIF(ALIF_Y2022!I:I,A28,ALIF_Y2022!F:F) -> 96132.78 | L28: =SUMIF(ALIF_Y2023!I:I,A28,ALIF_Y2023!F:F) -> 61539 | M28: =SUMIF(ALIF_Y2024!I:I,A28,ALIF_Y2024!F:F) -> 656254.1 | N28: =SUMIF(ALIF_Y2025!I:I,A28,ALIF_Y2025!F:F) -> 1276853.5
A29: Commission expenses | C29: =SUMIF(ALIF_Y2014!I:I,A29,ALIF_Y2014!F:F) -> 221073.86 | D29: =SUMIF(ALIF_Y2015!I:I,A29,ALIF_Y2015!F:F) -> 211475.23 | E29: =SUMIF(ALIF_Y2016!I:I,A29,ALIF_Y2016!F:F) -> 170392 | F29: =SUMIF(ALIF_Y2017!I:I,A29,ALIF_Y2017!F:F) -> 239089.32 | G29: =SUMIF(ALIF_Y2018!I:I,A29,ALIF_Y2018!F:F) -> 184849.25 | H29: =SUMIF(ALIF_Y2019!I:I,A29,ALIF_Y2019!F:F) -> 222802.95 | I29: =SUMIF(ALIF_Y2020!I:I,A29,ALIF_Y2020!F:F) -> 254893.24 | J29: =SUMIF(ALIF_Y2021!I:I,A29,ALIF_Y2021!F:F) -> 332942.77 | K29: =SUMIF(ALIF_Y2022!I:I,A29,ALIF_Y2022!F:F) -> 262263 | L29: =SUMIF(ALIF_Y2023!I:I,A29,ALIF_Y2023!F:F) -> 43952.72 | M29: =SUMIF(ALIF_Y2024!I:I,A29,ALIF_Y2024!F:F) -> 38359.55 | N29: =SUMIF(ALIF_Y2025!I:I,A29,ALIF_Y2025!F:F) -> 5036
A30: Buffet expenses | C30: =SUMIF(ALIF_Y2014!I:I,A30,ALIF_Y2014!F:F) -> 24136 | D30: =SUMIF(ALIF_Y2015!I:I,A30,ALIF_Y2015!F:F) -> 49422 | E30: =SUMIF(ALIF_Y2016!I:I,A30,ALIF_Y2016!F:F) -> 23617 | F30: =SUMIF(ALIF_Y2017!I:I,A30,ALIF_Y2017!F:F) -> 12728.2 | G30: =SUMIF(ALIF_Y2018!I:I,A30,ALIF_Y2018!F:F) -> 38545.124 | H30: =SUMIF(ALIF_Y2019!I:I,A30,ALIF_Y2019!F:F) -> 30691.55 | I30: =SUMIF(ALIF_Y2020!I:I,A30,ALIF_Y2020!F:F) -> 44987.73 | J30: =SUMIF(ALIF_Y2021!I:I,A30,ALIF_Y2021!F:F) -> 44509.047 | K30: =SUMIF(ALIF_Y2022!I:I,A30,ALIF_Y2022!F:F) -> 46729.389 | L30: =SUMIF(ALIF_Y2023!I:I,A30,ALIF_Y2023!F:F) -> 8770.327 | M30: =SUMIF(ALIF_Y2024!I:I,A30,ALIF_Y2024!F:F) -> 112372.72 | N30: =SUMIF(ALIF_Y2025!I:I,A30,ALIF_Y2025!F:F) -> 279488.05
A32: Selling and Distribution | C32: =SUM(C27:C31) -> 256053.86 | D32: =SUM(D27:D31) -> 328452.23 | E32: =SUM(E27:E31) -> 199171 | F32: =SUM(F27:F31) -> 287232.89 | G32: =SUM(G27:G31) -> 306068.41 | H32: =SUM(H27:H31) -> 340309.92 | I32: =SUM(I27:I31) -> 303880.97 | J32: =SUM(J27:J31) -> 379011.82 | ... N32: =SUM(N27:N31) -> 1613703.3
A34: Salaries and wages | C34: =SUMIF(ALIF_Y2014!I:I,A34,ALIF_Y2014!F:F) -> 6363603.8 | D34: =SUMIF(ALIF_Y2015!I:I,A34,ALIF_Y2015!F:F) -> 5731816.7 | E34: =SUMIF(ALIF_Y2016!I:I,A34,ALIF_Y2016!F:F) -> 5700243.6 | F34: =SUMIF(ALIF_Y2017!I:I,A34,ALIF_Y2017!F:F) -> 7742150.8 | G34: =SUMIF(ALIF_Y2018!I:I,A34,ALIF_Y2018!F:F) -> 7523616.8 | H34: =SUMIF(ALIF_Y2019!I:I,A34,ALIF_Y2019!F:F) -> 8539362.4 | I34: =SUMIF(ALIF_Y2020!I:I,A34,ALIF_Y2020!F:F) -> 10507908 | J34: =SUMIF(ALIF_Y2021!I:I,A34,ALIF_Y2021!F:F) -> 11276241 | K34: =SUMIF(ALIF_Y2022!I:I,A34,ALIF_Y2022!F:F) -> 10667360 | L34: =SUMIF(ALIF_Y2023!I:I,A34,ALIF_Y2023!F:F) -> 10673402 | M34: =SUMIF(ALIF_Y2024!I:I,A34,ALIF_Y2024!F:F) -> 10184021 | N34: =SUMIF(ALIF_Y2025!I:I,A34,ALIF_Y2025!F:F) -> 23383962
A35: Utilities | C35: =SUMIF(ALIF_Y2014!I:I,A35,ALIF_Y2014!F:F) -> 452003.42 | D35: =SUMIF(ALIF_Y2015!I:I,A35,ALIF_Y2015!F:F) -> 482714.05 | E35: =SUMIF(ALIF_Y2016!I:I,A35,ALIF_Y2016!F:F) -> 550372.54 | F35: =SUMIF(ALIF_Y2017!I:I,A35,ALIF_Y2017!F:F) -> 512953.74 | G35: =SUMIF(ALIF_Y2018!I:I,A35,ALIF_Y2018!F:F) -> 979494.06 | H35: =SUMIF(ALIF_Y2019!I:I,A35,ALIF_Y2019!F:F) -> 1067033.7 | I35: =SUMIF(ALIF_Y2020!I:I,A35,ALIF_Y2020!F:F) -> 1391075.6 | J35: =SUMIF(ALIF_Y2021!I:I,A35,ALIF_Y2021!F:F) -> 1172434.6 | K35: =SUMIF(ALIF_Y2022!I:I,A35,ALIF_Y2022!F:F) -> 1350946.7 | L35: =SUMIF(ALIF_Y2023!I:I,A35,ALIF_Y2023!F:F) -> 606309.52 | M35: =SUMIF(ALIF_Y2024!I:I,A35,ALIF_Y2024!F:F) -> 1013970 | N35: =SUMIF(ALIF_Y2025!I:I,A35,ALIF_Y2025!F:F) -> 753096.56
A36: Business travel | C36: =SUMIF(ALIF_Y2014!I:I,A36,ALIF_Y2014!F:F) -> 324499 | D36: =SUMIF(ALIF_Y2015!I:I,A36,ALIF_Y2015!F:F) -> 213428 | E36: =SUMIF(ALIF_Y2016!I:I,A36,ALIF_Y2016!F:F) -> 97884.22 | F36: =SUMIF(ALIF_Y2017!I:I,A36,ALIF_Y2017!F:F) -> 98488.72 | G36: =SUMIF(ALIF_Y2018!I:I,A36,ALIF_Y2018!F:F) -> 334049.23 | H36: =SUMIF(ALIF_Y2019!I:I,A36,ALIF_Y2019!F:F) -> 342874.68 | I36: =SUMIF(ALIF_Y2020!I:I,A36,ALIF_Y2020!F:F) -> 78102.23 | J36: =SUMIF(ALIF_Y2021!I:I,A36,ALIF_Y2021!F:F) -> 65074.312 | K36: =SUMIF(ALIF_Y2022!I:I,A36,ALIF_Y2022!F:F) -> 163076.27 | L36: =SUMIF(ALIF_Y2023!I:I,A36,ALIF_Y2023!F:F) -> 326944.08 | M36: =SUMIF(ALIF_Y2024!I:I,A36,ALIF_Y2024!F:F) -> 1176775.5 | N36: =SUMIF(ALIF_Y2025!I:I,A36,ALIF_Y2025!F:F) -> 736726.41
A37: Training | C37: =SUMIF(ALIF_Y2014!I:I,A37,ALIF_Y2014!F:F) -> 0 | D37: =SUMIF(ALIF_Y2015!I:I,A37,ALIF_Y2015!F:F) -> 5707.643 | E37: =SUMIF(ALIF_Y2016!I:I,A37,ALIF_Y2016!F:F) -> 0 | F37: =SUMIF(ALIF_Y2017!I:I,A37,ALIF_Y2017!F:F) -> 0 | G37: =SUMIF(ALIF_Y2018!I:I,A37,ALIF_Y2018!F:F) -> 0 | H37: =SUMIF(ALIF_Y2019!I:I,A37,ALIF_Y2019!F:F) -> 38300 | I37: =SUMIF(ALIF_Y2020!I:I,A37,ALIF_Y2020!F:F) -> 40087 | J37: =SUMIF(ALIF_Y2021!I:I,A37,ALIF_Y2021!F:F) -> 121235.63 | K37: =SUMIF(ALIF_Y2022!I:I,A37,ALIF_Y2022!F:F) -> 74764 | L37: =SUMIF(ALIF_Y2023!I:I,A37,ALIF_Y2023!F:F) -> 3329 | M37: =SUMIF(ALIF_Y2024!I:I,A37,ALIF_Y2024!F:F) -> 441573.53 | N37: =SUMIF(ALIF_Y2025!I:I,A37,ALIF_Y2025!F:F) -> 95706.072
A38: IT expenses | C38: =SUMIF(ALIF_Y2014!I:I,A38,ALIF_Y2014!F:F) -> 47876.31 | D38: =SUMIF(ALIF_Y2015!I:I,A38,ALIF_Y2015!F:F) -> 61858.551 | E38: =SUMIF(ALIF_Y2016!I:I,A38,ALIF_Y2016!F:F) -> 68446.898 | F38: =SUMIF(ALIF_Y2017!I:I,A38,ALIF_Y2017!F:F) -> 83539.5 | G38: =SUMIF(ALIF_Y2018!I:I,A38,ALIF_Y2018!F:F) -> 193976.31 | H38: =SUMIF(ALIF_Y2019!I:I,A38,ALIF_Y2019!F:F) -> 173017.55 | I38: =SUMIF(ALIF_Y2020!I:I,A38,ALIF_Y2020!F:F) -> 347776.16 | J38: =SUMIF(ALIF_Y2021!I:I,A38,ALIF_Y2021!F:F) -> 193144.23 | K38: =SUMIF(ALIF_Y2022!I:I,A38,ALIF_Y2022!F:F) -> 699621.14 | L38: =SUMIF(ALIF_Y2023!I:I,A38,ALIF_Y2023!F:F) -> 757807.59 | M38: =SUMIF(ALIF_Y2024!I:I,A38,ALIF_Y2024!F:F) -> 690317.47 | N38: =SUMIF(ALIF_Y2025!I:I,A38,ALIF_Y2025!F:F) -> 706542.29
A39: Govt license and fees (including modon) | C39: =SUMIF(ALIF_Y2014!I:I,A39,ALIF_Y2014!F:F) -> 497207 | D39: =SUMIF(ALIF_Y2015!I:I,A39,ALIF_Y2015!F:F) -> 594070.73 | E39: =SUMIF(ALIF_Y2016!I:I,A39,ALIF_Y2016!F:F) -> 881628.04 | F39: =SUMIF(ALIF_Y2017!I:I,A39,ALIF_Y2017!F:F) -> 878404.02 | G39: =SUMIF(ALIF_Y2018!I:I,A39,ALIF_Y2018!F:F) -> 798554.73 | H39: =SUMIF(ALIF_Y2019!I:I,A39,ALIF_Y2019!F:F) -> 721606.55 | I39: =SUMIF(ALIF_Y2020!I:I,A39,ALIF_Y2020!F:F) -> 2172417 | J39: =SUMIF(ALIF_Y2021!I:I,A39,ALIF_Y2021!F:F) -> 952190.3 | K39: =SUMIF(ALIF_Y2022!I:I,A39,ALIF_Y2022!F:F) -> 518370.67 | L39: =SUMIF(ALIF_Y2023!I:I,A39,ALIF_Y2023!F:F) -> 660248.72 | M39: =SUMIF(ALIF_Y2024!I:I,A39,ALIF_Y2024!F:F) -> 689064.96 | N39: =SUMIF(ALIF_Y2025!I:I,A39,ALIF_Y2025!F:F) -> 1035438.7
A40: Rent | C40: =SUMIF(ALIF_Y2014!I:I,A40,ALIF_Y2014!F:F) -> 0 | D40: =SUMIF(ALIF_Y2015!I:I,A40,ALIF_Y2015!F:F) -> 0 | E40: =SUMIF(ALIF_Y2016!I:I,A40,ALIF_Y2016!F:F) -> 0 | F40: =SUMIF(ALIF_Y2017!I:I,A40,ALIF_Y2017!F:F) -> 0 | G40: =SUMIF(ALIF_Y2018!I:I,A40,ALIF_Y2018!F:F) -> 0 | H40: =SUMIF(ALIF_Y2019!I:I,A40,ALIF_Y2019!F:F) -> 0 | I40: =SUMIF(ALIF_Y2020!I:I,A40,ALIF_Y2020!F:F) -> 0 | J40: =SUMIF(ALIF_Y2021!I:I,A40,ALIF_Y2021!F:F) -> 0 | K40: =SUMIF(ALIF_Y2022!I:I,A40,ALIF_Y2022!F:F) -> 0 | L40: =SUMIF(ALIF_Y2023!I:I,A40,ALIF_Y2023!F:F) -> 0 | M40: =SUMIF(ALIF_Y2024!I:I,A40,ALIF_Y2024!F:F) -> 24243.5 | N40: =SUMIF(ALIF_Y2025!I:I,A40,ALIF_Y2025!F:F) -> 147339.16
A41: Back office Support | C41: =SUMIF(ALIF_Y2014!I:I,A41,ALIF_Y2014!F:F) -> 17234.6 | D41: =SUMIF(ALIF_Y2015!I:I,A41,ALIF_Y2015!F:F) -> 5201 | E41: =SUMIF(ALIF_Y2016!I:I,A41,ALIF_Y2016!F:F) -> 52054 | F41: =SUMIF(ALIF_Y2017!I:I,A41,ALIF_Y2017!F:F) -> 40763.3 | G41: =SUMIF(ALIF_Y2018!I:I,A41,ALIF_Y2018!F:F) -> 100440.99 | H41: =SUMIF(ALIF_Y2019!I:I,A41,ALIF_Y2019!F:F) -> -488046.26 | I41: =SUMIF(ALIF_Y2020!I:I,A41,ALIF_Y2020!F:F) -> 2025126.3 | J41: =SUMIF(ALIF_Y2021!I:I,A41,ALIF_Y2021!F:F) -> 183980.26 | K41: =SUMIF(ALIF_Y2022!I:I,A41,ALIF_Y2022!F:F) -> 170065.17 | L41: =SUMIF(ALIF_Y2023!I:I,A41,ALIF_Y2023!F:F) -> 8953.96 | M41: =SUMIF(ALIF_Y2024!I:I,A41,ALIF_Y2024!F:F) -> 41863.288 | N41: =SUMIF(ALIF_Y2025!I:I,A41,ALIF_Y2025!F:F) -> 58776.647
A42: AIMS expenses | C42: =SUMIF(ALIF_Y2014!I:I,A42,ALIF_Y2014!F:F) -> 0 | D42: =SUMIF(ALIF_Y2015!I:I,A42,ALIF_Y2015!F:F) -> 0 | E42: =SUMIF(ALIF_Y2016!I:I,A42,ALIF_Y2016!F:F) -> 0 | F42: =SUMIF(ALIF_Y2017!I:I,A42,ALIF_Y2017!F:F) -> 0 | G42: =SUMIF(ALIF_Y2018!I:I,A42,ALIF_Y2018!F:F) -> 0 | H42: =SUMIF(ALIF_Y2019!I:I,A42,ALIF_Y2019!F:F) -> 0 | I42: =SUMIF(ALIF_Y2020!I:I,A42,ALIF_Y2020!F:F) -> 0 | J42: =SUMIF(ALIF_Y2021!I:I,A42,ALIF_Y2021!F:F) -> 0 | K42: =SUMIF(ALIF_Y2022!I:I,A42,ALIF_Y2022!F:F) -> 700886 | L42: =SUMIF(ALIF_Y2023!I:I,A42,ALIF_Y2023!F:F) -> 0 | M42: =SUMIF(ALIF_Y2024!I:I,A42,ALIF_Y2024!F:F) -> 0 | N42: =SUMIF(ALIF_Y2025!I:I,A42,ALIF_Y2025!F:F) -> 0
A44: General and Admin | C44: =SUM(C34:C43) -> 7702424.1 | D44: =SUM(D34:D43) -> 7094796.7 | E44: =SUM(E34:E43) -> 7350629.3 | F44: =SUM(F34:F43) -> 9356300.1 | G44: =SUM(G34:G43) -> 9930132.1 | H44: =SUM(H34:H43) -> 10394149 | I44: =SUM(I34:I43) -> 16562492 | J44: =SUM(J34:J43) -> 13964301 | ... N44: =SUM(N34:N43) -> 26917588
A46: Bad debts expense | C46: =SUMIF(ALIF_Y2014!I:I,A46,ALIF_Y2014!F:F) -> 700005.97 | D46: =SUMIF(ALIF_Y2015!I:I,A46,ALIF_Y2015!F:F) -> 133917.82 | E46: =SUMIF(ALIF_Y2016!I:I,A46,ALIF_Y2016!F:F) -> 0 | F46: =SUMIF(ALIF_Y2017!I:I,A46,ALIF_Y2017!F:F) -> 0 | G46: =SUMIF(ALIF_Y2018!I:I,A46,ALIF_Y2018!F:F) -> 0 | H46: =SUMIF(ALIF_Y2019!I:I,A46,ALIF_Y2019!F:F) -> 0 | I46: =SUMIF(ALIF_Y2020!I:I,A46,ALIF_Y2020!F:F) -> 325461 | J46: =SUMIF(ALIF_Y2021!I:I,A46,ALIF_Y2021!F:F) -> 248775 | K46: =SUMIF(ALIF_Y2022!I:I,A46,ALIF_Y2022!F:F) -> 103333.33 | L46: =SUMIF(ALIF_Y2023!I:I,A46,ALIF_Y2023!F:F) -> 8931099.4 | M46: =SUMIF(ALIF_Y2024!I:I,A46,ALIF_Y2024!F:F) -> -5119898.6 | N46: =SUMIF(ALIF_Y2025!I:I,A46,ALIF_Y2025!F:F) -> -678521.16
A47: Inventory Adjustment Expense | C47: =SUMIF(ALIF_Y2014!I:I,A47,ALIF_Y2014!F:F) -> 0 | D47: =SUMIF(ALIF_Y2015!I:I,A47,ALIF_Y2015!F:F) -> 0 | E47: =SUMIF(ALIF_Y2016!I:I,A47,ALIF_Y2016!F:F) -> 0 | F47: =SUMIF(ALIF_Y2017!I:I,A47,ALIF_Y2017!F:F) -> 0 | G47: =SUMIF(ALIF_Y2018!I:I,A47,ALIF_Y2018!F:F) -> 0 | H47: =SUMIF(ALIF_Y2019!I:I,A47,ALIF_Y2019!F:F) -> 0 | I47: =SUMIF(ALIF_Y2020!I:I,A47,ALIF_Y2020!F:F) -> 0 | J47: =SUMIF(ALIF_Y2021!I:I,A47,ALIF_Y2021!F:F) -> 0 | K47: =SUMIF(ALIF_Y2022!I:I,A47,ALIF_Y2022!F:F) -> 0 | L47: =SUMIF(ALIF_Y2023!I:I,A47,ALIF_Y2023!F:F) -> 0 | M47: =SUMIF(ALIF_Y2024!I:I,A47,ALIF_Y2024!F:F) -> 3148512.3 | N47: =SUMIF(ALIF_Y2025!I:I,A47,ALIF_Y2025!F:F) -> 0
A49: OPERATING INCOME (EBITDA) | C49: =C24-C32-C44-C46-C47 -> 18580847 | D49: =D24-D32-D44-D46-D47 -> 15090112 | E49: =E24-E32-E44-E46-E47 -> 7150161.8 | F49: =F24-F32-F44-F46-F47 -> 4111239.8 | G49: =G24-G32-G44-G46-G47 -> 8129965.8 | H49: =H24-H32-H44-H46-H47 -> 10782838 | I49: =I24-I32-I44-I46-I47 -> -13774255 | J49: =J24-J32-J44-J46-J47 -> 9389608.7 | ... N49: =N24-N32-N44-N46-N47 -> -29788746
A51: Finance cost | C51: =SUMIF(ALIF_Y2014!I:I,A51,ALIF_Y2014!F:F) -> 1986535.1 | D51: =SUMIF(ALIF_Y2015!I:I,A51,ALIF_Y2015!F:F) -> 1159554.7 | E51: =SUMIF(ALIF_Y2016!I:I,A51,ALIF_Y2016!F:F) -> 1539704.4 | F51: =SUMIF(ALIF_Y2017!I:I,A51,ALIF_Y2017!F:F) -> 1568335 | G51: =SUMIF(ALIF_Y2018!I:I,A51,ALIF_Y2018!F:F) -> 2338864.7 | H51: =SUMIF(ALIF_Y2019!I:I,A51,ALIF_Y2019!F:F) -> 3369252 | I51: =SUMIF(ALIF_Y2020!I:I,A51,ALIF_Y2020!F:F) -> 3139563.6 | J51: =SUMIF(ALIF_Y2021!I:I,A51,ALIF_Y2021!F:F) -> 4025597.3 | K51: =SUMIF(ALIF_Y2022!I:I,A51,ALIF_Y2022!F:F) -> 4641310.1 | L51: =SUMIF(ALIF_Y2023!I:I,A51,ALIF_Y2023!F:F) -> 5894124.6 | M51: =SUMIF(ALIF_Y2024!I:I,A51,ALIF_Y2024!F:F) -> 7716907.1 | N51: =SUMIF(ALIF_Y2025!I:I,A51,ALIF_Y2025!F:F) -> 11618933
A52: Depreciation expenses | C52: =SUMIF(ALIF_Y2014!I:I,A52,ALIF_Y2014!F:F) -> 410748.17 | D52: =SUMIF(ALIF_Y2015!I:I,A52,ALIF_Y2015!F:F) -> 447124.53 | E52: =SUMIF(ALIF_Y2016!I:I,A52,ALIF_Y2016!F:F) -> 295860.39 | F52: =SUMIF(ALIF_Y2017!I:I,A52,ALIF_Y2017!F:F) -> 378246.46 | G52: =SUMIF(ALIF_Y2018!I:I,A52,ALIF_Y2018!F:F) -> 903739.73 | H52: =SUMIF(ALIF_Y2019!I:I,A52,ALIF_Y2019!F:F) -> 718507.81 | I52: =SUMIF(ALIF_Y2020!I:I,A52,ALIF_Y2020!F:F) -> 1984412.7 | J52: =SUMIF(ALIF_Y2021!I:I,A52,ALIF_Y2021!F:F) -> 2123910.1 | K52: =SUMIF(ALIF_Y2022!I:I,A52,ALIF_Y2022!F:F) -> 2249190.8 | L52: =SUMIF(ALIF_Y2023!I:I,A52,ALIF_Y2023!F:F) -> 2301785 | M52: =SUMIF(ALIF_Y2024!I:I,A52,ALIF_Y2024!F:F) -> 2249499.9 | N52: =SUMIF(ALIF_Y2025!I:I,A52,ALIF_Y2025!F:F) -> 2603825.6
A53: Other Income | C53: =SUMIF(ALIF_Y2014!I:I,A53,ALIF_Y2014!F:F) -> 0 | D53: =SUMIF(ALIF_Y2015!I:I,A53,ALIF_Y2015!F:F) -> 0 | E53: =SUMIF(ALIF_Y2016!I:I,A53,ALIF_Y2016!F:F) -> 0 | F53: =SUMIF(ALIF_Y2017!I:I,A53,ALIF_Y2017!F:F) -> 0 | G53: =SUMIF(ALIF_Y2018!I:I,A53,ALIF_Y2018!F:F) -> 0 | H53: =SUMIF(ALIF_Y2019!I:I,A53,ALIF_Y2019!F:F) -> 0 | I53: =SUMIF(ALIF_Y2020!I:I,A53,ALIF_Y2020!F:F) -> 0 | J53: =SUMIF(ALIF_Y2021!I:I,A53,ALIF_Y2021!F:F) -> -751257.5 | K53: =SUMIF(ALIF_Y2022!I:I,A53,ALIF_Y2022!F:F) -> -1290167.1 | L53: =SUMIF(ALIF_Y2023!I:I,A53,ALIF_Y2023!F:F) -> -776507.2 | M53: =SUMIF(ALIF_Y2024!I:I,A53,ALIF_Y2024!F:F) -> -157172 | N53: =SUMIF(ALIF_Y2025!I:I,A53,ALIF_Y2025!F:F) -> -193037.5
A54: Zakat expenses | C54: =SUMIF(ALIF_Y2014!I:I,A54,ALIF_Y2014!F:F) -> 1537200 | D54: =SUMIF(ALIF_Y2015!I:I,A54,ALIF_Y2015!F:F) -> 1363871 | E54: =SUMIF(ALIF_Y2016!I:I,A54,ALIF_Y2016!F:F) -> 1221311.1 | F54: =SUMIF(ALIF_Y2017!I:I,A54,ALIF_Y2017!F:F) -> 994649.23 | G54: =SUMIF(ALIF_Y2018!I:I,A54,ALIF_Y2018!F:F) -> 1150000 | H54: =SUMIF(ALIF_Y2019!I:I,A54,ALIF_Y2019!F:F) -> 954424.53 | I54: =SUMIF(ALIF_Y2020!I:I,A54,ALIF_Y2020!F:F) -> 644385.89 | J54: =SUMIF(ALIF_Y2021!I:I,A54,ALIF_Y2021!F:F) -> 146434.87 | K54: =SUMIF(ALIF_Y2022!I:I,A54,ALIF_Y2022!F:F) -> 672246.94 | L54: =SUMIF(ALIF_Y2023!I:I,A54,ALIF_Y2023!F:F) -> 235302.94 | M54: =SUMIF(ALIF_Y2024!I:I,A54,ALIF_Y2024!F:F) -> 9561.04 | N54: =SUMIF(ALIF_Y2025!I:I,A54,ALIF_Y2025!F:F) -> 0
A56: NET INCOME | C56: =C49-C51-C52-C54-C53 -> 14646364 | D56: =D49-D51-D52-D54-D53 -> 12119562 | E56: =E49-E51-E52-E54-E53 -> 4093286 | F56: =F49-F51-F52-F54-F53 -> 1170009.1 | G56: =G49-G51-G52-G54-G53 -> 3737361.4 | H56: =H49-H51-H52-H54-H53 -> 5740653.4 | I56: =I49-I51-I52-I54-I53 -> -19542617 | J56: =J49-J51-J52-J54-J53 -> 3844923.9 | ... N56: =N49-N51-N52-N54-N53 -> -43818467
A58: Actuarial gains and losses | C58: =SUMIF(ALIF_Y2014!I:I,A58,ALIF_Y2014!F:F) -> 0 | D58: =SUMIF(ALIF_Y2015!I:I,A58,ALIF_Y2015!F:F) -> 0 | E58: =SUMIF(ALIF_Y2016!I:I,A58,ALIF_Y2016!F:F) -> 0 | F58: =SUMIF(ALIF_Y2017!I:I,A58,ALIF_Y2017!F:F) -> 0 | G58: =SUMIF(ALIF_Y2018!I:I,A58,ALIF_Y2018!F:F) -> 0 | H58: =SUMIF(ALIF_Y2019!I:I,A58,ALIF_Y2019!F:F) -> -608441 | I58: =SUMIF(ALIF_Y2020!I:I,A58,ALIF_Y2020!F:F) -> 180079 | J58: =SUMIF(ALIF_Y2021!I:I,A58,ALIF_Y2021!F:F) -> -25921 | K58: =SUMIF(ALIF_Y2022!I:I,A58,ALIF_Y2022!F:F) -> 35621 | L58: =SUMIF(ALIF_Y2023!I:I,A58,ALIF_Y2023!F:F) -> 1151975.3 | M58: =SUMIF(ALIF_Y2024!I:I,A58,ALIF_Y2024!F:F) -> -1573353 | N58: =SUMIF(ALIF_Y2025!I:I,A58,ALIF_Y2025!F:F) -> 0
A59: OTHER COMRPREHENSIVE INCOME | C59: =C56-C58 -> 14646364 | D59: =D56-D58 -> 12119562 | E59: =E56-E58 -> 4093286 | F59: =F56-F58 -> 1170009.1 | G59: =G56-G58 -> 3737361.4 | H59: =H56-H58 -> 6349094.4 | I59: =I56-I58 -> -19722696 | J59: =J56-J58 -> 3870844.9 | ... N59: =N56-N58 -> -43818467
A61: Percent:
B62: COGS | C62: =C22/C8*100 -> 79.668412 | D62: =D22/D8*100 -> 79.307001 | E62: =E22/E8*100 -> 83.251274 | F62: =F22/F8*100 -> 85.222412 | G62: =G22/G8*100 -> 82.900883 | H62: =H22/H8*100 -> 85.270373 | I62: =I22/I8*100 -> 97.300551 | J62: =J22/J8*100 -> 86.867889 | ... N62: =N22/N8*100 -> 101.24988
B63: Raw materials | C63: =C10/C8*100 -> 61.161253 | D63: =D10/D8*100 -> 60.217073 | E63: =E10/E8*100 -> 62.870215 | F63: =F10/F8*100 -> 62.54309 | G63: =G10/G8*100 -> 69.974579 | H63: =H10/H8*100 -> 69.687111 | I63: =I10/I8*100 -> 79.76793 | J63: =J10/J8*100 -> 70.341712 | ... N63: =N10/N8*100 -> 73.768564
B64: Direct Labor | C64: =C11/C8*100 -> 7.5465913 | D64: =D11/D8*100 -> 4.5361805 | E64: =E11/E8*100 -> 3.1357672 | F64: =F11/F8*100 -> 8.6773253 | G64: =G11/G8*100 -> 4.3669098 | H64: =H11/H8*100 -> 3.2428377 | I64: =I11/I8*100 -> 3.6465851 | J64: =J11/J8*100 -> 3.3477116 | ... N64: =N11/N8*100 -> 9.4660559
B65: Freight expenses | C65: =C12/C8*100 -> 1.995795 | D65: =D12/D8*100 -> 2.4987486 | E65: =E12/E8*100 -> 3.0384963 | F65: =F12/F8*100 -> 2.3992986 | G65: =G12/G8*100 -> 3.0317613 | H65: =H12/H8*100 -> 2.3845413 | I65: =I12/I8*100 -> 2.12638 | J65: =J12/J8*100 -> 1.5333646 | ... N65: =N12/N8*100 -> 1.4420122
B66: Customs duties and clearances | N66: =N13/N8*100 -> -9.019016e-16
B67: Depreciation - Machines | C67: =C14/C8*100 -> 2.2050242 | D67: =D14/D8*100 -> 2.8922543 | E67: =E14/E8*100 -> 3.9137519 | F67: =F14/F8*100 -> 3.7957567 | G67: =G14/G8*100 -> 2.0464561 | H67: =H14/H8*100 -> 2.4904576 | I67: =I14/I8*100 -> 2.5723285 | J67: =J14/J8*100 -> 1.8875223 | ... N67: =N14/N8*100 -> 4.7488802
B68: Overhead - Labor Cost | C68: =C15/C8*100 -> 1.8169906 | D68: =D15/D8*100 -> 2.2112318 | E68: =E15/E8*100 -> 2.5690916 | F68: =F15/F8*100 -> 2.1855574 | G68: =G15/G8*100 -> 1.0195951 | H68: =H15/H8*100 -> 2.703335 | I68: =I15/I8*100 -> 3.2542755 | J68: =J15/J8*100 -> 3.5859333 | ... N68: =N15/N8*100 -> 1.6472544
B69: Overhead - Consumables & SP | C69: =C16/C8*100 -> 2.5948297 | D69: =D16/D8*100 -> 3.7131204 | E69: =E16/E8*100 -> 3.4385761 | F69: =F16/F8*100 -> 2.4265753 | G69: =G16/G8*100 -> 1.3732589 | H69: =H16/H8*100 -> 2.4868998 | I69: =I16/I8*100 -> 3.3890372 | J69: =J16/J8*100 -> 3.5105801 | ... N69: =N16/N8*100 -> 1.210559
B70: Overhead - Utility | C70: =C17/C8*100 -> 1.1323651 | D70: =D17/D8*100 -> 1.7271282 | E70: =E17/E8*100 -> 2.5142182 | F70: =F17/F8*100 -> 2.1262833 | G70: =G17/G8*100 -> 0.8180773 | H70: =H17/H8*100 -> 1.7464743 | I70: =I17/I8*100 -> 1.922632 | J70: =J17/J8*100 -> 1.5487481 | ... N70: =N17/N8*100 -> 1.8601962
B71: Overhead - R&M | C71: =C18/C8*100 -> 0.19215237 | D71: =D18/D8*100 -> 0.12632013 | E71: =E18/E8*100 -> 0.072256697 | F71: =F18/F8*100 -> 0.21892114 | G71: =G18/G8*100 -> 0.073435269 | H71: =H18/H8*100 -> 0.21022538 | I71: =I18/I8*100 -> 0.36876469 | J71: =J18/J8*100 -> 0.9666587 | ... N71: =N18/N8*100 -> 4.6898471
B72: Overhead - Rent | C72: =C19/C8*100 -> 1.0234104 | D72: =D19/D8*100 -> 1.3849441 | E72: =E19/E8*100 -> 1.6989009 | F72: =F19/F8*100 -> 0.84960405 | G72: =G19/G8*100 -> 0.19681021 | H72: =H19/H8*100 -> 0.3184915 | I72: =I19/I8*100 -> 0.25261808 | J72: =J19/J8*100 -> 0.14565861 | ... N72: =N19/N8*100 -> 0.26705764
B73: Overhead - Rent Labor | L73: =L20/L8*100 -> 0.49731809 | M73: =M20/M8*100 -> 2.1630279 | N73: =N20/N8*100 -> 2.1494517
B74: GP | C74: =C24/C8*100 -> 20.331588 | D74: =D24/D8*100 -> 20.692999 | E74: =E24/E8*100 -> 16.748726 | F74: =F24/F8*100 -> 14.777588 | G74: =G24/G8*100 -> 17.099117 | H74: =H24/H8*100 -> 14.729627 | I74: =I24/I8*100 -> 2.6994489 | J74: =J24/J8*100 -> 13.132111 | ... N74: =N24/N8*100 -> -1.2498779
B75: Selling | C75: =C32/C8*100 -> 0.19112002 | D75: =D32/D8*100 -> 0.30010942 | E75: =E32/E8*100 -> 0.22692987 | F75: =F32/F8*100 -> 0.30859174 | G75: =G32/G8*100 -> 0.28495329 | H75: =H32/H8*100 -> 0.23295854 | I75: =I32/I8*100 -> 0.24002699 | J75: =J32/J8*100 -> 0.20754267 | ... N75: =N32/N8*100 -> 1.0418171
B76: G&A | C76: =C44/C8*100 -> 5.7491321 | D76: =D44/D8*100 -> 6.4825723 | E76: =E44/E8*100 -> 8.3751017 | F76: =F44/F8*100 -> 10.052042 | G76: =G44/G8*100 -> 9.24507 | H76: =H44/H8*100 -> 7.1152958 | I76: =I44/I8*100 -> 13.082244 | J76: =J44/J8*100 -> 7.6466961 | ... N76: =N44/N8*100 -> 17.378165
B77: Finance Cost | C77: =C51/C8*100 -> 1.4827608 | D77: =D51/D8*100 -> 1.0594944 | E77: =E51/E8*100 -> 1.7542961 | F77: =F51/F8*100 -> 1.6849576 | G77: =G51/G8*100 -> 2.1775106 | H77: =H51/H8*100 -> 2.3064154 | I77: =I51/I8*100 -> 2.4798525 | J77: =J51/J8*100 -> 2.2043724 | ... N77: =N51/N8*100 -> 7.5012567
B78: Depreciation | C78: =C52/C8*100 -> 0.30658471 | D78: =D52/D8*100 -> 0.40854125 | E78: =E52/E8*100 -> 0.33709506 | F78: =F52/F8*100 -> 0.40637315 | G78: =G52/G8*100 -> 0.84139234 | H78: =H52/H8*100 -> 0.49185323 | I78: =I52/I8*100 -> 1.5674315 | J78: =J52/J8*100 -> 1.1630296 | ... N78: =N52/N8*100 -> 1.6810462
B79: EBITDA | C79: =C49/C8*100 -> 13.868847 | D79: =D49/D8*100 -> 13.787956 | E79: =E49/E8*100 -> 8.1466946 | F79: =F49/F8*100 -> 4.4169547 | G79: =G49/G8*100 -> 7.569094 | H79: =H49/H8*100 -> 7.3813723 | I79: =I49/I8*100 -> -10.879895 | J79: =J49/J8*100 -> 5.1416455 | ... N79: =N49/N8*100 -> -19.231802
B80: Net income (loss) | C80: =C56/C8*100 -> 10.932127 | D80: =D56/D8*100 -> 11.07374 | E80: =E56/E8*100 -> 4.6637757 | F80: =F56/F8*100 -> 1.2570119 | G80: =G56/G8*100 -> 3.4795275 | H80: =H56/H8*100 -> 3.929754 | I80: =I56/I8*100 -> -15.436161 | J80: =J56/J8*100 -> 2.1054377 | ... N80: =N56/N8*100 -> -28.289479
B82: Fixed Cost | C82: =C27+C28+C29+C30+C44+C46+C47+C51+C52+C54 -> 12592967 | D82: =D27+D28+D29+D30+D44+D46+D47+D51+D52+D54 -> 10527717 | E82: =E27+E28+E29+E30+E44+E46+E47+E51+E52+E54 -> 10606676 | F82: =F27+F28+F29+F30+F44+F46+F47+F51+F52+F54 -> 12584764 | G82: =G27+G28+G29+G30+G44+G46+G47+G51+G52+G54 -> 14628805 | H82: =H27+H28+H29+H30+H44+H46+H47+H51+H52+H54 -> 15776643 | I82: =I27+I28+I29+I30+I44+I46+I47+I51+I52+I54 -> 22960196 | J82: =J27+J28+J29+J30+J44+J46+J47+J51+J52+J54 -> 20888030 | ... N82: =N27+N28+N29+N30+N44+N46+N47+N51+N52+N54 -> 42075529
B83: Variable Cost | C83: =C22 -> 1.0673609e+08 | D83: =D22 -> 86796879 | E83: =E22 -> 73067681 | F83: =F22 -> 79323832 | G83: =G22 -> 89043859 | H83: =H22 -> 1.2456445e+08 | I83: =I22 -> 1.2318526e+08 | J83: =J22 -> 1.5863705e+08 | ... N83: =N22 -> 1.5682913e+08
B84: Contribution margin | C84: =C8-C83 -> 27239331 | D84: =D8-D83 -> 22647279 | E84: =E8-E83 -> 14699962 | F84: =F8-F83 -> 13754773 | G84: =G8-G83 -> 18366166 | H84: =H8-H83 -> 21517296 | I84: =I8-I83 -> 3417578.8 | J84: =J8-J83 -> 23981696 | ... N84: =N8-N83 -> -1935975.4
B85: Contribution margin % | C85: =C84/C8 -> 0.20331588 | D85: =D84/D8 -> 0.20692999 | E85: =E84/E8 -> 0.16748726 | F85: =F84/F8 -> 0.14777588 | G85: =G84/G8 -> 0.17099117 | H85: =H84/H8 -> 0.14729627 | I85: =I84/I8 -> 0.026994489 | J85: =J84/J8 -> 0.13132111 | ... N85: =N84/N8 -> -0.012498779
B86: Breakeven sales | C86: =C82/C85 -> 61937942 | D86: =D82/D85 -> 50875742 | E86: =E82/E85 -> 63328256 | F86: =F82/F85 -> 85161149 | G86: =G82/G85 -> 85552983 | H86: =H82/H85 -> 1.0710823e+08 | I86: =I82/I85 -> 8.5055123e+08 | J86: =J82/J85 -> 1.5906072e+08 | ... N86: =N82/N85 -> -3.3663711e+09
B87: Breakeven Tons | C87: =C86/C7 -> 10650.002 | D87: =D86/D7 -> 14608.556 | E87: =E86/E7 -> 23099.524 | F87: =F86/F7 -> 27016.288 | G87: =G86/G7 -> 22948.999 | H87: =H86/H7 -> 27968.2 | I87: =I86/I7 -> 246902.91 | J87: =J86/J7 -> 32753.912 | ... N87: =N86/N7 -> -981463.32

Sheet P&L
A1: ALIF
A2: Profit & Loss
A3: =BS!A3 -> 31 December 2025
C4: MAY 2025 | G4: MAY 2024 | K4: MAY 2023 | O4: MAY 2022 | S4: YTD MAY 2025 | W4: YTD MAY 2024 | AA4: YTD MAY 2023 | AE4: YTD MAY 2022
C5: Consolidated | D5: ALIF | E5: Vision | G5: Consolidated | H5: ALIF | I5: Vision | K5: Consolidated | L5: ALIF | M5: Vision | O5: Consolidated | P5: ALIF | Q5: Vision | S5: Consolidated | T5: ALIF | U5: Vision | W5: Consolidated | X5: ALIF | Y5: Vision | AA5: Consolidated | AB5: ALIF | AC5: Vision | AE5: Consolidated | AF5: ALIF | AG5: Vision
A6: Sales | C6: =SUM(D6:E6) -> #REF! | D6: =-SUMIF(#REF!,A6,#REF!) -> #REF! | E6: =-SUMIF(#REF!,A6,#REF!) -> #REF! | G6: =SUM(H6:I6) -> #REF! | H6: =-SUMIF(ALIF_Y2016!I:I,A6,ALIF_Y2016!F:F)-D6 -> #REF! | I6: =-SUMIF(#REF!,A6,#REF!)-E6 -> #REF! | K6: =SUM(L6:M6) -> #REF! | L6: =D6+H6 -> #REF! | M6: =E6+I6 -> #REF! | O6: =SUM(P6:Q6) -> #REF! | P6: =-SUMIF(#REF!,A6,#REF!) -> #REF! | Q6: =-SUMIF(#REF!,A6,#REF!) -> #REF! | S6: =SUM(T6:U6) -> #REF! | T6: =-SUMIF(#REF!,Q6,#REF!) -> #REF! | U6: =-SUMIF(#REF!,Q6,#REF!) -> #REF! | W6: =SUM(X6:Y6) -> #REF! | X6: =-SUMIF(ALIF_Y2016!Y:Y,Q6,ALIF_Y2016!V:V)-T6 -> #REF! | Y6: =-SUMIF(#REF!,Q6,#REF!)-U6 -> #REF! | AA6: =SUM(AB6:AC6) -> #REF! | AB6: =T6+X6 -> #REF! | AC6: =U6+Y6 -> #REF! | AE6: =SUM(AF6:AG6) -> #REF! | AF6: =-SUMIF(#REF!,Q6,#REF!) -> #REF! | AG6: =-SUMIF(#REF!,Q6,#REF!) -> #REF!
B8: Raw materials | C8: =SUM(D8:E8) -> #REF! | D8: =SUMIF(#REF!,B8,#REF!) -> #REF! | E8: =SUMIF(#REF!,B8,#REF!) -> #REF! | G8: =SUM(H8:I8) -> #REF! | H8: =SUMIF(ALIF_Y2016!I:I,B8,ALIF_Y2016!F:F)-D8 -> #REF! | I8: =SUMIF(#REF!,B8,#REF!)-E8 -> #REF! | K8: =SUM(L8:M8) -> #REF! | L8: =D8+H8 -> #REF! | M8: =E8+I8 -> #REF! | O8: =SUM(P8:Q8) -> #REF! | P8: =SUMIF(#REF!,B8,#REF!) -> #REF! | Q8: =SUMIF(#REF!,B8,#REF!) -> #REF! | S8: =SUM(T8:U8) -> #REF! | T8: =SUMIF(#REF!,R8,#REF!) -> #REF! | U8: =SUMIF(#REF!,R8,#REF!) -> #REF! | W8: =SUM(X8:Y8) -> #REF! | X8: =SUMIF(ALIF_Y2016!Y:Y,R8,ALIF_Y2016!V:V)-T8 -> #REF! | Y8: =SUMIF(#REF!,R8,#REF!)-U8 -> #REF! | AA8: =SUM(AB8:AC8) -> #REF! | AB8: =T8+X8 -> #REF! | AC8: =U8+Y8 -> #REF! | AE8: =SUM(AF8:AG8) -> #REF! | AF8: =SUMIF(#REF!,R8,#REF!) -> #REF! | AG8: =SUMIF(#REF!,R8,#REF!) -> #REF!
B9: Direct Labor | C9: =SUM(D9:E9) -> #REF! | D9: =SUMIF(#REF!,B9,#REF!) -> #REF! | E9: =SUMIF(#REF!,B9,#REF!) -> #REF! | G9: =SUM(H9:I9) -> #REF! | H9: =SUMIF(ALIF_Y2016!I:I,B9,ALIF_Y2016!F:F)-D9 -> #REF! | I9: =SUMIF(#REF!,B9,#REF!)-E9 -> #REF! | K9: =SUM(L9:M9) -> #REF! | L9: =D9+H9 -> #REF! | M9: =E9+I9 -> #REF! | O9: =SUM(P9:Q9) -> #REF! | P9: =SUMIF(#REF!,B9,#REF!) -> #REF! | Q9: =SUMIF(#REF!,B9,#REF!) -> #REF! | S9: =SUM(T9:U9) -> #REF! | T9: =SUMIF(#REF!,R9,#REF!) -> #REF! | U9: =SUMIF(#REF!,R9,#REF!) -> #REF! | W9: =SUM(X9:Y9) -> #REF! | X9: =SUMIF(ALIF_Y2016!Y:Y,R9,ALIF_Y2016!V:V)-T9 -> #REF! | Y9: =SUMIF(#REF!,R9,#REF!)-U9 -> #REF! | AA9: =SUM(AB9:AC9) -> #REF! | AB9: =T9+X9 -> #REF! | AC9: =U9+Y9 -> #REF! | AE9: =SUM(AF9:AG9) -> #REF! | AF9: =SUMIF(#REF!,R9,#REF!) -> #REF! | AG9: =SUMIF(#REF!,R9,#REF!) -> #REF!
B10: Overhead | C10: =SUM(D10:E10) -> #REF! | D10: =SUMIF(#REF!,B10,#REF!) -> #REF! | E10: =SUMIF(#REF!,B10,#REF!) -> #REF! | G10: =SUM(H10:I10) -> #REF! | H10: =SUMIF(ALIF_Y2016!I:I,B10,ALIF_Y2016!F:F)-D10 -> #REF! | I10: =SUMIF(#REF!,B10,#REF!)-E10 -> #REF! | K10: =SUM(L10:M10) -> #REF! | L10: =D10+H10 -> #REF! | M10: =E10+I10 -> #REF! | O10: =SUM(P10:Q10) -> #REF! | P10: =SUMIF(#REF!,B10,#REF!) -> #REF! | Q10: =SUMIF(#REF!,B10,#REF!) -> #REF! | S10: =SUM(T10:U10) -> #REF! | T10: =SUMIF(#REF!,R10,#REF!) -> #REF! | U10: =SUMIF(#REF!,R10,#REF!) -> #REF! | W10: =SUM(X10:Y10) -> #REF! | X10: =SUMIF(ALIF_Y2016!Y:Y,R10,ALIF_Y2016!V:V)-T10 -> #REF! | Y10: =SUMIF(#REF!,R10,#REF!)-U10 -> #REF! | AA10: =SUM(AB10:AC10) -> #REF! | AB10: =T10+X10 -> #REF! | AC10: =U10+Y10 -> #REF! | AE10: =SUM(AF10:AG10) -> #REF! | AF10: =SUMIF(#REF!,R10,#REF!) -> #REF! | AG10: =SUMIF(#REF!,R10,#REF!) -> #REF!
A12: Cost of Sales | C12: =SUM(C8:C11) -> #REF! | D12: =SUM(D8:D11) -> #REF! | E12: =SUM(E8:E11) -> #REF! | G12: =SUM(G8:G11) -> #REF! | H12: =SUM(H8:H11) -> #REF! | I12: =SUM(I8:I11) -> #REF! | K12: =SUM(K8:K11) -> #REF! | L12: =SUM(L8:L11) -> #REF! | M12: =SUM(M8:M11) -> #REF! | O12: =SUM(O8:O11) -> #REF! | P12: =SUM(P8:P11) -> #REF! | Q12: =SUM(Q8:Q11) -> #REF! | S12: =SUM(S8:S11) -> #REF! | T12: =SUM(T8:T11) -> #REF! | U12: =SUM(U8:U11) -> #REF! | W12: =SUM(W8:W11) -> #REF! | X12: =SUM(X8:X11) -> #REF! | Y12: =SUM(Y8:Y11) -> #REF! | AA12: =SUM(AA8:AA11) -> #REF! | AB12: =SUM(AB8:AB11) -> #REF! | AC12: =SUM(AC8:AC11) -> #REF! | AE12: =SUM(AE8:AE11) -> #REF! | AF12: =SUM(AF8:AF11) -> #REF! | AG12: =SUM(AG8:AG11) -> #REF!
A14: GROSS PROFIT | C14: =C6-C12 -> #REF! | D14: =D6-D12 -> #REF! | E14: =E6-E12 -> #REF! | G14: =G6-G12 -> #REF! | H14: =H6-H12 -> #REF! | I14: =I6-I12 -> #REF! | K14: =K6-K12 -> #REF! | L14: =L6-L12 -> #REF! | M14: =M6-M12 -> #REF! | O14: =O6-O12 -> #REF! | P14: =P6-P12 -> #REF! | Q14: =Q6-Q12 -> #REF! | S14: =S6-S12 -> #REF! | T14: =T6-T12 -> #REF! | U14: =U6-U12 -> #REF! | W14: =W6-W12 -> #REF! | X14: =X6-X12 -> #REF! | Y14: =Y6-Y12 -> #REF! | AA14: =AA6-AA12 -> #REF! | AB14: =AB6-AB12 -> #REF! | AC14: =AC6-AC12 -> #REF! | AE14: =AE6-AE12 -> #REF! | AF14: =AF6-AF12 -> #REF! | AG14: =AG6-AG12 -> #REF!
C15: =C14/C6 -> #REF! | D15: =D14/D6 -> #REF! | E15: =E14/E6 -> #REF! | G15: =G14/G6 -> #REF! | H15: =H14/H6 -> #REF! | I15: =I14/I6 -> #REF! | K15: =K14/K6 -> #REF! | L15: =L14/L6 -> #REF! | M15: =M14/M6 -> #REF! | O15: =O14/O6 -> #REF! | P15: =P14/P6 -> #REF! | Q15: =Q14/Q6 -> #REF! | S15: =S14/S6 -> #REF! | T15: =T14/T6 -> #REF! | U15: =U14/U6 -> #REF! | W15: =W14/W6 -> #REF! | X15: =X14/X6 -> #REF! | Y15: =Y14/Y6 -> #REF! | AA15: =AA14/AA6 -> #REF! | AB15: =AB14/AB6 -> #REF! | AC15: =AC14/AC6 -> #REF! | AE15: =AE14/AE6 -> #REF! | AF15: =AF14/AF6 -> #REF! | AG15: =AG14/AG6 -> #REF!
B17: Freight expenses | C17: =SUM(D17:E17) -> #REF! | D17: =SUMIF(#REF!,B17,#REF!) -> #REF! | E17: =SUMIF(#REF!,B17,#REF!) -> #REF! | G17: =SUM(H17:I17) -> #REF! | H17: =SUMIF(ALIF_Y2016!I:I,B17,ALIF_Y2016!F:F)-D17 -> #REF! | I17: =SUMIF(#REF!,B17,#REF!)-E17 -> #REF! | K17: =SUM(L17:M17) -> #REF! | L17: =D17+H17 -> #REF! | M17: =E17+I17 -> #REF! | O17: =SUM(P17:Q17) -> #REF! | P17: =SUMIF(#REF!,B17,#REF!) -> #REF! | Q17: =SUMIF(#REF!,B17,#REF!) -> #REF! | S17: =SUM(T17:U17) -> #REF! | T17: =SUMIF(#REF!,R17,#REF!) -> #REF! | U17: =SUMIF(#REF!,R17,#REF!) -> #REF! | W17: =SUM(X17:Y17) -> #REF! | X17: =SUMIF(ALIF_Y2016!Y:Y,R17,ALIF_Y2016!V:V)-T17 -> #REF! | Y17: =SUMIF(#REF!,R17,#REF!)-U17 -> #REF! | AA17: =SUM(AB17:AC17) -> #REF! | AB17: =T17+X17 -> #REF! | AC17: =U17+Y17 -> #REF! | AE17: =SUM(AF17:AG17) -> #REF! | AF17: =SUMIF(#REF!,R17,#REF!) -> #REF! | AG17: =SUMIF(#REF!,R17,#REF!) -> #REF!
B18: Customs duties and clearances | C18: =SUM(D18:E18) -> #REF! | D18: =SUMIF(#REF!,B18,#REF!) -> #REF! | E18: =SUMIF(#REF!,B18,#REF!) -> #REF! | G18: =SUM(H18:I18) -> #REF! | H18: =SUMIF(ALIF_Y2016!I:I,B18,ALIF_Y2016!F:F)-D18 -> #REF! | I18: =SUMIF(#REF!,B18,#REF!)-E18 -> #REF! | K18: =SUM(L18:M18) -> #REF! | L18: =D18+H18 -> #REF! | M18: =E18+I18 -> #REF! | O18: =SUM(P18:Q18) -> #REF! | P18: =SUMIF(#REF!,B18,#REF!) -> #REF! | Q18: =SUMIF(#REF!,B18,#REF!) -> #REF! | S18: =SUM(T18:U18) -> #REF! | T18: =SUMIF(#REF!,R18,#REF!) -> #REF! | U18: =SUMIF(#REF!,R18,#REF!) -> #REF! | W18: =SUM(X18:Y18) -> #REF! | X18: =SUMIF(ALIF_Y2016!Y:Y,R18,ALIF_Y2016!V:V)-T18 -> #REF! | Y18: =SUMIF(#REF!,R18,#REF!)-U18 -> #REF! | AA18: =SUM(AB18:AC18) -> #REF! | AB18: =T18+X18 -> #REF! | AC18: =U18+Y18 -> #REF! | AE18: =SUM(AF18:AG18) -> #REF! | AF18: =SUMIF(#REF!,R18,#REF!) -> #REF! | AG18: =SUMIF(#REF!,R18,#REF!) -> #REF!
B19: Advertising and promotion expenses | C19: =SUM(D19:E19) -> #REF! | D19: =SUMIF(#REF!,B19,#REF!) -> #REF! | E19: =SUMIF(#REF!,B19,#REF!) -> #REF! | G19: =SUM(H19:I19) -> #REF! | H19: =SUMIF(ALIF_Y2016!I:I,B19,ALIF_Y2016!F:F)-D19 -> #REF! | I19: =SUMIF(#REF!,B19,#REF!)-E19 -> #REF! | K19: =SUM(L19:M19) -> #REF! | L19: =D19+H19 -> #REF! | M19: =E19+I19 -> #REF! | O19: =SUM(P19:Q19) -> #REF! | P19: =SUMIF(#REF!,B19,#REF!) -> #REF! | Q19: =SUMIF(#REF!,B19,#REF!) -> #REF! | S19: =SUM(T19:U19) -> #REF! | T19: =SUMIF(#REF!,R19,#REF!) -> #REF! | U19: =SUMIF(#REF!,R19,#REF!) -> #REF! | W19: =SUM(X19:Y19) -> #REF! | X19: =SUMIF(ALIF_Y2016!Y:Y,R19,ALIF_Y2016!V:V)-T19 -> #REF! | Y19: =SUMIF(#REF!,R19,#REF!)-U19 -> #REF! | AA19: =SUM(AB19:AC19) -> #REF! | AB19: =T19+X19 -> #REF! | AC19: =U19+Y19 -> #REF! | AE19: =SUM(AF19:AG19) -> #REF! | AF19: =SUMIF(#REF!,R19,#REF!) -> #REF! | AG19: =SUMIF(#REF!,R19,#REF!) -> #REF!
B20: Exhibitions | C20: =SUM(D20:E20) -> #REF! | D20: =SUMIF(#REF!,B20,#REF!) -> #REF! | E20: =SUMIF(#REF!,B20,#REF!) -> #REF! | G20: =SUM(H20:I20) -> #REF! | H20: =SUMIF(ALIF_Y2016!I:I,B20,ALIF_Y2016!F:F)-D20 -> #REF! | I20: =SUMIF(#REF!,B20,#REF!)-E20 -> #REF! | K20: =SUM(L20:M20) -> #REF! | L20: =D20+H20 -> #REF! | M20: =E20+I20 -> #REF! | O20: =SUM(P20:Q20) -> #REF! | P20: =SUMIF(#REF!,B20,#REF!) -> #REF! | Q20: =SUMIF(#REF!,B20,#REF!) -> #REF! | S20: =SUM(T20:U20) -> #REF! | T20: =SUMIF(#REF!,R20,#REF!) -> #REF! | U20: =SUMIF(#REF!,R20,#REF!) -> #REF! | W20: =SUM(X20:Y20) -> #REF! | X20: =SUMIF(ALIF_Y2016!Y:Y,R20,ALIF_Y2016!V:V)-T20 -> #REF! | Y20: =SUMIF(#REF!,R20,#REF!)-U20 -> #REF! | AA20: =SUM(AB20:AC20) -> #REF! | AB20: =T20+X20 -> #REF! | AC20: =U20+Y20 -> #REF! | AE20: =SUM(AF20:AG20) -> #REF! | AF20: =SUMIF(#REF!,R20,#REF!) -> #REF! | AG20: =SUMIF(#REF!,R20,#REF!) -> #REF!
B21: Commission expenses | C21: =SUM(D21:E21) -> #REF! | D21: =SUMIF(#REF!,B21,#REF!) -> #REF! | E21: =SUMIF(#REF!,B21,#REF!) -> #REF! | G21: =SUM(H21:I21) -> #REF! | H21: =SUMIF(ALIF_Y2016!I:I,B21,ALIF_Y2016!F:F)-D21 -> #REF! | I21: =SUMIF(#REF!,B21,#REF!)-E21 -> #REF! | K21: =SUM(L21:M21) -> #REF! | L21: =D21+H21 -> #REF! | M21: =E21+I21 -> #REF! | O21: =SUM(P21:Q21) -> #REF! | P21: =SUMIF(#REF!,B21,#REF!) -> #REF! | Q21: =SUMIF(#REF!,B21,#REF!) -> #REF! | S21: =SUM(T21:U21) -> #REF! | T21: =SUMIF(#REF!,R21,#REF!) -> #REF! | U21: =SUMIF(#REF!,R21,#REF!) -> #REF! | W21: =SUM(X21:Y21) -> #REF! | X21: =SUMIF(ALIF_Y2016!Y:Y,R21,ALIF_Y2016!V:V)-T21 -> #REF! | Y21: =SUMIF(#REF!,R21,#REF!)-U21 -> #REF! | AA21: =SUM(AB21:AC21) -> #REF! | AB21: =T21+X21 -> #REF! | AC21: =U21+Y21 -> #REF! | AE21: =SUM(AF21:AG21) -> #REF! | AF21: =SUMIF(#REF!,R21,#REF!) -> #REF! | AG21: =SUMIF(#REF!,R21,#REF!) -> #REF!
B22: Buffet expenses | C22: =SUM(D22:E22) -> #REF! | D22: =SUMIF(#REF!,B22,#REF!) -> #REF! | E22: =SUMIF(#REF!,B22,#REF!) -> #REF! | G22: =SUM(H22:I22) -> #REF! | H22: =SUMIF(ALIF_Y2016!I:I,B22,ALIF_Y2016!F:F)-D22 -> #REF! | I22: =SUMIF(#REF!,B22,#REF!)-E22 -> #REF! | K22: =SUM(L22:M22) -> #REF! | L22: =D22+H22 -> #REF! | M22: =E22+I22 -> #REF! | O22: =SUM(P22:Q22) -> #REF! | P22: =SUMIF(#REF!,B22,#REF!) -> #REF! | Q22: =SUMIF(#REF!,B22,#REF!) -> #REF! | S22: =SUM(T22:U22) -> #REF! | T22: =SUMIF(#REF!,R22,#REF!) -> #REF! | U22: =SUMIF(#REF!,R22,#REF!) -> #REF! | W22: =SUM(X22:Y22) -> #REF! | X22: =SUMIF(ALIF_Y2016!Y:Y,R22,ALIF_Y2016!V:V)-T22 -> #REF! | Y22: =SUMIF(#REF!,R22,#REF!)-U22 -> #REF! | AA22: =SUM(AB22:AC22) -> #REF! | AB22: =T22+X22 -> #REF! | AC22: =U22+Y22 -> #REF! | AE22: =SUM(AF22:AG22) -> #REF! | AF22: =SUMIF(#REF!,R22,#REF!) -> #REF! | AG22: =SUMIF(#REF!,R22,#REF!) -> #REF!
A24: Selling and Distribution | C24: =SUM(C17:C23) -> #REF! | D24: =SUM(D17:D23) -> #REF! | E24: =SUM(E17:E23) -> #REF! | G24: =SUM(G17:G23) -> #REF! | H24: =SUM(H17:H23) -> #REF! | I24: =SUM(I17:I23) -> #REF! | K24: =SUM(K17:K23) -> #REF! | L24: =SUM(L17:L23) -> #REF! | M24: =SUM(M17:M23) -> #REF! | O24: =SUM(O17:O23) -> #REF! | P24: =SUM(P17:P23) -> #REF! | Q24: =SUM(Q17:Q23) -> #REF! | S24: =SUM(S17:S23) -> #REF! | T24: =SUM(T17:T23) -> #REF! | U24: =SUM(U17:U23) -> #REF! | W24: =SUM(W17:W23) -> #REF! | X24: =SUM(X17:X23) -> #REF! | Y24: =SUM(Y17:Y23) -> #REF! | AA24: =SUM(AA17:AA23) -> #REF! | AB24: =SUM(AB17:AB23) -> #REF! | AC24: =SUM(AC17:AC23) -> #REF! | AE24: =SUM(AE17:AE23) -> #REF! | AF24: =SUM(AF17:AF23) -> #REF! | AG24: =SUM(AG17:AG23) -> #REF!
B26: Salaries and wages | C26: =SUM(D26:E26) -> #REF! | D26: =SUMIF(#REF!,B26,#REF!) -> #REF! | E26: =SUMIF(#REF!,B26,#REF!) -> #REF! | G26: =SUM(H26:I26) -> #REF! | H26: =SUMIF(ALIF_Y2016!I:I,B26,ALIF_Y2016!F:F)-D26 -> #REF! | I26: =SUMIF(#REF!,B26,#REF!)-E26 -> #REF! | K26: =SUM(L26:M26) -> #REF! | L26: =D26+H26 -> #REF! | M26: =E26+I26 -> #REF! | O26: =SUM(P26:Q26) -> #REF! | P26: =SUMIF(#REF!,B26,#REF!) -> #REF! | Q26: =SUMIF(#REF!,B26,#REF!) -> #REF! | S26: =SUM(T26:U26) -> #REF! | T26: =SUMIF(#REF!,R26,#REF!) -> #REF! | U26: =SUMIF(#REF!,R26,#REF!) -> #REF! | W26: =SUM(X26:Y26) -> #REF! | X26: =SUMIF(ALIF_Y2016!Y:Y,R26,ALIF_Y2016!V:V)-T26 -> #REF! | Y26: =SUMIF(#REF!,R26,#REF!)-U26 -> #REF! | AA26: =SUM(AB26:AC26) -> #REF! | AB26: =T26+X26 -> #REF! | AC26: =U26+Y26 -> #REF! | AE26: =SUM(AF26:AG26) -> #REF! | AF26: =SUMIF(#REF!,R26,#REF!) -> #REF! | AG26: =SUMIF(#REF!,R26,#REF!) -> #REF!
B27: Utilities | C27: =SUM(D27:E27) -> #REF! | D27: =SUMIF(#REF!,B27,#REF!) -> #REF! | E27: =SUMIF(#REF!,B27,#REF!) -> #REF! | G27: =SUM(H27:I27) -> #REF! | H27: =SUMIF(ALIF_Y2016!I:I,B27,ALIF_Y2016!F:F)-D27 -> #REF! | I27: =SUMIF(#REF!,B27,#REF!)-E27 -> #REF! | K27: =SUM(L27:M27) -> #REF! | L27: =D27+H27 -> #REF! | M27: =E27+I27 -> #REF! | O27: =SUM(P27:Q27) -> #REF! | P27: =SUMIF(#REF!,B27,#REF!) -> #REF! | Q27: =SUMIF(#REF!,B27,#REF!) -> #REF! | S27: =SUM(T27:U27) -> #REF! | T27: =SUMIF(#REF!,R27,#REF!) -> #REF! | U27: =SUMIF(#REF!,R27,#REF!) -> #REF! | W27: =SUM(X27:Y27) -> #REF! | X27: =SUMIF(ALIF_Y2016!Y:Y,R27,ALIF_Y2016!V:V)-T27 -> #REF! | Y27: =SUMIF(#REF!,R27,#REF!)-U27 -> #REF! | AA27: =SUM(AB27:AC27) -> #REF! | AB27: =T27+X27 -> #REF! | AC27: =U27+Y27 -> #REF! | AE27: =SUM(AF27:AG27) -> #REF! | AF27: =SUMIF(#REF!,R27,#REF!) -> #REF! | AG27: =SUMIF(#REF!,R27,#REF!) -> #REF!
B28: Business travel | C28: =SUM(D28:E28) -> #REF! | D28: =SUMIF(#REF!,B28,#REF!) -> #REF! | E28: =SUMIF(#REF!,B28,#REF!) -> #REF! | G28: =SUM(H28:I28) -> #REF! | H28: =SUMIF(ALIF_Y2016!I:I,B28,ALIF_Y2016!F:F)-D28 -> #REF! | I28: =SUMIF(#REF!,B28,#REF!)-E28 -> #REF! | K28: =SUM(L28:M28) -> #REF! | L28: =D28+H28 -> #REF! | M28: =E28+I28 -> #REF! | O28: =SUM(P28:Q28) -> #REF! | P28: =SUMIF(#REF!,B28,#REF!) -> #REF! | Q28: =SUMIF(#REF!,B28,#REF!) -> #REF! | S28: =SUM(T28:U28) -> #REF! | T28: =SUMIF(#REF!,R28,#REF!) -> #REF! | U28: =SUMIF(#REF!,R28,#REF!) -> #REF! | W28: =SUM(X28:Y28) -> #REF! | X28: =SUMIF(ALIF_Y2016!Y:Y,R28,ALIF_Y2016!V:V)-T28 -> #REF! | Y28: =SUMIF(#REF!,R28,#REF!)-U28 -> #REF! | AA28: =SUM(AB28:AC28) -> #REF! | AB28: =T28+X28 -> #REF! | AC28: =U28+Y28 -> #REF! | AE28: =SUM(AF28:AG28) -> #REF! | AF28: =SUMIF(#REF!,R28,#REF!) -> #REF! | AG28: =SUMIF(#REF!,R28,#REF!) -> #REF!
B29: Training | C29: =SUM(D29:E29) -> #REF! | D29: =SUMIF(#REF!,B29,#REF!) -> #REF! | E29: =SUMIF(#REF!,B29,#REF!) -> #REF! | G29: =SUM(H29:I29) -> #REF! | H29: =SUMIF(ALIF_Y2016!I:I,B29,ALIF_Y2016!F:F)-D29 -> #REF! | I29: =SUMIF(#REF!,B29,#REF!)-E29 -> #REF! | K29: =SUM(L29:M29) -> #REF! | L29: =D29+H29 -> #REF! | M29: =E29+I29 -> #REF! | O29: =SUM(P29:Q29) -> #REF! | P29: =SUMIF(#REF!,B29,#REF!) -> #REF! | Q29: =SUMIF(#REF!,B29,#REF!) -> #REF! | S29: =SUM(T29:U29) -> #REF! | T29: =SUMIF(#REF!,R29,#REF!) -> #REF! | U29: =SUMIF(#REF!,R29,#REF!) -> #REF! | W29: =SUM(X29:Y29) -> #REF! | X29: =SUMIF(ALIF_Y2016!Y:Y,R29,ALIF_Y2016!V:V)-T29 -> #REF! | Y29: =SUMIF(#REF!,R29,#REF!)-U29 -> #REF! | AA29: =SUM(AB29:AC29) -> #REF! | AB29: =T29+X29 -> #REF! | AC29: =U29+Y29 -> #REF! | AE29: =SUM(AF29:AG29) -> #REF! | AF29: =SUMIF(#REF!,R29,#REF!) -> #REF! | AG29: =SUMIF(#REF!,R29,#REF!) -> #REF!
B30: IT expenses | C30: =SUM(D30:E30) -> #REF! | D30: =SUMIF(#REF!,B30,#REF!) -> #REF! | E30: =SUMIF(#REF!,B30,#REF!) -> #REF! | G30: =SUM(H30:I30) -> #REF! | H30: =SUMIF(ALIF_Y2016!I:I,B30,ALIF_Y2016!F:F)-D30 -> #REF! | I30: =SUMIF(#REF!,B30,#REF!)-E30 -> #REF! | K30: =SUM(L30:M30) -> #REF! | L30: =D30+H30 -> #REF! | M30: =E30+I30 -> #REF! | O30: =SUM(P30:Q30) -> #REF! | P30: =SUMIF(#REF!,B30,#REF!) -> #REF! | Q30: =SUMIF(#REF!,B30,#REF!) -> #REF! | S30: =SUM(T30:U30) -> #REF! | T30: =SUMIF(#REF!,R30,#REF!) -> #REF! | U30: =SUMIF(#REF!,R30,#REF!) -> #REF! | W30: =SUM(X30:Y30) -> #REF! | X30: =SUMIF(ALIF_Y2016!Y:Y,R30,ALIF_Y2016!V:V)-T30 -> #REF! | Y30: =SUMIF(#REF!,R30,#REF!)-U30 -> #REF! | AA30: =SUM(AB30:AC30) -> #REF! | AB30: =T30+X30 -> #REF! | AC30: =U30+Y30 -> #REF! | AE30: =SUM(AF30:AG30) -> #REF! | AF30: =SUMIF(#REF!,R30,#REF!) -> #REF! | AG30: =SUMIF(#REF!,R30,#REF!) -> #REF!
B31: Govt license and fees (including modon) | C31: =SUM(D31:E31) -> #REF! | D31: =SUMIF(#REF!,B31,#REF!) -> #REF! | E31: =SUMIF(#REF!,B31,#REF!) -> #REF! | G31: =SUM(H31:I31) -> #REF! | H31: =SUMIF(ALIF_Y2016!I:I,B31,ALIF_Y2016!F:F)-D31 -> #REF! | I31: =SUMIF(#REF!,B31,#REF!)-E31 -> #REF! | K31: =SUM(L31:M31) -> #REF! | L31: =D31+H31 -> #REF! | M31: =E31+I31 -> #REF! | O31: =SUM(P31:Q31) -> #REF! | P31: =SUMIF(#REF!,B31,#REF!) -> #REF! | Q31: =SUMIF(#REF!,B31,#REF!) -> #REF! | S31: =SUM(T31:U31) -> #REF! | T31: =SUMIF(#REF!,R31,#REF!) -> #REF! | U31: =SUMIF(#REF!,R31,#REF!) -> #REF! | W31: =SUM(X31:Y31) -> #REF! | X31: =SUMIF(ALIF_Y2016!Y:Y,R31,ALIF_Y2016!V:V)-T31 -> #REF! | Y31: =SUMIF(#REF!,R31,#REF!)-U31 -> #REF! | AA31: =SUM(AB31:AC31) -> #REF! | AB31: =T31+X31 -> #REF! | AC31: =U31+Y31 -> #REF! | AE31: =SUM(AF31:AG31) -> #REF! | AF31: =SUMIF(#REF!,R31,#REF!) -> #REF! | AG31: =SUMIF(#REF!,R31,#REF!) -> #REF!
B32: Rent | C32: =SUM(D32:E32) -> #REF! | D32: =SUMIF(#REF!,B32,#REF!) -> #REF! | E32: =SUMIF(#REF!,B32,#REF!) -> #REF! | G32: =SUM(H32:I32) -> #REF! | H32: =SUMIF(ALIF_Y2016!I:I,B32,ALIF_Y2016!F:F)-D32 -> #REF! | I32: =SUMIF(#REF!,B32,#REF!)-E32 -> #REF! | K32: =SUM(L32:M32) -> #REF! | L32: =D32+H32 -> #REF! | M32: =E32+I32 -> #REF! | O32: =SUM(P32:Q32) -> #REF! | P32: =SUMIF(#REF!,B32,#REF!) -> #REF! | Q32: =SUMIF(#REF!,B32,#REF!) -> #REF! | S32: =SUM(T32:U32) -> #REF! | T32: =SUMIF(#REF!,R32,#REF!) -> #REF! | U32: =SUMIF(#REF!,R32,#REF!) -> #REF! | W32: =SUM(X32:Y32) -> #REF! | X32: =SUMIF(ALIF_Y2016!Y:Y,R32,ALIF_Y2016!V:V)-T32 -> #REF! | Y32: =SUMIF(#REF!,R32,#REF!)-U32 -> #REF! | AA32: =SUM(AB32:AC32) -> #REF! | AB32: =T32+X32 -> #REF! | AC32: =U32+Y32 -> #REF! | AE32: =SUM(AF32:AG32) -> #REF! | AF32: =SUMIF(#REF!,R32,#REF!) -> #REF! | AG32: =SUMIF(#REF!,R32,#REF!) -> #REF!
B33: Back office Support | C33: =SUM(D33:E33) -> #REF! | D33: =SUMIF(#REF!,B33,#REF!) -> #REF! | E33: =SUMIF(#REF!,B33,#REF!) -> #REF! | G33: =SUM(H33:I33) -> #REF! | H33: =SUMIF(ALIF_Y2016!I:I,B33,ALIF_Y2016!F:F)-D33 -> #REF! | I33: =SUMIF(#REF!,B33,#REF!)-E33 -> #REF! | K33: =SUM(L33:M33) -> #REF! | L33: =D33+H33 -> #REF! | M33: =E33+I33 -> #REF! | O33: =SUM(P33:Q33) -> #REF! | P33: =SUMIF(#REF!,B33,#REF!) -> #REF! | Q33: =SUMIF(#REF!,B33,#REF!) -> #REF! | S33: =SUM(T33:U33) -> #REF! | T33: =SUMIF(#REF!,R33,#REF!) -> #REF! | U33: =SUMIF(#REF!,R33,#REF!) -> #REF! | W33: =SUM(X33:Y33) -> #REF! | X33: =SUMIF(ALIF_Y2016!Y:Y,R33,ALIF_Y2016!V:V)-T33 -> #REF! | Y33: =SUMIF(#REF!,R33,#REF!)-U33 -> #REF! | AA33: =SUM(AB33:AC33) -> #REF! | AB33: =T33+X33 -> #REF! | AC33: =U33+Y33 -> #REF! | AE33: =SUM(AF33:AG33) -> #REF! | AF33: =SUMIF(#REF!,R33,#REF!) -> #REF! | AG33: =SUMIF(#REF!,R33,#REF!) -> #REF!
A35: General and Admin | C35: =SUM(C26:C34) -> #REF! | D35: =SUM(D26:D34) -> #REF! | E35: =SUM(E26:E34) -> #REF! | G35: =SUM(G26:G34) -> #REF! | H35: =SUM(H26:H34) -> #REF! | I35: =SUM(I26:I34) -> #REF! | K35: =SUM(K26:K34) -> #REF! | L35: =SUM(L26:L34) -> #REF! | M35: =SUM(M26:M34) -> #REF! | O35: =SUM(O26:O34) -> #REF! | P35: =SUM(P26:P34) -> #REF! | Q35: =SUM(Q26:Q34) -> #REF! | S35: =SUM(S26:S34) -> #REF! | T35: =SUM(T26:T34) -> #REF! | U35: =SUM(U26:U34) -> #REF! | W35: =SUM(W26:W34) -> #REF! | X35: =SUM(X26:X34) -> #REF! | Y35: =SUM(Y26:Y34) -> #REF! | AA35: =SUM(AA26:AA34) -> #REF! | AB35: =SUM(AB26:AB34) -> #REF! | AC35: =SUM(AC26:AC34) -> #REF! | AE35: =SUM(AE26:AE34) -> #REF! | AF35: =SUM(AF26:AF34) -> #REF! | AG35: =SUM(AG26:AG34) -> #REF!
A37: Revised provision on Bad Debts | C37: =SUM(D37:E37) -> #REF! | D37: =SUMIF(#REF!,A37,#REF!) -> #REF! | E37: =SUMIF(#REF!,A37,#REF!) -> #REF! | G37: =SUM(H37:I37) -> #REF! | H37: =SUMIF(ALIF_Y2016!H:H,A37,ALIF_Y2016!F:F)-D37 -> #REF! | I37: =SUMIF(#REF!,A37,#REF!)-E37 -> #REF! | K37: =SUM(L37:M37) -> #REF! | L37: =D37+H37 -> #REF! | M37: =E37+I37 -> #REF! | O37: =SUM(P37:Q37) -> #REF! | P37: =SUMIF(#REF!,A37,#REF!) -> #REF! | Q37: =SUMIF(#REF!,A37,#REF!) -> #REF! | S37: =SUM(T37:U37) -> #REF! | T37: =SUMIF(#REF!,Q37,#REF!) -> #REF! | U37: =SUMIF(#REF!,Q37,#REF!) -> #REF! | W37: =SUM(X37:Y37) -> #REF! | X37: =SUMIF(ALIF_Y2016!X:X,Q37,ALIF_Y2016!V:V)-T37 -> #REF! | Y37: =SUMIF(#REF!,Q37,#REF!)-U37 -> #REF! | AA37: =SUM(AB37:AC37) -> #REF! | AB37: =T37+X37 -> #REF! | AC37: =U37+Y37 -> #REF! | AE37: =SUM(AF37:AG37) -> #REF! | AF37: =SUMIF(#REF!,Q37,#REF!) -> #REF! | AG37: =SUMIF(#REF!,Q37,#REF!) -> #REF!
A38: Inventory Adjustment Expense | C38: =SUM(D38:E38) -> #REF! | D38: =SUMIF(#REF!,A38,#REF!) -> #REF! | E38: =SUMIF(#REF!,A38,#REF!) -> #REF! | G38: =SUM(H38:I38) -> #REF! | H38: =SUMIF(ALIF_Y2016!I:I,A38,ALIF_Y2016!F:F)-D38 -> #REF! | I38: =SUMIF(#REF!,A38,#REF!)-E38 -> #REF! | K38: =SUM(L38:M38) -> #REF! | L38: =D38+H38 -> #REF! | M38: =E38+I38 -> #REF! | O38: =SUM(P38:Q38) -> #REF! | P38: =SUMIF(#REF!,A38,#REF!) -> #REF! | Q38: =SUMIF(#REF!,A38,#REF!) -> #REF! | S38: =SUM(T38:U38) -> #REF! | T38: =SUMIF(#REF!,Q38,#REF!) -> #REF! | U38: =SUMIF(#REF!,Q38,#REF!) -> #REF! | W38: =SUM(X38:Y38) -> #REF! | X38: =SUMIF(ALIF_Y2016!Y:Y,Q38,ALIF_Y2016!V:V)-T38 -> #REF! | Y38: =SUMIF(#REF!,Q38,#REF!)-U38 -> #REF! | AA38: =SUM(AB38:AC38) -> #REF! | AB38: =T38+X38 -> #REF! | AC38: =U38+Y38 -> #REF! | AE38: =SUM(AF38:AG38) -> #REF! | AF38: =SUMIF(#REF!,Q38,#REF!) -> #REF! | AG38: =SUMIF(#REF!,Q38,#REF!) -> #REF!
A40: OPERATING INCOME | C40: =C14-C24-C35-C37-C38 -> #REF! | D40: =D14-D24-D35-D37-D38 -> #REF! | E40: =E14-E24-E35-E37-E38 -> #REF! | G40: =G14-G24-G35-G37-G38 -> #REF! | H40: =H14-H24-H35-H37-H38 -> #REF! | I40: =I14-I24-I35-I37-I38 -> #REF! | K40: =K14-K24-K35-K37-K38 -> #REF! | L40: =L14-L24-L35-L37-L38 -> #REF! | M40: =M14-M24-M35-M37-M38 -> #REF! | O40: =O14-O24-O35-O37-O38 -> #REF! | P40: =P14-P24-P35-P37-P38 -> #REF! | Q40: =Q14-Q24-Q35-Q37-Q38 -> #REF! | S40: =S14-S24-S35-S37-S38 -> #REF! | T40: =T14-T24-T35-T37-T38 -> #REF! | U40: =U14-U24-U35-U37-U38 -> #REF! | W40: =W14-W24-W35-W37-W38 -> #REF! | X40: =X14-X24-X35-X37-X38 -> #REF! | Y40: =Y14-Y24-Y35-Y37-Y38 -> #REF! | AA40: =AA14-AA24-AA35-AA37-AA38 -> #REF! | AB40: =AB14-AB24-AB35-AB37-AB38 -> #REF! | AC40: =AC14-AC24-AC35-AC37-AC38 -> #REF! | AE40: =AE14-AE24-AE35-AE37-AE38 -> #REF! | AF40: =AF14-AF24-AF35-AF37-AF38 -> #REF! | AG40: =AG14-AG24-AG35-AG37-AG38 -> #REF!
A42: Finance cost | C42: =SUM(D42:E42) -> #REF! | D42: =SUMIF(#REF!,A42,#REF!) -> #REF! | E42: =SUMIF(#REF!,A42,#REF!) -> #REF! | G42: =SUM(H42:I42) -> #REF! | H42: =SUMIF(ALIF_Y2016!I:I,A42,ALIF_Y2016!F:F)-D42 -> #REF! | I42: =SUMIF(#REF!,A42,#REF!)-E42 -> #REF! | K42: =SUM(L42:M42) -> #REF! | L42: =D42+H42 -> #REF! | M42: =E42+I42 -> #REF! | O42: =SUM(P42:Q42) -> #REF! | P42: =SUMIF(#REF!,A42,#REF!) -> #REF! | Q42: =SUMIF(#REF!,A42,#REF!) -> #REF! | S42: =SUM(T42:U42) -> #REF! | T42: =SUMIF(#REF!,Q42,#REF!) -> #REF! | U42: =SUMIF(#REF!,Q42,#REF!) -> #REF! | W42: =SUM(X42:Y42) -> #REF! | X42: =SUMIF(ALIF_Y2016!Y:Y,Q42,ALIF_Y2016!V:V)-T42 -> #REF! | Y42: =SUMIF(#REF!,Q42,#REF!)-U42 -> #REF! | AA42: =SUM(AB42:AC42) -> #REF! | AB42: =T42+X42 -> #REF! | AC42: =U42+Y42 -> #REF! | AE42: =SUM(AF42:AG42) -> #REF! | AF42: =SUMIF(#REF!,Q42,#REF!) -> #REF! | AG42: =SUMIF(#REF!,Q42,#REF!) -> #REF!
A43: Depreciation expenses | C43: =SUM(D43:E43) -> #REF! | D43: =SUMIF(#REF!,A43,#REF!) -> #REF! | E43: =SUMIF(#REF!,A43,#REF!) -> #REF! | G43: =SUM(H43:I43) -> #REF! | H43: =SUMIF(ALIF_Y2016!H:H,A43,ALIF_Y2016!F:F)-D43 -> #REF! | I43: =SUMIF(#REF!,A43,#REF!)-E43 -> #REF! | K43: =SUM(L43:M43) -> #REF! | L43: =D43+H43 -> #REF! | M43: =E43+I43 -> #REF! | O43: =SUM(P43:Q43) -> #REF! | P43: =SUMIF(#REF!,A43,#REF!) -> #REF! | Q43: =SUMIF(#REF!,A43,#REF!) -> #REF! | S43: =SUM(T43:U43) -> #REF! | T43: =SUMIF(#REF!,Q43,#REF!) -> #REF! | U43: =SUMIF(#REF!,Q43,#REF!) -> #REF! | W43: =SUM(X43:Y43) -> #REF! | X43: =SUMIF(ALIF_Y2016!X:X,Q43,ALIF_Y2016!V:V)-T43 -> #REF! | Y43: =SUMIF(#REF!,Q43,#REF!)-U43 -> #REF! | AA43: =SUM(AB43:AC43) -> #REF! | AB43: =T43+X43 -> #REF! | AC43: =U43+Y43 -> #REF! | AE43: =SUM(AF43:AG43) -> #REF! | AF43: =SUMIF(#REF!,Q43,#REF!) -> #REF! | AG43: =SUMIF(#REF!,Q43,#REF!) -> #REF!
A44: Zakat expenses | C44: =SUM(D44:E44) -> #REF! | D44: =SUMIF(#REF!,A44,#REF!) -> #REF! | E44: =SUMIF(#REF!,A44,#REF!) -> #REF! | G44: =SUM(H44:I44) -> #REF! | H44: =SUMIF(ALIF_Y2016!I:I,A44,ALIF_Y2016!F:F)-D44 -> #REF! | I44: =SUMIF(#REF!,A44,#REF!)-E44 -> #REF! | K44: =SUM(L44:M44) -> #REF! | L44: =D44+H44 -> #REF! | M44: =E44+I44 -> #REF! | O44: =SUM(P44:Q44) -> #REF! | P44: =-SUMIF(#REF!,A44,#REF!) -> #REF! | Q44: =SUMIF(#REF!,A44,#REF!) -> #REF! | S44: =SUM(T44:U44) -> #REF! | T44: =SUMIF(#REF!,Q44,#REF!) -> #REF! | U44: =SUMIF(#REF!,Q44,#REF!) -> #REF! | W44: =SUM(X44:Y44) -> #REF! | X44: =SUMIF(ALIF_Y2016!Y:Y,Q44,ALIF_Y2016!V:V)-T44 -> #REF! | Y44: =SUMIF(#REF!,Q44,#REF!)-U44 -> #REF! | AA44: =SUM(AB44:AC44) -> #REF! | AB44: =T44+X44 -> #REF! | AC44: =U44+Y44 -> #REF! | AE44: =SUM(AF44:AG44) -> #REF! | AF44: =-SUMIF(#REF!,Q44,#REF!) -> #REF! | AG44: =SUMIF(#REF!,Q44,#REF!) -> #REF!
A46: NET INCOME | C46: =C40-C42-C43-C44 -> #REF! | D46: =D40-D42-D43-D44 -> #REF! | E46: =E40-E42-E43-E44 -> #REF! | G46: =G40-G42-G43-G44 -> #REF! | H46: =H40-H42-H43-H44 -> #REF! | I46: =I40-I42-I43-I44 -> #REF! | K46: =K40-K42-K43-K44 -> #REF! | L46: =L40-L42-L43-L44 -> #REF! | M46: =M40-M42-M43-M44 -> #REF! | O46: =O40-O42-O43-O44 -> #REF! | P46: =P40-P42-P43-P44 -> #REF! | Q46: =Q40-Q42-Q43-Q44 -> #REF! | S46: =S40-S42-S43-S44 -> #REF! | T46: =T40-T42-T43-T44 -> #REF! | U46: =U40-U42-U43-U44 -> #REF! | W46: =W40-W42-W43-W44 -> #REF! | X46: =X40-X42-X43-X44 -> #REF! | Y46: =Y40-Y42-Y43-Y44 -> #REF! | AA46: =AA40-AA42-AA43-AA44 -> #REF! | AB46: =AB40-AB42-AB43-AB44 -> #REF! | AC46: =AC40-AC42-AC43-AC44 -> #REF! | AE46: =AE40-AE42-AE43-AE44 -> #REF! | AF46: =AF40-AF42-AF43-AF44 -> #REF! | AG46: =AG40-AG42-AG43-AG44 -> #REF!
C47: =C46-D46-E46 -> #REF! | D47: =SUMIF(#REF!,"IS",#REF!)+D46 -> #REF! | E47: =SUMIF(#REF!,"IS",#REF!)+E46 -> #REF! | G47: =G46-H46-I46 -> #REF! | H47: =-SUMIF(ALIF_Y2016!G:G,"IS",ALIF_Y2016!F:F)-H46-D46 -> #REF! | I47: =-SUMIF(#REF!,"IS",#REF!)-I46-E46 -> #REF! | K47: =K46-C46-G46 -> #REF! | L47: =L46-D46-H46 -> #REF! | M47: =M46-E46-I46 -> #REF! | O47: =O46-P46-Q46 -> #REF! | S47: =S46-T46-U46 -> #REF! | T47: =SUMIF(#REF!,"IS",#REF!)+T46 -> #REF! | U47: =SUMIF(#REF!,"IS",#REF!)+U46 -> #REF! | W47: =W46-X46-Y46 -> #REF! | X47: =-SUMIF(ALIF_Y2016!W:W,"IS",ALIF_Y2016!V:V)-X46-T46 -> #REF! | Y47: =-SUMIF(#REF!,"IS",#REF!)-Y46-U46 -> #REF! | AA47: =AA46-S46-W46 -> #REF! | AB47: =AB46-T46-X46 -> #REF! | AC47: =AC46-U46-Y46 -> #REF! | AE47: =AE46-AF46-AG46 -> #REF!
C49: Conso | D49: ALIF | E49: VH | G49: Conso | H49: ALIF_Apr | I49: VH | K49: Conso | L49: ALIF_Apr | M49: VH | O49: Conso | P49: ALIF | Q49: VH | S49: Conso | T49: ALIF | U49: VH | W49: Conso | X49: ALIF_Apr | Y49: VH | AA49: Conso | AB49: ALIF_Apr | AC49: VH | AE49: Conso | AF49: ALIF | AG49: VH
B50: Sales | C50: =C6 -> #REF! | D50: =D6 -> #REF! | E50: =E6 -> #REF! | G50: =G6 -> #REF! | H50: =H6 -> #REF! | I50: =I6 -> #REF! | K50: =K6 -> #REF! | L50: =L6 -> #REF! | M50: =M6 -> #REF! | O50: =O6 -> #REF! | P50: =P6 -> #REF! | Q50: =Q6 -> #REF! | S50: =S6 -> #REF! | T50: =T6 -> #REF! | U50: =U6 -> #REF! | W50: =W6 -> #REF! | X50: =X6 -> #REF! | Y50: =Y6 -> #REF! | AA50: =AA6 -> #REF! | AB50: =AB6 -> #REF! | AC50: =AC6 -> #REF! | AE50: =AE6 -> #REF! | AF50: =AF6 -> #REF! | AG50: =AG6 -> #REF!
B51: Gros profit | C51: =C14 -> #REF! | D51: =D14 -> #REF! | E51: =E14 -> #REF! | G51: =G14 -> #REF! | H51: =H14 -> #REF! | I51: =I14 -> #REF! | K51: =K14 -> #REF! | L51: =L14 -> #REF! | M51: =M14 -> #REF! | O51: =O14 -> #REF! | P51: =P14 -> #REF! | Q51: =Q14 -> #REF! | S51: =S14 -> #REF! | T51: =T14 -> #REF! | U51: =U14 -> #REF! | W51: =W14 -> #REF! | X51: =X14 -> #REF! | Y51: =Y14 -> #REF! | AA51: =AA14 -> #REF! | AB51: =AB14 -> #REF! | AC51: =AC14 -> #REF! | AE51: =AE14 -> #REF! | AF51: =AF14 -> #REF! | AG51: =AG14 -> #REF!
B52: Net profit | C52: =C46 -> #REF! | D52: =D46 -> #REF! | E52: =E46 -> #REF! | G52: =G46 -> #REF! | H52: =H46 -> #REF! | I52: =I46 -> #REF! | K52: =K46 -> #REF! | L52: =L46 -> #REF! | M52: =M46 -> #REF! | O52: =O46 -> #REF! | P52: =P46 -> #REF! | Q52: =Q46 -> #REF! | S52: =S46 -> #REF! | T52: =T46 -> #REF! | U52: =U46 -> #REF! | W52: =W46 -> #REF! | X52: =X46 -> #REF! | Y52: =Y46 -> #REF! | AA52: =AA46 -> #REF! | AB52: =AB46 -> #REF! | AC52: =AC46 -> #REF! | AE52: =AE46 -> #REF! | AF52: =AF46 -> #REF! | AG52: =AG46 -> #REF!
B53: EBITDA | C53: =C40 -> #REF! | D53: =D40 -> #REF! | E53: =E40 -> #REF! | G53: =G40 -> #REF! | H53: =H40 -> #REF! | I53: =I40 -> #REF! | K53: =K40 -> #REF! | L53: =L40 -> #REF! | M53: =M40 -> #REF! | O53: =O40 -> #REF! | P53: =P40 -> #REF! | Q53: =Q40 -> #REF! | S53: =S40 -> #REF! | T53: =T40 -> #REF! | U53: =U40 -> #REF! | W53: =W40 -> #REF! | X53: =X40 -> #REF! | Y53: =Y40 -> #REF! | AA53: =AA40 -> #REF! | AB53: =AB40 -> #REF! | AC53: =AC40 -> #REF! | AE53: =AE40 -> #REF! | AF53: =AF40 -> #REF! | AG53: =AG40 -> #REF!
B54: Return on Equity | C54: =C46/BS!E42 -> #REF! | D54: =D46/BS!F42 -> #REF! | E54: =E46/BS!G42 -> #REF! | G54: =G46/BS!I42 -> #REF! | H54: =H46/BS!#REF! -> #REF! | I54: =I46/BS!#REF! -> #REF! | K54: =K46/BS!#REF! -> #REF! | L54: =L46/BS!#REF! -> #REF! | M54: =M46/BS!#REF! -> #REF! | O54: =O46/BS!#REF! -> #REF! | P54: =P46/BS!#REF! -> #REF! | Q54: =Q46/BS!#REF! -> #REF! | S54: =S46/BS!#REF! -> #REF! | T54: =T46/BS!#REF! -> #REF! | U54: =U46/BS!#REF! -> #REF! | W54: =W46/BS!#REF! -> #REF! | X54: =X46/BS!#REF! -> #REF! | Y54: =Y46/BS!#REF! -> #REF! | AA54: =AA46/BS!#REF! -> #REF! | AB54: =AB46/BS!#REF! -> #REF! | AC54: =AC46/BS!#REF! -> #REF! | AE54: =AE46/BS!#REF! -> #REF! | AF54: =AF46/BS!#REF! -> #REF! | AG54: =AG46/BS!#REF! -> #REF!
B56: COGS | C56: =C12/C6 -> #REF! | D56: =D12/D6 -> #REF! | E56: =E12/E6 -> #REF! | G56: =G12/G6 -> #REF! | H56: =H12/H6 -> #REF! | I56: =I12/I6 -> #REF! | K56: =K12/K6 -> #REF! | L56: =L12/L6 -> #REF! | M56: =M12/M6 -> #REF! | S56: =S12/S6 -> #REF! | T56: =T12/T6 -> #REF! | U56: =U12/U6 -> #REF! | W56: =W12/W6 -> #REF! | X56: =X12/X6 -> #REF! | Y56: =Y12/Y6 -> #REF! | AA56: =AA12/AA6 -> #REF! | AB56: =AB12/AB6 -> #REF! | AC56: =AC12/AC6 -> #REF!
B57: GP | C57: =C14/C6 -> #REF! | D57: =D14/D6 -> #REF! | E57: =E14/E6 -> #REF! | G57: =G14/G6 -> #REF! | H57: =H14/H6 -> #REF! | I57: =I14/I6 -> #REF! | K57: =K14/K6 -> #REF! | L57: =L14/L6 -> #REF! | M57: =M14/M6 -> #REF! | S57: =S14/S6 -> #REF! | T57: =T14/T6 -> #REF! | U57: =U14/U6 -> #REF! | W57: =W14/W6 -> #REF! | X57: =X14/X6 -> #REF! | Y57: =Y14/Y6 -> #REF! | AA57: =AA14/AA6 -> #REF! | AB57: =AB14/AB6 -> #REF! | AC57: =AC14/AC6 -> #REF!
B58: Selling | C58: =C24/C6 -> #REF! | D58: =D24/D6 -> #REF! | E58: =E24/E6 -> #REF! | G58: =G24/G6 -> #REF! | H58: =H24/H6 -> #REF! | I58: =I24/I6 -> #REF! | K58: =K24/K6 -> #REF! | L58: =L24/L6 -> #REF! | M58: =M24/M6 -> #REF! | S58: =S24/S6 -> #REF! | T58: =T24/T6 -> #REF! | U58: =U24/U6 -> #REF! | W58: =W24/W6 -> #REF! | X58: =X24/X6 -> #REF! | Y58: =Y24/Y6 -> #REF! | AA58: =AA24/AA6 -> #REF! | AB58: =AB24/AB6 -> #REF! | AC58: =AC24/AC6 -> #REF!
B59: G&A | C59: =C35/C6 -> #REF! | D59: =D35/D6 -> #REF! | E59: =E35/E6 -> #REF! | G59: =G35/G6 -> #REF! | H59: =H35/H6 -> #REF! | I59: =I35/I6 -> #REF! | K59: =K35/K6 -> #REF! | L59: =L35/L6 -> #REF! | M59: =M35/M6 -> #REF! | S59: =S35/S6 -> #REF! | T59: =T35/T6 -> #REF! | U59: =U35/U6 -> #REF! | W59: =W35/W6 -> #REF! | X59: =X35/X6 -> #REF! | Y59: =Y35/Y6 -> #REF! | AA59: =AA35/AA6 -> #REF! | AB59: =AB35/AB6 -> #REF! | AC59: =AC35/AC6 -> #REF!
B60: Finance Cost | C60: =C42/C6 -> #REF! | D60: =D42/D6 -> #REF! | E60: =E42/E6 -> #REF! | G60: =G42/G6 -> #REF! | H60: =H42/H6 -> #REF! | I60: =I42/I6 -> #REF! | K60: =K42/K6 -> #REF! | L60: =L42/L6 -> #REF! | M60: =M42/M6 -> #REF! | S60: =S42/S6 -> #REF! | T60: =T42/T6 -> #REF! | U60: =U42/U6 -> #REF! | W60: =W42/W6 -> #REF! | X60: =X42/X6 -> #REF! | Y60: =Y42/Y6 -> #REF! | AA60: =AA42/AA6 -> #REF! | AB60: =AB42/AB6 -> #REF! | AC60: =AC42/AC6 -> #REF!
B61: Depreciation | C61: =C43/C6 -> #REF! | D61: =D43/D6 -> #REF! | E61: =E43/E6 -> #REF! | G61: =G43/G6 -> #REF! | H61: =H43/H6 -> #REF! | I61: =I43/I6 -> #REF! | K61: =K43/K6 -> #REF! | L61: =L43/L6 -> #REF! | M61: =M43/M6 -> #REF! | S61: =S43/S6 -> #REF! | T61: =T43/T6 -> #REF! | U61: =U43/U6 -> #REF! | W61: =W43/W6 -> #REF! | X61: =X43/X6 -> #REF! | Y61: =Y43/Y6 -> #REF! | AA61: =AA43/AA6 -> #REF! | AB61: =AB43/AB6 -> #REF! | AC61: =AC43/AC6 -> #REF!
C63: -8809144.3 | D63: -8403518.2 | E63: -405626.16 | G63: -8809144.3 | H63: -8403518.2 | I63: -405626.16 | K63: -8809144.3 | L63: -8403518.2 | M63: -405626.16 | S63: -8809144.3 | T63: -8403518.2 | U63: -405626.16 | W63: -8809144.3 | X63: -8403518.2 | Y63: -405626.16 | AA63: -8809144.3 | AB63: -8403518.2 | AC63: -405626.16

Sheet CF
A1: AIMS INDUSTRIAL
A2: Cash Flow
A3: =BS!A3 -> 31 December 2025
B4: Jan | C4: Feb | D4: Mar | E4: Apr | F4: May | G4: Jun | H4: Jul | I4: Aug | J4: Sep | K4: Oct | L4: Nov | N4: Ytd | P4: Q1 | Q4: Q2 | R4: Q3 | S4: =K4&" - "&L4 -> Oct - Nov | T4: Ytd
A5: OPERATING ACTIVITIES
A6: Profit for the year before zakat | B6: ='P&L_2014-2025'!#REF! -> #REF! | C6: ='P&L_2014-2025'!#REF! -> #REF! | D6: ='P&L_2014-2025'!#REF! -> #REF! | E6: ='P&L_2014-2025'!#REF! -> #REF! | F6: ='P&L_2014-2025'!#REF! -> #REF! | G6: ='P&L_2014-2025'!#REF! -> #REF! | H6: ='P&L_2014-2025'!#REF! -> #REF! | I6: ='P&L_2014-2025'!#REF! -> #REF! | ... L6: ='P&L_2014-2025'!#REF! -> #REF! | N6: =SUM(B6:M6) -> #REF! | P6: =B6+C6+D6 -> #REF! | Q6: =E6+F6+G6 -> #REF! | R6: =H6+I6+J6 -> #REF! | S6: =K6+L6 -> #REF! | T6: =SUM(P6:S6) -> #REF!
A7: Adjustments for:
A8: Depreciation | B8: ='P&L_2014-2025'!#REF! -> #REF! | C8: ='P&L_2014-2025'!#REF! -> #REF! | D8: ='P&L_2014-2025'!#REF! -> #REF! | E8: ='P&L_2014-2025'!#REF! -> #REF! | F8: ='P&L_2014-2025'!#REF! -> #REF! | G8: ='P&L_2014-2025'!#REF! -> #REF! | H8: ='P&L_2014-2025'!#REF! -> #REF! | I8: ='P&L_2014-2025'!#REF! -> #REF! | ... L8: ='P&L_2014-2025'!#REF! -> #REF! | N8: =SUM(B8:M8) -> #REF! | P8: =B8+C8+D8 -> #REF! | Q8: =E8+F8+G8 -> #REF! | R8: =H8+I8+J8 -> #REF! | S8: =K8+L8 -> #REF! | T8: =SUM(P8:S8) -> #REF!
A9: Amortization of the right of use the asset | B9: =-BS!I16 -> -1995348 | C9: =-BS!O16 -> -2545644.4 | D9: =-BS!#REF! -> #REF! | E9: =-BS!#REF! -> #REF! | F9: =-BS!#REF! -> #REF! | G9: =-BS!#REF! -> #REF! | H9: =-BS!#REF! -> #REF! | I9: =-BS!#REF! -> #REF! | J9: =-BS!#REF! -> #REF! | K9: =-BS!#REF! -> #REF! | L9: =-BS!#REF! -> #REF! | N9: =SUM(B9:M9) -> #REF! | P9: =B9+C9+D9 -> #REF! | Q9: =E9+F9+G9 -> #REF! | R9: =H9+I9+J9 -> #REF! | S9: =K9+L9 -> #REF! | T9: =SUM(P9:S9) -> #REF!
A10: Provision of Expected credit loss | N10: =SUM(B10:M10) -> 0 | P10: =B10+C10+D10 -> 0 | Q10: =E10+F10+G10 -> 0 | R10: =H10+I10+J10 -> 0 | S10: =K10+L10 -> 0 | T10: =SUM(P10:S10) -> 0
A11: Provision for inventory write-off | B11: ='P&L_2014-2025'!#REF! -> #REF! | C11: ='P&L_2014-2025'!#REF! -> #REF! | D11: ='P&L_2014-2025'!#REF! -> #REF! | E11: ='P&L_2014-2025'!#REF! -> #REF! | F11: ='P&L_2014-2025'!#REF! -> #REF! | G11: ='P&L_2014-2025'!#REF! -> #REF! | H11: ='P&L_2014-2025'!#REF! -> #REF! | I11: ='P&L_2014-2025'!#REF! -> #REF! | ... L11: ='P&L_2014-2025'!#REF! -> #REF! | N11: =SUM(B11:M11) -> #REF! | P11: =B11+C11+D11 -> #REF! | Q11: =E11+F11+G11 -> #REF! | R11: =H11+I11+J11 -> #REF! | S11: =K11+L11 -> #REF! | T11: =SUM(P11:S11) -> #REF!
A12: End of service indemnities | B12: =BS!I32 -> 4294641 | C12: =BS!O32 -> 4431984.9 | D12: =BS!#REF! -> #REF! | E12: =BS!#REF! -> #REF! | F12: =BS!#REF! -> #REF! | G12: =BS!#REF! -> #REF! | H12: =BS!#REF! -> #REF! | I12: =BS!#REF! -> #REF! | J12: =BS!#REF! -> #REF! | K12: =BS!#REF! -> #REF! | L12: =BS!#REF! -> #REF! | N12: =SUM(B12:M12) -> #REF! | P12: =B12+C12+D12 -> #REF! | Q12: =E12+F12+G12 -> #REF! | R12: =H12+I12+J12 -> #REF! | S12: =K12+L12 -> #REF! | T12: =SUM(P12:S12) -> #REF!
A13: provision for evacuation | B13: =BS!I33 -> 4120000 | C13: =BS!O33 -> 4862172.9 | D13: =BS!#REF! -> #REF! | E13: =BS!#REF! -> #REF! | F13: =BS!#REF! -> #REF! | G13: =BS!#REF! -> #REF! | H13: =BS!#REF! -> #REF! | I13: =BS!#REF! -> #REF! | J13: =BS!#REF! -> #REF! | K13: =BS!#REF! -> #REF! | L13: =BS!#REF! -> #REF! | N13: =SUM(B13:M13) -> #REF! | P13: =B13+C13+D13 -> #REF! | Q13: =E13+F13+G13 -> #REF! | R13: =H13+I13+J13 -> #REF! | S13: =K13+L13 -> #REF! | T13: =SUM(P13:S13) -> #REF!
A14: Finance charge | B14: ='P&L_2014-2025'!#REF! -> #REF! | C14: ='P&L_2014-2025'!#REF! -> #REF! | D14: ='P&L_2014-2025'!#REF! -> #REF! | E14: ='P&L_2014-2025'!#REF! -> #REF! | F14: ='P&L_2014-2025'!#REF! -> #REF! | G14: ='P&L_2014-2025'!#REF! -> #REF! | H14: ='P&L_2014-2025'!#REF! -> #REF! | I14: ='P&L_2014-2025'!#REF! -> #REF! | ... L14: ='P&L_2014-2025'!#REF! -> #REF! | N14: =SUM(B14:M14) -> #REF! | P14: =B14+C14+D14 -> #REF! | Q14: =E14+F14+G14 -> #REF! | R14: =H14+I14+J14 -> #REF! | S14: =K14+L14 -> #REF! | T14: =SUM(P14:S14) -> #REF!
A16: Working capital changes: | B16: =SUM(B6:B15) -> #REF! | C16: =SUM(C6:C15) -> #REF! | D16: =SUM(D6:D15) -> #REF! | E16: =SUM(E6:E15) -> #REF! | F16: =SUM(F6:F15) -> #REF! | G16: =SUM(G6:G15) -> #REF! | H16: =SUM(H6:H15) -> #REF! | I16: =SUM(I6:I15) -> #REF! | ... L16: =SUM(L6:L15) -> #REF! | N16: =SUM(N6:N15) -> #REF! | P16: =SUM(P6:P15) -> #REF! | Q16: =SUM(Q6:Q15) -> #REF! | R16: =SUM(R6:R15) -> #REF! | S16: =SUM(S6:S15) -> #REF! | T16: =SUM(T6:T15) -> #REF!
A17: (Increase)/decrease current assets
A18: Inventory | B18: =-BS!I10-B11 -> #REF! | C18: =-BS!O10-C11 -> #REF! | D18: =-BS!#REF!-D11 -> #REF! | E18: =-BS!#REF!-E11 -> #REF! | F18: =-BS!#REF!-F11 -> #REF! | G18: =-BS!#REF!-G11 -> #REF! | H18: =-BS!#REF!-H11 -> #REF! | I18: =-BS!#REF!-I11 -> #REF! | J18: =-BS!#REF!-J11 -> #REF! | K18: =-BS!#REF!-K11 -> #REF! | L18: =-BS!#REF!-L11 -> #REF! | N18: =SUM(B18:M18) -> #REF! | P18: =B18+C18+D18 -> #REF! | Q18: =E18+F18+G18 -> #REF! | R18: =H18+I18+J18 -> #REF! | S18: =K18+L18 -> #REF! | T18: =SUM(P18:S18) -> #REF!
A19: Prepayments and other receivables | B19: =-BS!I9 -> -8522666 | C19: =-BS!O9 -> -10384903 | D19: =-BS!#REF! -> #REF! | E19: =-BS!#REF! -> #REF! | F19: =-BS!#REF! -> #REF! | G19: =-BS!#REF! -> #REF! | H19: =-BS!#REF! -> #REF! | I19: =-BS!#REF! -> #REF! | J19: =-BS!#REF! -> #REF! | K19: =-BS!#REF! -> #REF! | L19: =-BS!#REF! -> #REF! | N19: =SUM(B19:M19) -> #REF! | P19: =B19+C19+D19 -> #REF! | Q19: =E19+F19+G19 -> #REF! | R19: =H19+I19+J19 -> #REF! | S19: =K19+L19 -> #REF! | T19: =SUM(P19:S19) -> #REF!
A20: Due from RP | B20: =-BS!I14 -> 0 | C20: =-BS!O14 -> 0 | D20: =-BS!#REF! -> #REF! | E20: =-BS!#REF! -> #REF! | F20: =-BS!#REF! -> #REF! | G20: =-BS!#REF! -> #REF! | H20: =-BS!#REF! -> #REF! | I20: =-BS!#REF! -> #REF! | J20: =-BS!#REF! -> #REF! | K20: =-BS!#REF! -> #REF! | L20: =-BS!#REF! -> #REF! | N20: =SUM(B20:M20) -> #REF! | P20: =B20+C20+D20 -> #REF! | Q20: =E20+F20+G20 -> #REF! | R20: =H20+I20+J20 -> #REF! | S20: =K20+L20 -> #REF! | T20: =SUM(P20:S20) -> #REF!
A21: Trade receivables | B21: =-BS!I8 -> -40286632 | C21: =-BS!O8 -> -34614828 | D21: =-BS!#REF! -> #REF! | E21: =-BS!#REF! -> #REF! | F21: =-BS!#REF! -> #REF! | G21: =-BS!#REF! -> #REF! | H21: =-BS!#REF! -> #REF! | I21: =-BS!#REF! -> #REF! | J21: =-BS!#REF! -> #REF! | K21: =-BS!#REF! -> #REF! | L21: =-BS!#REF! -> #REF! | N21: =SUM(B21:M21) -> #REF! | P21: =B21+C21+D21 -> #REF! | Q21: =E21+F21+G21 -> #REF! | R21: =H21+I21+J21 -> #REF! | S21: =K21+L21 -> #REF! | T21: =SUM(P21:S21) -> #REF!
A22: Due to RP | B22: =BS!I31 -> 502289.05 | C22: =BS!O31 -> 30600617 | D22: =BS!#REF! -> #REF! | E22: =BS!#REF! -> #REF! | F22: =BS!#REF! -> #REF! | G22: =BS!#REF! -> #REF! | H22: =BS!#REF! -> #REF! | I22: =BS!#REF! -> #REF! | J22: =BS!#REF! -> #REF! | K22: =BS!#REF! -> #REF! | L22: =BS!#REF! -> #REF! | N22: =SUM(B22:M22) -> #REF! | P22: =B22+C22+D22 -> #REF! | Q22: =E22+F22+G22 -> #REF! | R22: =H22+I22+J22 -> #REF! | S22: =K22+L22 -> #REF! | T22: =SUM(P22:S22) -> #REF!
A23: Provision for evacuation | S23: =K23+L23 -> 0
A24: Account payable, and other credit balances | B24: =BS!I26 -> 6947242 | C24: =BS!O26 -> 24407376 | D24: =BS!#REF! -> #REF! | E24: =BS!#REF! -> #REF! | F24: =BS!#REF! -> #REF! | G24: =BS!#REF! -> #REF! | H24: =BS!#REF! -> #REF! | I24: =BS!#REF! -> #REF! | J24: =BS!#REF! -> #REF! | K24: =BS!#REF! -> #REF! | L24: =BS!#REF! -> #REF! | N24: =SUM(B24:M24) -> #REF! | P24: =B24+C24+D24 -> #REF! | Q24: =E24+F24+G24 -> #REF! | R24: =H24+I24+J24 -> #REF! | S24: =K24+L24 -> #REF! | T24: =SUM(P24:S24) -> #REF!
A26: Cash from operations | B26: =SUM(B16:B24) -> #REF! | C26: =SUM(C16:C24) -> #REF! | D26: =SUM(D16:D24) -> #REF! | E26: =SUM(E16:E24) -> #REF! | F26: =SUM(F16:F24) -> #REF! | G26: =SUM(G16:G24) -> #REF! | H26: =SUM(H16:H24) -> #REF! | I26: =SUM(I16:I24) -> #REF! | ... L26: =SUM(L16:L24) -> #REF! | N26: =SUM(N16:N24) -> #REF! | P26: =SUM(P16:P24) -> #REF! | Q26: =SUM(Q16:Q24) -> #REF! | R26: =SUM(R16:R24) -> #REF! | S26: =SUM(S16:S24) -> #REF! | T26: =SUM(T16:T24) -> #REF!
A28: Finance charge paid
A29: Zakat paid | B29: =BS!I25 -> 983057 | C29: =BS!O25 -> 0 | D29: =BS!#REF! -> #REF! | E29: =BS!#REF! -> #REF! | F29: =BS!#REF! -> #REF! | G29: =BS!#REF! -> #REF! | H29: =BS!#REF! -> #REF! | I29: =BS!#REF! -> #REF! | J29: =BS!#REF! -> #REF! | K29: =BS!#REF! -> #REF! | L29: =BS!#REF! -> #REF! | N29: =SUM(B29:M29) -> #REF! | P29: =B29+C29+D29 -> #REF! | Q29: =E29+F29+G29 -> #REF! | R29: =H29+I29+J29 -> #REF! | S29: =K29+L29 -> #REF! | T29: =SUM(P29:S29) -> #REF!
A30: Zakat diff | S30: =K30+L30 -> 0
A31: Employees’ end of service benefits paid | S31: =K31+L31 -> 0
A33: Net cash from operating activities | B33: =SUM(B26:B31) -> #REF! | C33: =SUM(C26:C31) -> #REF! | D33: =SUM(D26:D31) -> #REF! | E33: =SUM(E26:E31) -> #REF! | F33: =SUM(F26:F31) -> #REF! | G33: =SUM(G26:G31) -> #REF! | H33: =SUM(H26:H31) -> #REF! | I33: =SUM(I26:I31) -> #REF! | ... L33: =SUM(L26:L31) -> #REF! | N33: =SUM(N26:N31) -> #REF! | P33: =SUM(P26:P31) -> #REF! | Q33: =SUM(Q26:Q31) -> #REF! | R33: =SUM(R26:R31) -> #REF! | S33: =SUM(S26:S31) -> #REF! | T33: =SUM(T26:T31) -> #REF!
A35: INVESTING ACTIVITIES
A36: Additions of property, plant and equipment | B36: =-BS!I15-B8 -> #REF! | C36: =-BS!O15-C8 -> #REF! | D36: =-BS!#REF!-D8 -> #REF! | E36: =-BS!#REF!-E8 -> #REF! | F36: =-BS!#REF!-F8 -> #REF! | G36: =-BS!#REF!-G8 -> #REF! | H36: =-BS!#REF!-H8 -> #REF! | I36: =-BS!#REF!-I8 -> #REF! | J36: =-BS!#REF!-J8 -> #REF! | K36: =-BS!#REF!-K8 -> #REF! | L36: =-BS!#REF!-L8 -> #REF! | N36: =SUM(B36:M36) -> #REF! | P36: =B36+C36+D36 -> #REF! | Q36: =E36+F36+G36 -> #REF! | R36: =H36+I36+J36 -> #REF! | S36: =K36+L36 -> #REF! | T36: =SUM(P36:S36) -> #REF!
A37: Right of use | B37: =-BS!I16-B9 -> 0 | C37: =-BS!O16-C9 -> 0 | D37: =-BS!#REF!-D9 -> #REF! | E37: =-BS!#REF!-E9 -> #REF! | F37: =-BS!#REF!-F9 -> #REF! | G37: =-BS!#REF!-G9 -> #REF! | H37: =-BS!#REF!-H9 -> #REF! | I37: =-BS!#REF!-I9 -> #REF! | J37: =-BS!#REF!-J9 -> #REF! | K37: =-BS!#REF!-K9 -> #REF! | L37: =-BS!#REF!-L9 -> #REF! | N37: =SUM(B37:M37) -> #REF! | P37: =B37+C37+D37 -> #REF! | Q37: =E37+F37+G37 -> #REF! | R37: =H37+I37+J37 -> #REF! | S37: =K37+L37 -> #REF! | T37: =SUM(P37:S37) -> #REF!
A38: Dissposals | S38: =K38+L38 -> 0
A40: Net cash from (used in) investing activities | B40: =SUM(B36:B39) -> #REF! | C40: =SUM(C36:C39) -> #REF! | D40: =SUM(D36:D39) -> #REF! | E40: =SUM(E36:E39) -> #REF! | F40: =SUM(F36:F39) -> #REF! | G40: =SUM(G36:G39) -> #REF! | H40: =SUM(H36:H39) -> #REF! | I40: =SUM(I36:I39) -> #REF! | ... L40: =SUM(L36:L39) -> #REF! | N40: =SUM(N36:N39) -> #REF! | P40: =SUM(P36:P39) -> #REF! | Q40: =SUM(Q36:Q39) -> #REF! | R40: =SUM(R36:R39) -> #REF! | S40: =SUM(S36:S39) -> #REF! | T40: =SUM(T36:T39) -> #REF!
A42: FINANCING ACTIVITIES | S42: =K42+L42 -> 0
A43: Financial Lease - Paid | S43: =K43+L43 -> 0
A44: Lease liability | B44: =BS!I30+BS!I24 -> 1874374 | C44: =BS!O30+BS!O24 -> 2585822 | D44: =BS!#REF!+BS!#REF! -> #REF! | E44: =BS!#REF!+BS!#REF! -> #REF! | F44: =BS!#REF!+BS!#REF! -> #REF! | G44: =BS!#REF!+BS!#REF! -> #REF! | H44: =BS!#REF!+BS!#REF! -> #REF! | I44: =BS!#REF!+BS!#REF! -> #REF! | J44: =BS!#REF!+BS!#REF! -> #REF! | K44: =BS!#REF!+BS!#REF! -> #REF! | L44: =BS!#REF!+BS!#REF! -> #REF! | N44: =SUM(B44:M44) -> #REF! | P44: =B44+C44+D44 -> #REF! | Q44: =E44+F44+G44 -> #REF! | R44: =H44+I44+J44 -> #REF! | S44: =K44+L44 -> #REF! | T44: =SUM(P44:S44) -> #REF!
A45: Increase is share capital | P45: =B45+C45+D45 -> 0 | Q45: =E45+F45+G45 -> 0 | R45: =H45+I45+J45 -> 0 | S45: =K45+L45 -> 0 | T45: =SUM(P45:S45) -> 0
A46: cash and cash eq | P46: =B46+C46+D46 -> 0 | Q46: =E46+F46+G46 -> 0 | R46: =H46+I46+J46 -> 0 | S46: =K46+L46 -> 0 | T46: =SUM(P46:S46) -> 0
A47: Bank Facilities | B47: =BS!I23-B14 -> #REF! | C47: =BS!O23-C14 -> #REF! | D47: =BS!#REF!-D14 -> #REF! | E47: =BS!#REF!-E14 -> #REF! | F47: =BS!#REF!-F14 -> #REF! | G47: =BS!#REF!-G14 -> #REF! | H47: =BS!#REF!-H14 -> #REF! | I47: =BS!#REF!-I14 -> #REF! | J47: =BS!#REF!-J14 -> #REF! | K47: =BS!#REF!-K14 -> #REF! | L47: =BS!#REF!-L14 -> #REF! | N47: =SUM(B47:M47) -> #REF! | P47: =B47+C47+D47 -> #REF! | Q47: =E47+F47+G47 -> #REF! | R47: =H47+I47+J47 -> #REF! | S47: =K47+L47 -> #REF! | T47: =SUM(P47:S47) -> #REF!
A49: Net cash used in financing activities | B49: =SUM(B43:B48) -> #REF! | C49: =SUM(C43:C48) -> #REF! | D49: =SUM(D43:D48) -> #REF! | E49: =SUM(E43:E48) -> #REF! | F49: =SUM(F43:F48) -> #REF! | G49: =SUM(G43:G48) -> #REF! | H49: =SUM(H43:H48) -> #REF! | I49: =SUM(I43:I48) -> #REF! | ... L49: =SUM(L43:L48) -> #REF! | N49: =SUM(N43:N48) -> #REF! | P49: =SUM(P43:P48) -> #REF! | Q49: =SUM(Q43:Q48) -> #REF! | R49: =SUM(R43:R48) -> #REF! | S49: =SUM(S43:S48) -> #REF! | T49: =SUM(T43:T48) -> #REF!
A51: NET change IN CASH AND CASH EQUIVALENTS | B51: =B33+B40+B49 -> #REF! | C51: =C33+C40+C49 -> #REF! | D51: =D33+D40+D49 -> #REF! | E51: =E33+E40+E49 -> #REF! | F51: =F33+F40+F49 -> #REF! | G51: =G33+G40+G49 -> #REF! | H51: =H33+H40+H49 -> #REF! | I51: =I33+I40+I49 -> #REF! | ... L51: =L33+L40+L49 -> #REF! | N51: =N33+N40+N49 -> #REF! | P51: =P33+P40+P49 -> #REF! | Q51: =Q33+Q40+Q49 -> #REF! | R51: =R33+R40+R49 -> #REF! | S51: =S33+S40+S49 -> #REF! | T51: =T33+T40+T49 -> #REF!
A53: Cash and cash equivalents - Beginning balance | B53: =BS!#REF! -> #REF! | C53: =BS!E7 -> 4470130.8 | D53: =BS!K7 -> 10651132 | E53: =BS!#REF! -> #REF! | F53: =BS!#REF! -> #REF! | G53: =BS!#REF! -> #REF! | H53: =BS!#REF! -> #REF! | I53: =BS!#REF! -> #REF! | J53: =BS!#REF! -> #REF! | K53: =BS!#REF! -> #REF! | L53: =BS!#REF! -> #REF! | N53: =B53 -> #REF! | P53: =B53 -> #REF! | Q53: =E53 -> #REF! | R53: =H53 -> #REF! | S53: =K53 -> #REF! | T53: =P53 -> #REF!
A54: Cash of Mada acqistion
A56: CASH AND CASH EQUIVALENTS | B56: =B51+B53+B54 -> #REF! | C56: =C51+C53+C54 -> #REF! | D56: =D51+D53+D54 -> #REF! | E56: =E51+E53+E54 -> #REF! | F56: =F51+F53+F54 -> #REF! | G56: =G51+G53+G54 -> #REF! | H56: =H51+H53+H54 -> #REF! | I56: =I51+I53+I54 -> #REF! | ... L56: =L51+L53+L54 -> #REF! | N56: =N51+N53+N54 -> #REF! | P56: =P51+P53+P54 -> #REF! | Q56: =Q51+Q53+Q54 -> #REF! | R56: =R51+R53+R54 -> #REF! | S56: =S51+S53+S54 -> #REF! | T56: =T51+T53+T54 -> #REF!
B57: =BS!E7-CF!B56 -> #REF! | C57: =BS!K7-C56 -> #REF! | D57: =BS!#REF!-D56 -> #REF! | E57: =BS!#REF!-E56 -> #REF! | F57: =BS!#REF!-F56 -> #REF! | G57: =BS!#REF!-G56 -> #REF! | H57: =BS!#REF!-H56 -> #REF! | I57: =BS!#REF!-I56 -> #REF! | J57: =BS!#REF!-J56 -> #REF! | K57: =BS!#REF!-K56 -> #REF! | L57: =BS!#REF!-L56 -> #REF! | N57: =BS!#REF!-N56 -> #REF! | P57: =D56-P56 -> #REF! | Q57: =G56-Q56 -> #REF! | R57: =J56-R56 -> #REF! | S57: =L56-S56 -> #REF! | T57: =N56-T56 -> #REF!

Sheet Notes
A1: AIMS INDUSTRIAL
A2: NOTES
A3: =BS!A3 -> 31 December 2025 | C3: CONSOLIDATED | Q3: ALIF | AE3: VH
C4: Jan | D4: Feb | E4: Mar | F4: Apr | G4: May | H4: Jun | I4: Jul | J4: Aug | K4: Sep | L4: Oct | M4: Nov | N4: Dec | O4: YTD | Q4: Jan | R4: Feb | S4: Mar | T4: Apr | U4: May | V4: Jun | W4: Jul | X4: Aug | Y4: Sep | Z4: Oct | AA4: Nov | AB4: Dec | AC4: YTD | AE4: Jan | AF4: Feb | AG4: Mar | AH4: Apr | AI4: May | AJ4: Jun | AK4: Jul | AL4: Aug | AM4: Sep | AN4: Oct | AO4: Nov | AP4: Dec | AQ4: YTD
A6: CASH AND CASH EQUIVALENTS
A7: 130001 | B7: ALBILAD BANK A | C7: =Q7+AE7 -> #REF! | D7: =R7+AF7 -> #REF! | E7: =S7+AG7 -> #REF! | F7: =T7+AH7 -> #REF! | G7: =U7+AI7 -> #REF! | H7: =V7+AJ7 -> #REF! | I7: =W7+AK7 -> #REF! | J7: =X7+AL7 -> #REF! | ... N7: =AB7+AP7 -> 0 | Q7: =SUMIF(#REF!,$A7,#REF!) -> #REF! | R7: =SUMIF(ALIF_Y2014!$A:$A,$A7,ALIF_Y2014!$F:$F) -> 7283978.5 | S7: =SUMIF(ALIF_Y2015!$A:$A,$A7,ALIF_Y2015!$F:$F) -> 2480104.3 | T7: =SUMIF(ALIF_Y2016!$A:$A,$A7,ALIF_Y2016!$F:$F) -> 2109690.5 | U7: =SUMIF(ALIF_Y2017!$A:$A,$A7,ALIF_Y2017!$F:$F) -> 2591031.9 | V7: =SUMIF(ALIF_Y2018!$A:$A,$A7,ALIF_Y2018!$F:$F) -> 2068549.7 | W7: =SUMIF(ALIF_Y2019!$A:$A,$A7,ALIF_Y2019!$F:$F) -> 1482460.2 | X7: =SUMIF(ALIF_Y2020!$A:$A,$A7,ALIF_Y2020!$F:$F) -> -0.41 | Y7: =SUMIF(ALIF_Y2021!$A:$A,$A7,ALIF_Y2021!$F:$F) -> 254890.07 | Z7: =SUMIF(ALIF_Y2022!$A:$A,$A7,ALIF_Y2022!$F:$F) -> 0 | AA7: =SUMIF(ALIF_Y2023!$A:$A,$A7,ALIF_Y2023!$F:$F) -> 0 | AE7: =SUMIF(#REF!,$A7,#REF!) -> #REF! | AF7: =SUMIF(#REF!,$A7,#REF!) -> #REF! | AG7: =SUMIF(#REF!,$A7,#REF!) -> #REF! | AH7: =SUMIF(#REF!,$A7,#REF!) -> #REF! | AI7: =SUMIF(#REF!,$A7,#REF!) -> #REF! | AJ7: =SUMIF(#REF!,$A7,#REF!) -> #REF! | AK7: =SUMIF(#REF!,$A7,#REF!) -> #REF! | AL7: =SUMIF(#REF!,$A7,#REF!) -> #REF! | ... AO7: =SUMIF(#REF!,$A7,#REF!) -> #REF!
A8: 130002 | B8: ALBILAD BANK B | C8: =Q8+AE8 -> #REF! | D8: =R8+AF8 -> #REF! | E8: =S8+AG8 -> #REF! | F8: =T8+AH8 -> #REF! | G8: =U8+AI8 -> #REF! | H8: =V8+AJ8 -> #REF! | I8: =W8+AK8 -> #REF! | J8: =X8+AL8 -> #REF! | ... N8: =AB8+AP8 -> 0 | Q8: =SUMIF(#REF!,$A8,#REF!) -> #REF! | R8: =SUMIF(ALIF_Y2014!$A:$A,$A8,ALIF_Y2014!$F:$F) -> 54868.49 | S8: =SUMIF(ALIF_Y2015!$A:$A,$A8,ALIF_Y2015!$F:$F) -> 2429.1 | T8: =SUMIF(ALIF_Y2016!$A:$A,$A8,ALIF_Y2016!$F:$F) -> 30078.2 | U8: =SUMIF(ALIF_Y2017!$A:$A,$A8,ALIF_Y2017!$F:$F) -> 51063.64 | V8: =SUMIF(ALIF_Y2018!$A:$A,$A8,ALIF_Y2018!$F:$F) -> 6349.32 | W8: =SUMIF(ALIF_Y2019!$A:$A,$A8,ALIF_Y2019!$F:$F) -> 777923.25 | X8: =SUMIF(ALIF_Y2020!$A:$A,$A8,ALIF_Y2020!$F:$F) -> 744918.4 | Y8: =SUMIF(ALIF_Y2021!$A:$A,$A8,ALIF_Y2021!$F:$F) -> 0 | Z8: =SUMIF(ALIF_Y2022!$A:$A,$A8,ALIF_Y2022!$F:$F) -> 0 | AA8: =SUMIF(ALIF_Y2023!$A:$A,$A8,ALIF_Y2023!$F:$F) -> 0 | AE8: =SUMIF(#REF!,$A8,#REF!) -> #REF! | AF8: =SUMIF(#REF!,$A8,#REF!) -> #REF! | AG8: =SUMIF(#REF!,$A8,#REF!) -> #REF! | AH8: =SUMIF(#REF!,$A8,#REF!) -> #REF! | AI8: =SUMIF(#REF!,$A8,#REF!) -> #REF! | AJ8: =SUMIF(#REF!,$A8,#REF!) -> #REF! | AK8: =SUMIF(#REF!,$A8,#REF!) -> #REF! | AL8: =SUMIF(#REF!,$A8,#REF!) -> #REF! | ... AO8: =SUMIF(#REF!,$A8,#REF!) -> #REF!
A9: 130003 | B9: ALBILAD BANK C | C9: =Q9+AE9 -> #REF! | D9: =R9+AF9 -> #REF! | E9: =S9+AG9 -> #REF! | F9: =T9+AH9 -> #REF! | G9: =U9+AI9 -> #REF! | H9: =V9+AJ9 -> #REF! | I9: =W9+AK9 -> #REF! | J9: =X9+AL9 -> #REF! | ... N9: =AB9+AP9 -> 0 | Q9: =SUMIF(#REF!,$A9,#REF!) -> #REF! | R9: =SUMIF(ALIF_Y2014!$A:$A,$A9,ALIF_Y2014!$F:$F) -> 0 | S9: =SUMIF(ALIF_Y2015!$A:$A,$A9,ALIF_Y2015!$F:$F) -> 0 | T9: =SUMIF(ALIF_Y2016!$A:$A,$A9,ALIF_Y2016!$F:$F) -> 0 | U9: =SUMIF(ALIF_Y2017!$A:$A,$A9,ALIF_Y2017!$F:$F) -> 0 | V9: =SUMIF(ALIF_Y2018!$A:$A,$A9,ALIF_Y2018!$F:$F) -> 0 | W9: =SUMIF(ALIF_Y2019!$A:$A,$A9,ALIF_Y2019!$F:$F) -> 0 | X9: =SUMIF(ALIF_Y2020!$A:$A,$A9,ALIF_Y2020!$F:$F) -> 0 | Y9: =SUMIF(ALIF_Y2021!$A:$A,$A9,ALIF_Y2021!$F:$F) -> 0 | Z9: =SUMIF(ALIF_Y2022!$A:$A,$A9,ALIF_Y2022!$F:$F) -> 0 | AA9: =SUMIF(ALIF_Y2023!$A:$A,$A9,ALIF_Y2023!$F:$F) -> 0 | AE9: =SUMIF(#REF!,$A9,#REF!) -> #REF! | AF9: =SUMIF(#REF!,$A9,#REF!) -> #REF! | AG9: =SUMIF(#REF!,$A9,#REF!) -> #REF! | AH9: =SUMIF(#REF!,$A9,#REF!) -> #REF! | AI9: =SUMIF(#REF!,$A9,#REF!) -> #REF! | AJ9: =SUMIF(#REF!,$A9,#REF!) -> #REF! | AK9: =SUMIF(#REF!,$A9,#REF!) -> #REF! | AL9: =SUMIF(#REF!,$A9,#REF!) -> #REF! | ... AO9: =SUMIF(#REF!,$A9,#REF!) -> #REF!
A10: 130004 | B10: AL RAJHI BANK FAC | C10: =Q10+AE10 -> #REF! | D10: =R10+AF10 -> #REF! | E10: =S10+AG10 -> #REF! | F10: =T10+AH10 -> #REF! | G10: =U10+AI10 -> #REF! | H10: =V10+AJ10 -> #REF! | I10: =W10+AK10 -> #REF! | J10: =X10+AL10 -> #REF! | ... N10: =AB10+AP10 -> 0 | Q10: =SUMIF(#REF!,$A10,#REF!) -> #REF! | R10: =SUMIF(ALIF_Y2014!$A:$A,$A10,ALIF_Y2014!$F:$F) -> 2446274.1 | S10: =SUMIF(ALIF_Y2015!$A:$A,$A10,ALIF_Y2015!$F:$F) -> 669960.12 | T10: =SUMIF(ALIF_Y2016!$A:$A,$A10,ALIF_Y2016!$F:$F) -> 623354.35 | U10: =SUMIF(ALIF_Y2017!$A:$A,$A10,ALIF_Y2017!$F:$F) -> 2170226.4 | V10: =SUMIF(ALIF_Y2018!$A:$A,$A10,ALIF_Y2018!$F:$F) -> 281961.51 | W10: =SUMIF(ALIF_Y2019!$A:$A,$A10,ALIF_Y2019!$F:$F) -> 144938.85 | X10: =SUMIF(ALIF_Y2020!$A:$A,$A10,ALIF_Y2020!$F:$F) -> 108178.8 | Y10: =SUMIF(ALIF_Y2021!$A:$A,$A10,ALIF_Y2021!$F:$F) -> 31128.8 | Z10: =SUMIF(ALIF_Y2022!$A:$A,$A10,ALIF_Y2022!$F:$F) -> 15028.8 | AA10: =SUMIF(ALIF_Y2023!$A:$A,$A10,ALIF_Y2023!$F:$F) -> 0 | AE10: =SUMIF(#REF!,$A10,#REF!) -> #REF! | AF10: =SUMIF(#REF!,$A10,#REF!) -> #REF! | AG10: =SUMIF(#REF!,$A10,#REF!) -> #REF! | AH10: =SUMIF(#REF!,$A10,#REF!) -> #REF! | AI10: =SUMIF(#REF!,$A10,#REF!) -> #REF! | AJ10: =SUMIF(#REF!,$A10,#REF!) -> #REF! | AK10: =SUMIF(#REF!,$A10,#REF!) -> #REF! | AL10: =SUMIF(#REF!,$A10,#REF!) -> #REF! | ... AO10: =SUMIF(#REF!,$A10,#REF!) -> #REF!
A11: 130005 | B11: AL-RAJHI BANK IND | C11: =Q11+AE11 -> #REF! | D11: =R11+AF11 -> #REF! | E11: =S11+AG11 -> #REF! | F11: =T11+AH11 -> #REF! | G11: =U11+AI11 -> #REF! | H11: =V11+AJ11 -> #REF! | I11: =W11+AK11 -> #REF! | J11: =X11+AL11 -> #REF! | ... N11: =AB11+AP11 -> 0 | Q11: =SUMIF(#REF!,$A11,#REF!) -> #REF! | R11: =SUMIF(ALIF_Y2014!$A:$A,$A11,ALIF_Y2014!$F:$F) -> 173876.8 | S11: =SUMIF(ALIF_Y2015!$A:$A,$A11,ALIF_Y2015!$F:$F) -> 72019.39 | T11: =SUMIF(ALIF_Y2016!$A:$A,$A11,ALIF_Y2016!$F:$F) -> 5311.27 | U11: =SUMIF(ALIF_Y2017!$A:$A,$A11,ALIF_Y2017!$F:$F) -> 1196051 | V11: =SUMIF(ALIF_Y2018!$A:$A,$A11,ALIF_Y2018!$F:$F) -> 0 | W11: =SUMIF(ALIF_Y2019!$A:$A,$A11,ALIF_Y2019!$F:$F) -> 0 | X11: =SUMIF(ALIF_Y2020!$A:$A,$A11,ALIF_Y2020!$F:$F) -> 0 | Y11: =SUMIF(ALIF_Y2021!$A:$A,$A11,ALIF_Y2021!$F:$F) -> 0 | Z11: =SUMIF(ALIF_Y2022!$A:$A,$A11,ALIF_Y2022!$F:$F) -> 0 | AA11: =SUMIF(ALIF_Y2023!$A:$A,$A11,ALIF_Y2023!$F:$F) -> 0 | AE11: =SUMIF(#REF!,$A11,#REF!) -> #REF! | AF11: =SUMIF(#REF!,$A11,#REF!) -> #REF! | AG11: =SUMIF(#REF!,$A11,#REF!) -> #REF! | AH11: =SUMIF(#REF!,$A11,#REF!) -> #REF! | AI11: =SUMIF(#REF!,$A11,#REF!) -> #REF! | AJ11: =SUMIF(#REF!,$A11,#REF!) -> #REF! | AK11: =SUMIF(#REF!,$A11,#REF!) -> #REF! | AL11: =SUMIF(#REF!,$A11,#REF!) -> #REF! | ... AO11: =SUMIF(#REF!,$A11,#REF!) -> #REF!
A12: 130006 | B12: SAUDI BRITISH BANK | C12: =Q12+AE12 -> #REF! | D12: =R12+AF12 -> #REF! | E12: =S12+AG12 -> #REF! | F12: =T12+AH12 -> #REF! | G12: =U12+AI12 -> #REF! | H12: =V12+AJ12 -> #REF! | I12: =W12+AK12 -> #REF! | J12: =X12+AL12 -> #REF! | ... N12: =AB12+AP12 -> 0 | Q12: =SUMIF(#REF!,$A12,#REF!) -> #REF! | R12: =SUMIF(ALIF_Y2014!$A:$A,$A12,ALIF_Y2014!$F:$F) -> 268845.77 | S12: =SUMIF(ALIF_Y2015!$A:$A,$A12,ALIF_Y2015!$F:$F) -> 127521.81 | T12: =SUMIF(ALIF_Y2016!$A:$A,$A12,ALIF_Y2016!$F:$F) -> 18521.5 | U12: =SUMIF(ALIF_Y2017!$A:$A,$A12,ALIF_Y2017!$F:$F) -> 91646.45 | V12: =SUMIF(ALIF_Y2018!$A:$A,$A12,ALIF_Y2018!$F:$F) -> 26670.35 | W12: =SUMIF(ALIF_Y2019!$A:$A,$A12,ALIF_Y2019!$F:$F) -> 115009.41 | X12: =SUMIF(ALIF_Y2020!$A:$A,$A12,ALIF_Y2020!$F:$F) -> 89237.65 | Y12: =SUMIF(ALIF_Y2021!$A:$A,$A12,ALIF_Y2021!$F:$F) -> 221073.65 | Z12: =SUMIF(ALIF_Y2022!$A:$A,$A12,ALIF_Y2022!$F:$F) -> 0 | AA12: =SUMIF(ALIF_Y2023!$A:$A,$A12,ALIF_Y2023!$F:$F) -> 0 | AE12: =SUMIF(#REF!,$A12,#REF!) -> #REF! | AF12: =SUMIF(#REF!,$A12,#REF!) -> #REF! | AG12: =SUMIF(#REF!,$A12,#REF!) -> #REF! | AH12: =SUMIF(#REF!,$A12,#REF!) -> #REF! | AI12: =SUMIF(#REF!,$A12,#REF!) -> #REF! | AJ12: =SUMIF(#REF!,$A12,#REF!) -> #REF! | AK12: =SUMIF(#REF!,$A12,#REF!) -> #REF! | AL12: =SUMIF(#REF!,$A12,#REF!) -> #REF! | ... AO12: =SUMIF(#REF!,$A12,#REF!) -> #REF!
A13: 130007 | B13: NATIONAL COMMERCIAL BANK (NCB) | C13: =Q13+AE13 -> #REF! | D13: =R13+AF13 -> #REF! | E13: =S13+AG13 -> #REF! | F13: =T13+AH13 -> #REF! | G13: =U13+AI13 -> #REF! | H13: =V13+AJ13 -> #REF! | I13: =W13+AK13 -> #REF! | J13: =X13+AL13 -> #REF! | ... N13: =AB13+AP13 -> 0 | Q13: =SUMIF(#REF!,$A13,#REF!) -> #REF! | R13: =SUMIF(ALIF_Y2014!$A:$A,$A13,ALIF_Y2014!$F:$F) -> 530312.98 | S13: =SUMIF(ALIF_Y2015!$A:$A,$A13,ALIF_Y2015!$F:$F) -> 1042740.7 | T13: =SUMIF(ALIF_Y2016!$A:$A,$A13,ALIF_Y2016!$F:$F) -> 1782205.8 | U13: =SUMIF(ALIF_Y2017!$A:$A,$A13,ALIF_Y2017!$F:$F) -> 812449.22 | V13: =SUMIF(ALIF_Y2018!$A:$A,$A13,ALIF_Y2018!$F:$F) -> 1634615.1 | W13: =SUMIF(ALIF_Y2019!$A:$A,$A13,ALIF_Y2019!$F:$F) -> 1132000.1 | X13: =SUMIF(ALIF_Y2020!$A:$A,$A13,ALIF_Y2020!$F:$F) -> 271627.56 | Y13: =SUMIF(ALIF_Y2021!$A:$A,$A13,ALIF_Y2021!$F:$F) -> 975113.48 | Z13: =SUMIF(ALIF_Y2022!$A:$A,$A13,ALIF_Y2022!$F:$F) -> 1397142 | AA13: =SUMIF(ALIF_Y2023!$A:$A,$A13,ALIF_Y2023!$F:$F) -> 0 | AE13: =SUMIF(#REF!,$A13,#REF!) -> #REF! | AF13: =SUMIF(#REF!,$A13,#REF!) -> #REF! | AG13: =SUMIF(#REF!,$A13,#REF!) -> #REF! | AH13: =SUMIF(#REF!,$A13,#REF!) -> #REF! | AI13: =SUMIF(#REF!,$A13,#REF!) -> #REF! | AJ13: =SUMIF(#REF!,$A13,#REF!) -> #REF! | AK13: =SUMIF(#REF!,$A13,#REF!) -> #REF! | AL13: =SUMIF(#REF!,$A13,#REF!) -> #REF! | ... AO13: =SUMIF(#REF!,$A13,#REF!) -> #REF!
A14: 130008 | B14: RIYAD BANK SIC SR 9940 | C14: =Q14+AE14 -> #REF! | D14: =R14+AF14 -> #REF! | E14: =S14+AG14 -> #REF! | F14: =T14+AH14 -> #REF! | G14: =U14+AI14 -> #REF! | H14: =V14+AJ14 -> #REF! | I14: =W14+AK14 -> #REF! | J14: =X14+AL14 -> #REF! | ... N14: =AB14+AP14 -> 0 | Q14: =SUMIF(#REF!,$A14,#REF!) -> #REF! | R14: =SUMIF(ALIF_Y2014!$A:$A,$A14,ALIF_Y2014!$F:$F) -> 272978.02 | S14: =SUMIF(ALIF_Y2015!$A:$A,$A14,ALIF_Y2015!$F:$F) -> 16963.79 | T14: =SUMIF(ALIF_Y2016!$A:$A,$A14,ALIF_Y2016!$F:$F) -> 52027.55 | U14: =SUMIF(ALIF_Y2017!$A:$A,$A14,ALIF_Y2017!$F:$F) -> 298807.52 | V14: =SUMIF(ALIF_Y2018!$A:$A,$A14,ALIF_Y2018!$F:$F) -> 4769151.6 | W14: =SUMIF(ALIF_Y2019!$A:$A,$A14,ALIF_Y2019!$F:$F) -> 1609557.1 | X14: =SUMIF(ALIF_Y2020!$A:$A,$A14,ALIF_Y2020!$F:$F) -> 1334479.3 | Y14: =SUMIF(ALIF_Y2021!$A:$A,$A14,ALIF_Y2021!$F:$F) -> 563831.72 | Z14: =SUMIF(ALIF_Y2022!$A:$A,$A14,ALIF_Y2022!$F:$F) -> 125346.06 | AA14: =SUMIF(ALIF_Y2023!$A:$A,$A14,ALIF_Y2023!$F:$F) -> 252733.8 | AE14: =SUMIF(#REF!,$A14,#REF!) -> #REF! | AF14: =SUMIF(#REF!,$A14,#REF!) -> #REF! | AG14: =SUMIF(#REF!,$A14,#REF!) -> #REF! | AH14: =SUMIF(#REF!,$A14,#REF!) -> #REF! | AI14: =SUMIF(#REF!,$A14,#REF!) -> #REF! | AJ14: =SUMIF(#REF!,$A14,#REF!) -> #REF! | AK14: =SUMIF(#REF!,$A14,#REF!) -> #REF! | AL14: =SUMIF(#REF!,$A14,#REF!) -> #REF! | ... AO14: =SUMIF(#REF!,$A14,#REF!) -> #REF!
A15: 130009 | B15: ARAB NATIONAL BANK | C15: =Q15+AE15 -> #REF! | D15: =R15+AF15 -> #REF! | E15: =S15+AG15 -> #REF! | F15: =T15+AH15 -> #REF! | G15: =U15+AI15 -> #REF! | H15: =V15+AJ15 -> #REF! | I15: =W15+AK15 -> #REF! | J15: =X15+AL15 -> #REF! | ... N15: =AB15+AP15 -> 0 | Q15: =SUMIF(#REF!,$A15,#REF!) -> #REF! | R15: =SUMIF(ALIF_Y2014!$A:$A,$A15,ALIF_Y2014!$F:$F) -> 0 | S15: =SUMIF(ALIF_Y2015!$A:$A,$A15,ALIF_Y2015!$F:$F) -> 0 | T15: =SUMIF(ALIF_Y2016!$A:$A,$A15,ALIF_Y2016!$F:$F) -> 0 | U15: =SUMIF(ALIF_Y2017!$A:$A,$A15,ALIF_Y2017!$F:$F) -> 0 | V15: =SUMIF(ALIF_Y2018!$A:$A,$A15,ALIF_Y2018!$F:$F) -> 0 | W15: =SUMIF(ALIF_Y2019!$A:$A,$A15,ALIF_Y2019!$F:$F) -> 883583.5 | X15: =SUMIF(ALIF_Y2020!$A:$A,$A15,ALIF_Y2020!$F:$F) -> 481793.78 | Y15: =SUMIF(ALIF_Y2021!$A:$A,$A15,ALIF_Y2021!$F:$F) -> 752895.54 | Z15: =SUMIF(ALIF_Y2022!$A:$A,$A15,ALIF_Y2022!$F:$F) -> 4424115 | AA15: =SUMIF(ALIF_Y2023!$A:$A,$A15,ALIF_Y2023!$F:$F) -> 575464.68 | AE15: =SUMIF(#REF!,$A15,#REF!) -> #REF! | AF15: =SUMIF(#REF!,$A15,#REF!) -> #REF! | AG15: =SUMIF(#REF!,$A15,#REF!) -> #REF! | AH15: =SUMIF(#REF!,$A15,#REF!) -> #REF! | AI15: =SUMIF(#REF!,$A15,#REF!) -> #REF! | AJ15: =SUMIF(#REF!,$A15,#REF!) -> #REF! | AK15: =SUMIF(#REF!,$A15,#REF!) -> #REF! | AL15: =SUMIF(#REF!,$A15,#REF!) -> #REF! | ... AO15: =SUMIF(#REF!,$A15,#REF!) -> #REF!
A16: 130010 | B16: AL INMA BANK SAUDI ARABIA | C16: =Q16+AE16 -> #REF! | D16: =R16+AF16 -> #REF! | E16: =S16+AG16 -> #REF! | F16: =T16+AH16 -> #REF! | G16: =U16+AI16 -> #REF! | H16: =V16+AJ16 -> #REF! | I16: =W16+AK16 -> #REF! | J16: =X16+AL16 -> #REF! | ... N16: =AB16+AP16 -> 0 | Q16: =SUMIF(#REF!,$A16,#REF!) -> #REF! | R16: =SUMIF(ALIF_Y2014!$A:$A,$A16,ALIF_Y2014!$F:$F) -> 0 | S16: =SUMIF(ALIF_Y2015!$A:$A,$A16,ALIF_Y2015!$F:$F) -> 0 | T16: =SUMIF(ALIF_Y2016!$A:$A,$A16,ALIF_Y2016!$F:$F) -> 0 | U16: =SUMIF(ALIF_Y2017!$A:$A,$A16,ALIF_Y2017!$F:$F) -> 0 | V16: =SUMIF(ALIF_Y2018!$A:$A,$A16,ALIF_Y2018!$F:$F) -> 0 | W16: =SUMIF(ALIF_Y2019!$A:$A,$A16,ALIF_Y2019!$F:$F) -> 419127.51 | X16: =SUMIF(ALIF_Y2020!$A:$A,$A16,ALIF_Y2020!$F:$F) -> 14548085 | Y16: =SUMIF(ALIF_Y2021!$A:$A,$A16,ALIF_Y2021!$F:$F) -> 728505.9 | Z16: =SUMIF(ALIF_Y2022!$A:$A,$A16,ALIF_Y2022!$F:$F) -> 4858085.4 | AA16: =SUMIF(ALIF_Y2023!$A:$A,$A16,ALIF_Y2023!$F:$F) -> 912741.95 | AE16: =SUMIF(#REF!,$A16,#REF!) -> #REF! | AF16: =SUMIF(#REF!,$A16,#REF!) -> #REF! | AG16: =SUMIF(#REF!,$A16,#REF!) -> #REF! | AH16: =SUMIF(#REF!,$A16,#REF!) -> #REF! | AI16: =SUMIF(#REF!,$A16,#REF!) -> #REF! | AJ16: =SUMIF(#REF!,$A16,#REF!) -> #REF! | AK16: =SUMIF(#REF!,$A16,#REF!) -> #REF! | AL16: =SUMIF(#REF!,$A16,#REF!) -> #REF! | ... AO16: =SUMIF(#REF!,$A16,#REF!) -> #REF!
A17: 130011 | B17: AL INMA BANK (68502524190000) | C17: =Q17+AE17 -> #REF! | D17: =R17+AF17 -> #REF! | E17: =S17+AG17 -> #REF! | F17: =T17+AH17 -> #REF! | G17: =U17+AI17 -> #REF! | H17: =V17+AJ17 -> #REF! | I17: =W17+AK17 -> #REF! | J17: =X17+AL17 -> #REF! | ... N17: =AB17+AP17 -> 0 | Q17: =SUMIF(#REF!,$A17,#REF!) -> #REF! | R17: =SUMIF(ALIF_Y2014!$A:$A,$A17,ALIF_Y2014!$F:$F) -> 0 | S17: =SUMIF(ALIF_Y2015!$A:$A,$A17,ALIF_Y2015!$F:$F) -> 0 | T17: =SUMIF(ALIF_Y2016!$A:$A,$A17,ALIF_Y2016!$F:$F) -> 0 | U17: =SUMIF(ALIF_Y2017!$A:$A,$A17,ALIF_Y2017!$F:$F) -> 0 | V17: =SUMIF(ALIF_Y2018!$A:$A,$A17,ALIF_Y2018!$F:$F) -> 0 | W17: =SUMIF(ALIF_Y2019!$A:$A,$A17,ALIF_Y2019!$F:$F) -> 0 | X17: =SUMIF(ALIF_Y2020!$A:$A,$A17,ALIF_Y2020!$F:$F) -> 10099447 | Y17: =SUMIF(ALIF_Y2021!$A:$A,$A17,ALIF_Y2021!$F:$F) -> 1837850.2 | Z17: =SUMIF(ALIF_Y2022!$A:$A,$A17,ALIF_Y2022!$F:$F) -> 1029152.9 | AA17: =SUMIF(ALIF_Y2023!$A:$A,$A17,ALIF_Y2023!$F:$F) -> 371638.27 | AE17: =SUMIF(#REF!,$A17,#REF!) -> #REF! | AF17: =SUMIF(#REF!,$A17,#REF!) -> #REF! | AG17: =SUMIF(#REF!,$A17,#REF!) -> #REF! | AH17: =SUMIF(#REF!,$A17,#REF!) -> #REF! | AI17: =SUMIF(#REF!,$A17,#REF!) -> #REF! | AJ17: =SUMIF(#REF!,$A17,#REF!) -> #REF! | AK17: =SUMIF(#REF!,$A17,#REF!) -> #REF! | AL17: =SUMIF(#REF!,$A17,#REF!) -> #REF! | ... AO17: =SUMIF(#REF!,$A17,#REF!) -> #REF!
A18: 130012 | B18: ALBILAD ALIF 0006 | C18: =Q18+AE18 -> #REF! | D18: =R18+AF18 -> #REF! | E18: =S18+AG18 -> #REF! | F18: =T18+AH18 -> #REF! | G18: =U18+AI18 -> #REF! | H18: =V18+AJ18 -> #REF! | I18: =W18+AK18 -> #REF! | J18: =X18+AL18 -> #REF! | ... N18: =AB18+AP18 -> 0 | Q18: =SUMIF(#REF!,$A18,#REF!) -> #REF! | R18: =SUMIF(ALIF_Y2014!$A:$A,$A18,ALIF_Y2014!$F:$F) -> 0 | S18: =SUMIF(ALIF_Y2015!$A:$A,$A18,ALIF_Y2015!$F:$F) -> 0 | T18: =SUMIF(ALIF_Y2016!$A:$A,$A18,ALIF_Y2016!$F:$F) -> 0 | U18: =SUMIF(ALIF_Y2017!$A:$A,$A18,ALIF_Y2017!$F:$F) -> 0 | V18: =SUMIF(ALIF_Y2018!$A:$A,$A18,ALIF_Y2018!$F:$F) -> 0 | W18: =SUMIF(ALIF_Y2019!$A:$A,$A18,ALIF_Y2019!$F:$F) -> 0 | X18: =SUMIF(ALIF_Y2020!$A:$A,$A18,ALIF_Y2020!$F:$F) -> 12249437 | Y18: =SUMIF(ALIF_Y2021!$A:$A,$A18,ALIF_Y2021!$F:$F) -> 2278838.6 | Z18: =SUMIF(ALIF_Y2022!$A:$A,$A18,ALIF_Y2022!$F:$F) -> 1252439.5 | AA18: =SUMIF(ALIF_Y2023!$A:$A,$A18,ALIF_Y2023!$F:$F) -> 925749.64 | AE18: =SUMIF(#REF!,$A18,#REF!) -> #REF! | AF18: =SUMIF(#REF!,$A18,#REF!) -> #REF! | AG18: =SUMIF(#REF!,$A18,#REF!) -> #REF! | AH18: =SUMIF(#REF!,$A18,#REF!) -> #REF! | AI18: =SUMIF(#REF!,$A18,#REF!) -> #REF! | AJ18: =SUMIF(#REF!,$A18,#REF!) -> #REF! | AK18: =SUMIF(#REF!,$A18,#REF!) -> #REF! | AL18: =SUMIF(#REF!,$A18,#REF!) -> #REF! | ... AO18: =SUMIF(#REF!,$A18,#REF!) -> #REF!
... A25: 130017 | B25: Bank Al Bilad USD | C25: =Q25+AE25 -> #REF! | D25: =R25+AF25 -> #REF! | E25: =S25+AG25 -> #REF! | F25: =T25+AH25 -> #REF! | G25: =U25+AI25 -> #REF! | H25: =V25+AJ25 -> #REF! | I25: =W25+AK25 -> #REF! | J25: =X25+AL25 -> #REF! | ... N25: =AB25+AP25 -> 0 | Q25: =SUMIF(#REF!,$A25,#REF!) -> #REF! | R25: =SUMIF(ALIF_Y2014!$A:$A,$A25,ALIF_Y2014!$F:$F) -> 0 | S25: =SUMIF(ALIF_Y2015!$A:$A,$A25,ALIF_Y2015!$F:$F) -> 0 | T25: =SUMIF(ALIF_Y2016!$A:$A,$A25,ALIF_Y2016!$F:$F) -> 0 | U25: =SUMIF(ALIF_Y2017!$A:$A,$A25,ALIF_Y2017!$F:$F) -> 0 | V25: =SUMIF(ALIF_Y2018!$A:$A,$A25,ALIF_Y2018!$F:$F) -> 0 | W25: =SUMIF(ALIF_Y2019!$A:$A,$A25,ALIF_Y2019!$F:$F) -> 0 | X25: =SUMIF(ALIF_Y2020!$A:$A,$A25,ALIF_Y2020!$F:$F) -> 0 | Y25: =SUMIF(ALIF_Y2021!$A:$A,$A25,ALIF_Y2021!$F:$F) -> 0 | Z25: =SUMIF(ALIF_Y2022!$A:$A,$A25,ALIF_Y2022!$F:$F) -> 0 | AA25: =SUMIF(ALIF_Y2023!$A:$A,$A25,ALIF_Y2023!$F:$F) -> 0 | AE25: =SUMIF(#REF!,$A25,#REF!) -> #REF! | AF25: =SUMIF(#REF!,$A25,#REF!) -> #REF! | AG25: =SUMIF(#REF!,$A25,#REF!) -> #REF! | AH25: =SUMIF(#REF!,$A25,#REF!) -> #REF! | AI25: =SUMIF(#REF!,$A25,#REF!) -> #REF! | AJ25: =SUMIF(#REF!,$A25,#REF!) -> #REF! | AK25: =SUMIF(#REF!,$A25,#REF!) -> #REF! | AL25: =SUMIF(#REF!,$A25,#REF!) -> #REF! | ... AO25: =SUMIF(#REF!,$A25,#REF!) -> #REF!
C27: =SUM(C7:C26) -> #REF! | D27: =SUM(D7:D26) -> #REF! | E27: =SUM(E7:E26) -> #REF! | F27: =SUM(F7:F26) -> #REF! | G27: =SUM(G7:G26) -> #REF! | H27: =SUM(H7:H26) -> #REF! | I27: =SUM(I7:I26) -> #REF! | J27: =SUM(J7:J26) -> #REF! | ... N27: =SUM(N7:N26) -> 0 | Q27: =SUM(Q7:Q26) -> #REF! | R27: =SUM(R7:R26) -> 11085979 | S27: =SUM(S7:S26) -> 4470130.8 | T27: =SUM(T7:T26) -> 4689654.8 | U27: =SUM(U7:U26) -> 7257276.1 | V27: =SUM(V7:V26) -> 8817544.4 | W27: =SUM(W7:W26) -> 6590030 | X27: =SUM(X7:X26) -> 40745293 | ... AB27: =SUM(AB7:AB26) -> 0 | AE27: =SUM(AE7:AE26) -> #REF! | AF27: =SUM(AF7:AF26) -> #REF! | AG27: =SUM(AG7:AG26) -> #REF! | AH27: =SUM(AH7:AH26) -> #REF! | AI27: =SUM(AI7:AI26) -> #REF! | AJ27: =SUM(AJ7:AJ26) -> #REF! | AK27: =SUM(AK7:AK26) -> #REF! | AL27: =SUM(AL7:AL26) -> #REF! | ... AO27: =SUM(AO7:AO26) -> #REF!
A29: TRADE RECEIVABLES
A30: 140001 | B30: TRADE DEBTORS | C30: =Q30+AE30 -> #REF! | D30: =R30+AF30 -> #REF! | E30: =S30+AG30 -> #REF! | F30: =T30+AH30 -> #REF! | G30: =U30+AI30 -> #REF! | H30: =V30+AJ30 -> #REF! | I30: =W30+AK30 -> #REF! | J30: =X30+AL30 -> #REF! | ... N30: =AB30+AP30 -> 0 | Q30: =SUMIF(#REF!,$A30,#REF!) -> #REF! | R30: =SUMIF(ALIF_Y2014!$A:$A,$A30,ALIF_Y2014!$F:$F) -> 36187909 | S30: =SUMIF(ALIF_Y2015!$A:$A,$A30,ALIF_Y2015!$F:$F) -> 36923559 | T30: =SUMIF(ALIF_Y2016!$A:$A,$A30,ALIF_Y2016!$F:$F) -> 39673676 | U30: =SUMIF(ALIF_Y2017!$A:$A,$A30,ALIF_Y2017!$F:$F) -> 39364278 | V30: =SUMIF(ALIF_Y2018!$A:$A,$A30,ALIF_Y2018!$F:$F) -> 38308186 | W30: =SUMIF(ALIF_Y2019!$A:$A,$A30,ALIF_Y2019!$F:$F) -> 43443359 | X30: =SUMIF(ALIF_Y2020!$A:$A,$A30,ALIF_Y2020!$F:$F) -> 38933965 | Y30: =SUMIF(ALIF_Y2021!$A:$A,$A30,ALIF_Y2021!$F:$F) -> 63268300 | Z30: =SUMIF(ALIF_Y2022!$A:$A,$A30,ALIF_Y2022!$F:$F) -> 73001860 | AA30: =SUMIF(ALIF_Y2023!$A:$A,$A30,ALIF_Y2023!$F:$F) -> 45463354 | AE30: =SUMIF(#REF!,$A30,#REF!) -> #REF! | AF30: =SUMIF(#REF!,$A30,#REF!) -> #REF! | AG30: =SUMIF(#REF!,$A30,#REF!) -> #REF! | AH30: =SUMIF(#REF!,$A30,#REF!) -> #REF! | AI30: =SUMIF(#REF!,$A30,#REF!) -> #REF! | AJ30: =SUMIF(#REF!,$A30,#REF!) -> #REF! | AK30: =SUMIF(#REF!,$A30,#REF!) -> #REF! | AL30: =SUMIF(#REF!,$A30,#REF!) -> #REF! | ... AO30: =SUMIF(#REF!,$A30,#REF!) -> #REF!
A31: 140010 | B31: SUNDRY DEBTORS | C31: =Q31+AE31 -> #REF! | D31: =R31+AF31 -> #REF! | E31: =S31+AG31 -> #REF! | F31: =T31+AH31 -> #REF! | G31: =U31+AI31 -> #REF! | H31: =V31+AJ31 -> #REF! | I31: =W31+AK31 -> #REF! | J31: =X31+AL31 -> #REF! | ... N31: =AB31+AP31 -> 0 | Q31: =SUMIF(#REF!,$A31,#REF!) -> #REF! | R31: =SUMIF(ALIF_Y2014!$A:$A,$A31,ALIF_Y2014!$F:$F) -> 0 | S31: =SUMIF(ALIF_Y2015!$A:$A,$A31,ALIF_Y2015!$F:$F) -> 0 | T31: =SUMIF(ALIF_Y2016!$A:$A,$A31,ALIF_Y2016!$F:$F) -> 0 | U31: =SUMIF(ALIF_Y2017!$A:$A,$A31,ALIF_Y2017!$F:$F) -> 0 | V31: =SUMIF(ALIF_Y2018!$A:$A,$A31,ALIF_Y2018!$F:$F) -> 0 | W31: =SUMIF(ALIF_Y2019!$A:$A,$A31,ALIF_Y2019!$F:$F) -> 0 | X31: =SUMIF(ALIF_Y2020!$A:$A,$A31,ALIF_Y2020!$F:$F) -> 0 | Y31: =SUMIF(ALIF_Y2021!$A:$A,$A31,ALIF_Y2021!$F:$F) -> 0 | Z31: =SUMIF(ALIF_Y2022!$A:$A,$A31,ALIF_Y2022!$F:$F) -> 0 | AA31: =SUMIF(ALIF_Y2023!$A:$A,$A31,ALIF_Y2023!$F:$F) -> 0 | AE31: =SUMIF(#REF!,$A31,#REF!) -> #REF! | AF31: =SUMIF(#REF!,$A31,#REF!) -> #REF! | AG31: =SUMIF(#REF!,$A31,#REF!) -> #REF! | AH31: =SUMIF(#REF!,$A31,#REF!) -> #REF! | AI31: =SUMIF(#REF!,$A31,#REF!) -> #REF! | AJ31: =SUMIF(#REF!,$A31,#REF!) -> #REF! | AK31: =SUMIF(#REF!,$A31,#REF!) -> #REF! | AL31: =SUMIF(#REF!,$A31,#REF!) -> #REF! | ... AO31: =SUMIF(#REF!,$A31,#REF!) -> #REF!
A32: 121003 | B32: CLEARING ACC | C32: =Q32+AE32 -> #REF! | D32: =R32+AF32 -> #REF! | E32: =S32+AG32 -> #REF! | F32: =T32+AH32 -> #REF! | G32: =U32+AI32 -> #REF! | H32: =V32+AJ32 -> #REF! | I32: =W32+AK32 -> #REF! | J32: =X32+AL32 -> #REF! | ... N32: =AB32+AP32 -> 0 | Q32: =SUMIF(#REF!,$A32,#REF!) -> #REF! | R32: =SUMIF(ALIF_Y2014!$A:$A,$A32,ALIF_Y2014!$F:$F) -> 0 | S32: =SUMIF(ALIF_Y2015!$A:$A,$A32,ALIF_Y2015!$F:$F) -> 0 | T32: =SUMIF(ALIF_Y2016!$A:$A,$A32,ALIF_Y2016!$F:$F) -> 0 | U32: =SUMIF(ALIF_Y2017!$A:$A,$A32,ALIF_Y2017!$F:$F) -> 0 | V32: =SUMIF(ALIF_Y2018!$A:$A,$A32,ALIF_Y2018!$F:$F) -> 0 | W32: =SUMIF(ALIF_Y2019!$A:$A,$A32,ALIF_Y2019!$F:$F) -> 0 | X32: =SUMIF(ALIF_Y2020!$A:$A,$A32,ALIF_Y2020!$F:$F) -> 0 | Y32: =SUMIF(ALIF_Y2021!$A:$A,$A32,ALIF_Y2021!$F:$F) -> 0 | Z32: =SUMIF(ALIF_Y2022!$A:$A,$A32,ALIF_Y2022!$F:$F) -> 0 | AA32: =SUMIF(ALIF_Y2023!$A:$A,$A32,ALIF_Y2023!$F:$F) -> 0 | AE32: =SUMIF(#REF!,$A32,#REF!) -> #REF! | AF32: =SUMIF(#REF!,$A32,#REF!) -> #REF! | AG32: =SUMIF(#REF!,$A32,#REF!) -> #REF! | AH32: =SUMIF(#REF!,$A32,#REF!) -> #REF! | AI32: =SUMIF(#REF!,$A32,#REF!) -> #REF! | AJ32: =SUMIF(#REF!,$A32,#REF!) -> #REF! | AK32: =SUMIF(#REF!,$A32,#REF!) -> #REF! | AL32: =SUMIF(#REF!,$A32,#REF!) -> #REF! | ... AO32: =SUMIF(#REF!,$A32,#REF!) -> #REF!
A33: 260003 | B33: PROVISION FOR DOUBTFUL DEBTS | C33: =Q33+AE33 -> #REF! | D33: =R33+AF33 -> #REF! | E33: =S33+AG33 -> #REF! | F33: =T33+AH33 -> #REF! | G33: =U33+AI33 -> #REF! | H33: =V33+AJ33 -> #REF! | I33: =W33+AK33 -> #REF! | J33: =X33+AL33 -> #REF! | ... N33: =AB33+AP33 -> 0 | Q33: =SUMIF(#REF!,$A33,#REF!) -> #REF! | R33: =SUMIF(ALIF_Y2014!$A:$A,$A33,ALIF_Y2014!$F:$F) -> -1409581.5 | S33: =SUMIF(ALIF_Y2015!$A:$A,$A33,ALIF_Y2015!$F:$F) -> -1409581.5 | T33: =SUMIF(ALIF_Y2016!$A:$A,$A33,ALIF_Y2016!$F:$F) -> -3563173.5 | U33: =SUMIF(ALIF_Y2017!$A:$A,$A33,ALIF_Y2017!$F:$F) -> -3563173.5 | V33: =SUMIF(ALIF_Y2018!$A:$A,$A33,ALIF_Y2018!$F:$F) -> -3407320.1 | W33: =SUMIF(ALIF_Y2019!$A:$A,$A33,ALIF_Y2019!$F:$F) -> -3156727.1 | X33: =SUMIF(ALIF_Y2020!$A:$A,$A33,ALIF_Y2020!$F:$F) -> -3482088.1 | Y33: =SUMIF(ALIF_Y2021!$A:$A,$A33,ALIF_Y2021!$F:$F) -> -3454104.7 | Z33: =SUMIF(ALIF_Y2022!$A:$A,$A33,ALIF_Y2022!$F:$F) -> -3557438 | AA33: =SUMIF(ALIF_Y2023!$A:$A,$A33,ALIF_Y2023!$F:$F) -> -12488537 | AE33: =SUMIF(#REF!,$A33,#REF!) -> #REF! | AF33: =SUMIF(#REF!,$A33,#REF!) -> #REF! | AG33: =SUMIF(#REF!,$A33,#REF!) -> #REF! | AH33: =SUMIF(#REF!,$A33,#REF!) -> #REF! | AI33: =SUMIF(#REF!,$A33,#REF!) -> #REF! | AJ33: =SUMIF(#REF!,$A33,#REF!) -> #REF! | AK33: =SUMIF(#REF!,$A33,#REF!) -> #REF! | AL33: =SUMIF(#REF!,$A33,#REF!) -> #REF! | ... AO33: =SUMIF(#REF!,$A33,#REF!) -> #REF!
C35: =SUM(C30:C34) -> #REF! | D35: =SUM(D30:D34) -> #REF! | E35: =SUM(E30:E34) -> #REF! | F35: =SUM(F30:F34) -> #REF! | G35: =SUM(G30:G34) -> #REF! | H35: =SUM(H30:H34) -> #REF! | I35: =SUM(I30:I34) -> #REF! | J35: =SUM(J30:J34) -> #REF! | ... N35: =SUM(N30:N34) -> 0 | Q35: =SUM(Q30:Q34) -> #REF! | R35: =SUM(R30:R34) -> 34778327 | S35: =SUM(S30:S34) -> 35513977 | T35: =SUM(T30:T34) -> 36110502 | U35: =SUM(U30:U34) -> 35801104 | V35: =SUM(V30:V34) -> 34900866 | W35: =SUM(W30:W34) -> 40286632 | X35: =SUM(X30:X34) -> 35451877 | ... AB35: =SUM(AB30:AB34) -> 0 | AE35: =SUM(AE30:AE34) -> #REF! | AF35: =SUM(AF30:AF34) -> #REF! | AG35: =SUM(AG30:AG34) -> #REF! | AH35: =SUM(AH30:AH34) -> #REF! | AI35: =SUM(AI30:AI34) -> #REF! | AJ35: =SUM(AJ30:AJ34) -> #REF! | AK35: =SUM(AK30:AK34) -> #REF! | AL35: =SUM(AL30:AL34) -> #REF! | ... AO35: =SUM(AO30:AO34) -> #REF!
A36: PREPAID EXPENSES
A37: 121001 | B37: PRE OPERATING EXPS | C37: =Q37+AE37 -> #REF! | D37: =R37+AF37 -> #REF! | E37: =S37+AG37 -> #REF! | F37: =T37+AH37 -> #REF! | G37: =U37+AI37 -> #REF! | H37: =V37+AJ37 -> #REF! | I37: =W37+AK37 -> #REF! | J37: =X37+AL37 -> #REF! | ... N37: =AB37+AP37 -> 0 | Q37: =SUMIF(#REF!,$A37,#REF!) -> #REF! | R37: =SUMIF(ALIF_Y2014!$A:$A,$A37,ALIF_Y2014!$F:$F) -> 5363766.1 | S37: =SUMIF(ALIF_Y2015!$A:$A,$A37,ALIF_Y2015!$F:$F) -> 6677123.3 | T37: =SUMIF(ALIF_Y2016!$A:$A,$A37,ALIF_Y2016!$F:$F) -> 8098665.1 | U37: =SUMIF(ALIF_Y2017!$A:$A,$A37,ALIF_Y2017!$F:$F) -> 13762616 | V37: =SUMIF(ALIF_Y2018!$A:$A,$A37,ALIF_Y2018!$F:$F) -> 13762616 | W37: =SUMIF(ALIF_Y2019!$A:$A,$A37,ALIF_Y2019!$F:$F) -> 13762616 | X37: =SUMIF(ALIF_Y2020!$A:$A,$A37,ALIF_Y2020!$F:$F) -> 13762616 | Y37: =SUMIF(ALIF_Y2021!$A:$A,$A37,ALIF_Y2021!$F:$F) -> 13762616 | Z37: =SUMIF(ALIF_Y2022!$A:$A,$A37,ALIF_Y2022!$F:$F) -> 13762616 | AA37: =SUMIF(ALIF_Y2023!$A:$A,$A37,ALIF_Y2023!$F:$F) -> 13762616 | AE37: =SUMIF(#REF!,$A37,#REF!) -> #REF! | AF37: =SUMIF(#REF!,$A37,#REF!) -> #REF! | AG37: =SUMIF(#REF!,$A37,#REF!) -> #REF! | AH37: =SUMIF(#REF!,$A37,#REF!) -> #REF! | AI37: =SUMIF(#REF!,$A37,#REF!) -> #REF! | AJ37: =SUMIF(#REF!,$A37,#REF!) -> #REF! | AK37: =SUMIF(#REF!,$A37,#REF!) -> #REF! | AL37: =SUMIF(#REF!,$A37,#REF!) -> #REF! | ... AO37: =SUMIF(#REF!,$A37,#REF!) -> #REF!
A38: 121002 | B38: AMORTIZATION OF PRE OPERATING EXPS | C38: =Q38+AE38 -> #REF! | D38: =R38+AF38 -> #REF! | E38: =S38+AG38 -> #REF! | F38: =T38+AH38 -> #REF! | G38: =U38+AI38 -> #REF! | H38: =V38+AJ38 -> #REF! | I38: =W38+AK38 -> #REF! | J38: =X38+AL38 -> #REF! | ... N38: =AB38+AP38 -> 0 | Q38: =SUMIF(#REF!,$A38,#REF!) -> #REF! | R38: =SUMIF(ALIF_Y2014!$A:$A,$A38,ALIF_Y2014!$F:$F) -> -3650674.1 | S38: =SUMIF(ALIF_Y2015!$A:$A,$A38,ALIF_Y2015!$F:$F) -> -3650674.1 | T38: =SUMIF(ALIF_Y2016!$A:$A,$A38,ALIF_Y2016!$F:$F) -> -8098665.1 | U38: =SUMIF(ALIF_Y2017!$A:$A,$A38,ALIF_Y2017!$F:$F) -> -13762616 | V38: =SUMIF(ALIF_Y2018!$A:$A,$A38,ALIF_Y2018!$F:$F) -> -13762616 | W38: =SUMIF(ALIF_Y2019!$A:$A,$A38,ALIF_Y2019!$F:$F) -> -13762616 | X38: =SUMIF(ALIF_Y2020!$A:$A,$A38,ALIF_Y2020!$F:$F) -> -13762616 | Y38: =SUMIF(ALIF_Y2021!$A:$A,$A38,ALIF_Y2021!$F:$F) -> -13762616 | Z38: =SUMIF(ALIF_Y2022!$A:$A,$A38,ALIF_Y2022!$F:$F) -> -13762616 | AA38: =SUMIF(ALIF_Y2023!$A:$A,$A38,ALIF_Y2023!$F:$F) -> -13762616 | AE38: =SUMIF(#REF!,$A38,#REF!) -> #REF! | AF38: =SUMIF(#REF!,$A38,#REF!) -> #REF! | AG38: =SUMIF(#REF!,$A38,#REF!) -> #REF! | AH38: =SUMIF(#REF!,$A38,#REF!) -> #REF! | AI38: =SUMIF(#REF!,$A38,#REF!) -> #REF! | AJ38: =SUMIF(#REF!,$A38,#REF!) -> #REF! | AK38: =SUMIF(#REF!,$A38,#REF!) -> #REF! | AL38: =SUMIF(#REF!,$A38,#REF!) -> #REF! | ... AO38: =SUMIF(#REF!,$A38,#REF!) -> #REF!
A39: 150001 | B39: EMPLOYEES LOANS | C39: =Q39+AE39 -> #REF! | D39: =R39+AF39 -> #REF! | E39: =S39+AG39 -> #REF! | F39: =T39+AH39 -> #REF! | G39: =U39+AI39 -> #REF! | H39: =V39+AJ39 -> #REF! | I39: =W39+AK39 -> #REF! | J39: =X39+AL39 -> #REF! | ... N39: =AB39+AP39 -> 0 | Q39: =SUMIF(#REF!,$A39,#REF!) -> #REF! | R39: =SUMIF(ALIF_Y2014!$A:$A,$A39,ALIF_Y2014!$F:$F) -> 584170.48 | S39: =SUMIF(ALIF_Y2015!$A:$A,$A39,ALIF_Y2015!$F:$F) -> 456284.48 | T39: =SUMIF(ALIF_Y2016!$A:$A,$A39,ALIF_Y2016!$F:$F) -> 420934.68 | U39: =SUMIF(ALIF_Y2017!$A:$A,$A39,ALIF_Y2017!$F:$F) -> 43750 | V39: =SUMIF(ALIF_Y2018!$A:$A,$A39,ALIF_Y2018!$F:$F) -> 383368 | W39: =SUMIF(ALIF_Y2019!$A:$A,$A39,ALIF_Y2019!$F:$F) -> 516445.74 | X39: =SUMIF(ALIF_Y2020!$A:$A,$A39,ALIF_Y2020!$F:$F) -> 161280 | Y39: =SUMIF(ALIF_Y2021!$A:$A,$A39,ALIF_Y2021!$F:$F) -> 37250 | Z39: =SUMIF(ALIF_Y2022!$A:$A,$A39,ALIF_Y2022!$F:$F) -> 19000.5 | AA39: =SUMIF(ALIF_Y2023!$A:$A,$A39,ALIF_Y2023!$F:$F) -> 131188.18 | AE39: =SUMIF(#REF!,$A39,#REF!) -> #REF! | AF39: =SUMIF(#REF!,$A39,#REF!) -> #REF! | AG39: =SUMIF(#REF!,$A39,#REF!) -> #REF! | AH39: =SUMIF(#REF!,$A39,#REF!) -> #REF! | AI39: =SUMIF(#REF!,$A39,#REF!) -> #REF! | AJ39: =SUMIF(#REF!,$A39,#REF!) -> #REF! | AK39: =SUMIF(#REF!,$A39,#REF!) -> #REF! | AL39: =SUMIF(#REF!,$A39,#REF!) -> #REF! | ... AO39: =SUMIF(#REF!,$A39,#REF!) -> #REF!
A40: 170005 | B40: L/C MARGINAL DEPOSITS BILAD | C40: =Q40+AE40 -> #REF! | D40: =R40+AF40 -> #REF! | E40: =S40+AG40 -> #REF! | F40: =T40+AH40 -> #REF! | G40: =U40+AI40 -> #REF! | H40: =V40+AJ40 -> #REF! | I40: =W40+AK40 -> #REF! | J40: =X40+AL40 -> #REF! | ... N40: =AB40+AP40 -> 0 | Q40: =SUMIF(#REF!,$A40,#REF!) -> #REF! | R40: =SUMIF(ALIF_Y2014!$A:$A,$A40,ALIF_Y2014!$F:$F) -> 0 | S40: =SUMIF(ALIF_Y2015!$A:$A,$A40,ALIF_Y2015!$F:$F) -> 0 | T40: =SUMIF(ALIF_Y2016!$A:$A,$A40,ALIF_Y2016!$F:$F) -> 0 | U40: =SUMIF(ALIF_Y2017!$A:$A,$A40,ALIF_Y2017!$F:$F) -> 0 | V40: =SUMIF(ALIF_Y2018!$A:$A,$A40,ALIF_Y2018!$F:$F) -> 0 | W40: =SUMIF(ALIF_Y2019!$A:$A,$A40,ALIF_Y2019!$F:$F) -> 0 | X40: =SUMIF(ALIF_Y2020!$A:$A,$A40,ALIF_Y2020!$F:$F) -> 0 | Y40: =SUMIF(ALIF_Y2021!$A:$A,$A40,ALIF_Y2021!$F:$F) -> 0 | Z40: =SUMIF(ALIF_Y2022!$A:$A,$A40,ALIF_Y2022!$F:$F) -> 0 | AA40: =SUMIF(ALIF_Y2023!$A:$A,$A40,ALIF_Y2023!$F:$F) -> 0 | AE40: =SUMIF(#REF!,$A40,#REF!) -> #REF! | AF40: =SUMIF(#REF!,$A40,#REF!) -> #REF! | AG40: =SUMIF(#REF!,$A40,#REF!) -> #REF! | AH40: =SUMIF(#REF!,$A40,#REF!) -> #REF! | AI40: =SUMIF(#REF!,$A40,#REF!) -> #REF! | AJ40: =SUMIF(#REF!,$A40,#REF!) -> #REF! | AK40: =SUMIF(#REF!,$A40,#REF!) -> #REF! | AL40: =SUMIF(#REF!,$A40,#REF!) -> #REF! | ... AO40: =SUMIF(#REF!,$A40,#REF!) -> #REF!
A41: 170006 | B41: L/C MARGINAL DEPOSITS AL RIYADH BANK | C41: =Q41+AE41 -> #REF! | D41: =R41+AF41 -> #REF! | E41: =S41+AG41 -> #REF! | F41: =T41+AH41 -> #REF! | G41: =U41+AI41 -> #REF! | H41: =V41+AJ41 -> #REF! | I41: =W41+AK41 -> #REF! | J41: =X41+AL41 -> #REF! | ... N41: =AB41+AP41 -> 0 | Q41: =SUMIF(#REF!,$A41,#REF!) -> #REF! | R41: =SUMIF(ALIF_Y2014!$A:$A,$A41,ALIF_Y2014!$F:$F) -> 190719 | S41: =SUMIF(ALIF_Y2015!$A:$A,$A41,ALIF_Y2015!$F:$F) -> 453316.3 | T41: =SUMIF(ALIF_Y2016!$A:$A,$A41,ALIF_Y2016!$F:$F) -> 971548.61 | U41: =SUMIF(ALIF_Y2017!$A:$A,$A41,ALIF_Y2017!$F:$F) -> 0 | V41: =SUMIF(ALIF_Y2018!$A:$A,$A41,ALIF_Y2018!$F:$F) -> 0 | W41: =SUMIF(ALIF_Y2019!$A:$A,$A41,ALIF_Y2019!$F:$F) -> 0 | X41: =SUMIF(ALIF_Y2020!$A:$A,$A41,ALIF_Y2020!$F:$F) -> 0 | Y41: =SUMIF(ALIF_Y2021!$A:$A,$A41,ALIF_Y2021!$F:$F) -> 1240226.5 | Z41: =SUMIF(ALIF_Y2022!$A:$A,$A41,ALIF_Y2022!$F:$F) -> 18329.42 | AA41: =SUMIF(ALIF_Y2023!$A:$A,$A41,ALIF_Y2023!$F:$F) -> 0 | AE41: =SUMIF(#REF!,$A41,#REF!) -> #REF! | AF41: =SUMIF(#REF!,$A41,#REF!) -> #REF! | AG41: =SUMIF(#REF!,$A41,#REF!) -> #REF! | AH41: =SUMIF(#REF!,$A41,#REF!) -> #REF! | AI41: =SUMIF(#REF!,$A41,#REF!) -> #REF! | AJ41: =SUMIF(#REF!,$A41,#REF!) -> #REF! | AK41: =SUMIF(#REF!,$A41,#REF!) -> #REF! | AL41: =SUMIF(#REF!,$A41,#REF!) -> #REF! | ... AO41: =SUMIF(#REF!,$A41,#REF!) -> #REF!
A42: 170007 | B42: L/C MARGINAL DEPOSITS NCB | C42: =Q42+AE42 -> #REF! | D42: =R42+AF42 -> #REF! | E42: =S42+AG42 -> #REF! | F42: =T42+AH42 -> #REF! | G42: =U42+AI42 -> #REF! | H42: =V42+AJ42 -> #REF! | I42: =W42+AK42 -> #REF! | J42: =X42+AL42 -> #REF! | ... N42: =AB42+AP42 -> 0 | Q42: =SUMIF(#REF!,$A42,#REF!) -> #REF! | R42: =SUMIF(ALIF_Y2014!$A:$A,$A42,ALIF_Y2014!$F:$F) -> 1274692.6 | S42: =SUMIF(ALIF_Y2015!$A:$A,$A42,ALIF_Y2015!$F:$F) -> 319948.95 | T42: =SUMIF(ALIF_Y2016!$A:$A,$A42,ALIF_Y2016!$F:$F) -> 0 | U42: =SUMIF(ALIF_Y2017!$A:$A,$A42,ALIF_Y2017!$F:$F) -> 0 | V42: =SUMIF(ALIF_Y2018!$A:$A,$A42,ALIF_Y2018!$F:$F) -> 0 | W42: =SUMIF(ALIF_Y2019!$A:$A,$A42,ALIF_Y2019!$F:$F) -> 0 | X42: =SUMIF(ALIF_Y2020!$A:$A,$A42,ALIF_Y2020!$F:$F) -> 0 | Y42: =SUMIF(ALIF_Y2021!$A:$A,$A42,ALIF_Y2021!$F:$F) -> 0 | Z42: =SUMIF(ALIF_Y2022!$A:$A,$A42,ALIF_Y2022!$F:$F) -> 0 | AA42: =SUMIF(ALIF_Y2023!$A:$A,$A42,ALIF_Y2023!$F:$F) -> 0 | AE42: =SUMIF(#REF!,$A42,#REF!) -> #REF! | AF42: =SUMIF(#REF!,$A42,#REF!) -> #REF! | AG42: =SUMIF(#REF!,$A42,#REF!) -> #REF! | AH42: =SUMIF(#REF!,$A42,#REF!) -> #REF! | AI42: =SUMIF(#REF!,$A42,#REF!) -> #REF! | AJ42: =SUMIF(#REF!,$A42,#REF!) -> #REF! | AK42: =SUMIF(#REF!,$A42,#REF!) -> #REF! | AL42: =SUMIF(#REF!,$A42,#REF!) -> #REF! | ... AO42: =SUMIF(#REF!,$A42,#REF!) -> #REF!
A43: 170008 | B43: L/C MARGINAL DEPOSITS ALINMA | C43: =Q43+AE43 -> #REF! | D43: =R43+AF43 -> #REF! | E43: =S43+AG43 -> #REF! | F43: =T43+AH43 -> #REF! | G43: =U43+AI43 -> #REF! | H43: =V43+AJ43 -> #REF! | I43: =W43+AK43 -> #REF! | J43: =X43+AL43 -> #REF! | ... N43: =AB43+AP43 -> 0 | Q43: =SUMIF(#REF!,$A43,#REF!) -> #REF! | R43: =SUMIF(ALIF_Y2014!$A:$A,$A43,ALIF_Y2014!$F:$F) -> 0 | S43: =SUMIF(ALIF_Y2015!$A:$A,$A43,ALIF_Y2015!$F:$F) -> -0.002 | T43: =SUMIF(ALIF_Y2016!$A:$A,$A43,ALIF_Y2016!$F:$F) -> 0 | U43: =SUMIF(ALIF_Y2017!$A:$A,$A43,ALIF_Y2017!$F:$F) -> 0 | V43: =SUMIF(ALIF_Y2018!$A:$A,$A43,ALIF_Y2018!$F:$F) -> 0 | W43: =SUMIF(ALIF_Y2019!$A:$A,$A43,ALIF_Y2019!$F:$F) -> 75267.74 | X43: =SUMIF(ALIF_Y2020!$A:$A,$A43,ALIF_Y2020!$F:$F) -> 0 | Y43: =SUMIF(ALIF_Y2021!$A:$A,$A43,ALIF_Y2021!$F:$F) -> 402889.63 | Z43: =SUMIF(ALIF_Y2022!$A:$A,$A43,ALIF_Y2022!$F:$F) -> 0 | AA43: =SUMIF(ALIF_Y2023!$A:$A,$A43,ALIF_Y2023!$F:$F) -> 0 | AE43: =SUMIF(#REF!,$A43,#REF!) -> #REF! | AF43: =SUMIF(#REF!,$A43,#REF!) -> #REF! | AG43: =SUMIF(#REF!,$A43,#REF!) -> #REF! | AH43: =SUMIF(#REF!,$A43,#REF!) -> #REF! | AI43: =SUMIF(#REF!,$A43,#REF!) -> #REF! | AJ43: =SUMIF(#REF!,$A43,#REF!) -> #REF! | AK43: =SUMIF(#REF!,$A43,#REF!) -> #REF! | AL43: =SUMIF(#REF!,$A43,#REF!) -> #REF! | ... AO43: =SUMIF(#REF!,$A43,#REF!) -> #REF!
A44: 170009 | B44: PREPAID RENT | C44: =Q44+AE44 -> #REF! | D44: =R44+AF44 -> #REF! | E44: =S44+AG44 -> #REF! | F44: =T44+AH44 -> #REF! | G44: =U44+AI44 -> #REF! | H44: =V44+AJ44 -> #REF! | I44: =W44+AK44 -> #REF! | J44: =X44+AL44 -> #REF! | ... N44: =AB44+AP44 -> 0 | Q44: =SUMIF(#REF!,$A44,#REF!) -> #REF! | R44: =SUMIF(ALIF_Y2014!$A:$A,$A44,ALIF_Y2014!$F:$F) -> 120000.1 | S44: =SUMIF(ALIF_Y2015!$A:$A,$A44,ALIF_Y2015!$F:$F) -> 94955 | T44: =SUMIF(ALIF_Y2016!$A:$A,$A44,ALIF_Y2016!$F:$F) -> 59583 | U44: =SUMIF(ALIF_Y2017!$A:$A,$A44,ALIF_Y2017!$F:$F) -> 34444.001 | V44: =SUMIF(ALIF_Y2018!$A:$A,$A44,ALIF_Y2018!$F:$F) -> 75235 | W44: =SUMIF(ALIF_Y2019!$A:$A,$A44,ALIF_Y2019!$F:$F) -> 85513 | X44: =SUMIF(ALIF_Y2020!$A:$A,$A44,ALIF_Y2020!$F:$F) -> 64609 | Y44: =SUMIF(ALIF_Y2021!$A:$A,$A44,ALIF_Y2021!$F:$F) -> 33000 | Z44: =SUMIF(ALIF_Y2022!$A:$A,$A44,ALIF_Y2022!$F:$F) -> 62777 | AA44: =SUMIF(ALIF_Y2023!$A:$A,$A44,ALIF_Y2023!$F:$F) -> 60962 | AE44: =SUMIF(#REF!,$A44,#REF!) -> #REF! | AF44: =SUMIF(#REF!,$A44,#REF!) -> #REF! | AG44: =SUMIF(#REF!,$A44,#REF!) -> #REF! | AH44: =SUMIF(#REF!,$A44,#REF!) -> #REF! | AI44: =SUMIF(#REF!,$A44,#REF!) -> #REF! | AJ44: =SUMIF(#REF!,$A44,#REF!) -> #REF! | AK44: =SUMIF(#REF!,$A44,#REF!) -> #REF! | AL44: =SUMIF(#REF!,$A44,#REF!) -> #REF! | ... AO44: =SUMIF(#REF!,$A44,#REF!) -> #REF!
A45: 170010 | B45: PREPAID HOUSING ALLOWANCE | C45: =Q45+AE45 -> #REF! | D45: =R45+AF45 -> #REF! | E45: =S45+AG45 -> #REF! | F45: =T45+AH45 -> #REF! | G45: =U45+AI45 -> #REF! | H45: =V45+AJ45 -> #REF! | I45: =W45+AK45 -> #REF! | J45: =X45+AL45 -> #REF! | ... N45: =AB45+AP45 -> 0 | Q45: =SUMIF(#REF!,$A45,#REF!) -> #REF! | R45: =SUMIF(ALIF_Y2014!$A:$A,$A45,ALIF_Y2014!$F:$F) -> 0 | S45: =SUMIF(ALIF_Y2015!$A:$A,$A45,ALIF_Y2015!$F:$F) -> 0 | T45: =SUMIF(ALIF_Y2016!$A:$A,$A45,ALIF_Y2016!$F:$F) -> 0 | U45: =SUMIF(ALIF_Y2017!$A:$A,$A45,ALIF_Y2017!$F:$F) -> 0 | V45: =SUMIF(ALIF_Y2018!$A:$A,$A45,ALIF_Y2018!$F:$F) -> 0 | W45: =SUMIF(ALIF_Y2019!$A:$A,$A45,ALIF_Y2019!$F:$F) -> 0 | X45: =SUMIF(ALIF_Y2020!$A:$A,$A45,ALIF_Y2020!$F:$F) -> 0 | Y45: =SUMIF(ALIF_Y2021!$A:$A,$A45,ALIF_Y2021!$F:$F) -> 0 | Z45: =SUMIF(ALIF_Y2022!$A:$A,$A45,ALIF_Y2022!$F:$F) -> 0 | AA45: =SUMIF(ALIF_Y2023!$A:$A,$A45,ALIF_Y2023!$F:$F) -> 0 | AE45: =SUMIF(#REF!,$A45,#REF!) -> #REF! | AF45: =SUMIF(#REF!,$A45,#REF!) -> #REF! | AG45: =SUMIF(#REF!,$A45,#REF!) -> #REF! | AH45: =SUMIF(#REF!,$A45,#REF!) -> #REF! | AI45: =SUMIF(#REF!,$A45,#REF!) -> #REF! | AJ45: =SUMIF(#REF!,$A45,#REF!) -> #REF! | AK45: =SUMIF(#REF!,$A45,#REF!) -> #REF! | AL45: =SUMIF(#REF!,$A45,#REF!) -> #REF! | ... AO45: =SUMIF(#REF!,$A45,#REF!) -> #REF!
A46: 170011 | B46: PREPAID TICKETS&VISA ALLOWANCE | C46: =Q46+AE46 -> #REF! | D46: =R46+AF46 -> #REF! | E46: =S46+AG46 -> #REF! | F46: =T46+AH46 -> #REF! | G46: =U46+AI46 -> #REF! | H46: =V46+AJ46 -> #REF! | I46: =W46+AK46 -> #REF! | J46: =X46+AL46 -> #REF! | ... N46: =AB46+AP46 -> 0 | Q46: =SUMIF(#REF!,$A46,#REF!) -> #REF! | R46: =SUMIF(ALIF_Y2014!$A:$A,$A46,ALIF_Y2014!$F:$F) -> 0 | S46: =SUMIF(ALIF_Y2015!$A:$A,$A46,ALIF_Y2015!$F:$F) -> 0 | T46: =SUMIF(ALIF_Y2016!$A:$A,$A46,ALIF_Y2016!$F:$F) -> 0 | U46: =SUMIF(ALIF_Y2017!$A:$A,$A46,ALIF_Y2017!$F:$F) -> 0 | V46: =SUMIF(ALIF_Y2018!$A:$A,$A46,ALIF_Y2018!$F:$F) -> 175000 | W46: =SUMIF(ALIF_Y2019!$A:$A,$A46,ALIF_Y2019!$F:$F) -> 1453882.8 | X46: =SUMIF(ALIF_Y2020!$A:$A,$A46,ALIF_Y2020!$F:$F) -> 0 | Y46: =SUMIF(ALIF_Y2021!$A:$A,$A46,ALIF_Y2021!$F:$F) -> 0 | Z46: =SUMIF(ALIF_Y2022!$A:$A,$A46,ALIF_Y2022!$F:$F) -> 0 | AA46: =SUMIF(ALIF_Y2023!$A:$A,$A46,ALIF_Y2023!$F:$F) -> 0 | AE46: =SUMIF(#REF!,$A46,#REF!) -> #REF! | AF46: =SUMIF(#REF!,$A46,#REF!) -> #REF! | AG46: =SUMIF(#REF!,$A46,#REF!) -> #REF! | AH46: =SUMIF(#REF!,$A46,#REF!) -> #REF! | AI46: =SUMIF(#REF!,$A46,#REF!) -> #REF! | AJ46: =SUMIF(#REF!,$A46,#REF!) -> #REF! | AK46: =SUMIF(#REF!,$A46,#REF!) -> #REF! | AL46: =SUMIF(#REF!,$A46,#REF!) -> #REF! | ... AO46: =SUMIF(#REF!,$A46,#REF!) -> #REF!
A47: 170012 | B47: PREPAID FURNITURE ALLOWANCE | C47: =Q47+AE47 -> #REF! | D47: =R47+AF47 -> #REF! | E47: =S47+AG47 -> #REF! | F47: =T47+AH47 -> #REF! | G47: =U47+AI47 -> #REF! | H47: =V47+AJ47 -> #REF! | I47: =W47+AK47 -> #REF! | J47: =X47+AL47 -> #REF! | ... N47: =AB47+AP47 -> 0 | Q47: =SUMIF(#REF!,$A47,#REF!) -> #REF! | R47: =SUMIF(ALIF_Y2014!$A:$A,$A47,ALIF_Y2014!$F:$F) -> 0 | S47: =SUMIF(ALIF_Y2015!$A:$A,$A47,ALIF_Y2015!$F:$F) -> 0 | T47: =SUMIF(ALIF_Y2016!$A:$A,$A47,ALIF_Y2016!$F:$F) -> 0 | U47: =SUMIF(ALIF_Y2017!$A:$A,$A47,ALIF_Y2017!$F:$F) -> 0 | V47: =SUMIF(ALIF_Y2018!$A:$A,$A47,ALIF_Y2018!$F:$F) -> 0 | W47: =SUMIF(ALIF_Y2019!$A:$A,$A47,ALIF_Y2019!$F:$F) -> 214300 | X47: =SUMIF(ALIF_Y2020!$A:$A,$A47,ALIF_Y2020!$F:$F) -> 171440 | Y47: =SUMIF(ALIF_Y2021!$A:$A,$A47,ALIF_Y2021!$F:$F) -> 128580 | Z47: =SUMIF(ALIF_Y2022!$A:$A,$A47,ALIF_Y2022!$F:$F) -> -0.006 | AA47: =SUMIF(ALIF_Y2023!$A:$A,$A47,ALIF_Y2023!$F:$F) -> 0 | AE47: =SUMIF(#REF!,$A47,#REF!) -> #REF! | AF47: =SUMIF(#REF!,$A47,#REF!) -> #REF! | AG47: =SUMIF(#REF!,$A47,#REF!) -> #REF! | AH47: =SUMIF(#REF!,$A47,#REF!) -> #REF! | AI47: =SUMIF(#REF!,$A47,#REF!) -> #REF! | AJ47: =SUMIF(#REF!,$A47,#REF!) -> #REF! | AK47: =SUMIF(#REF!,$A47,#REF!) -> #REF! | AL47: =SUMIF(#REF!,$A47,#REF!) -> #REF! | ... AO47: =SUMIF(#REF!,$A47,#REF!) -> #REF!
A48: 170013 | B48: PREPAID INSURANCE RENT | C48: =Q48+AE48 -> #REF! | D48: =R48+AF48 -> #REF! | E48: =S48+AG48 -> #REF! | F48: =T48+AH48 -> #REF! | G48: =U48+AI48 -> #REF! | H48: =V48+AJ48 -> #REF! | I48: =W48+AK48 -> #REF! | J48: =X48+AL48 -> #REF! | ... N48: =AB48+AP48 -> 0 | Q48: =SUMIF(#REF!,$A48,#REF!) -> #REF! | R48: =SUMIF(ALIF_Y2014!$A:$A,$A48,ALIF_Y2014!$F:$F) -> 59000 | S48: =SUMIF(ALIF_Y2015!$A:$A,$A48,ALIF_Y2015!$F:$F) -> 59000 | T48: =SUMIF(ALIF_Y2016!$A:$A,$A48,ALIF_Y2016!$F:$F) -> 59000 | U48: =SUMIF(ALIF_Y2017!$A:$A,$A48,ALIF_Y2017!$F:$F) -> 59000 | V48: =SUMIF(ALIF_Y2018!$A:$A,$A48,ALIF_Y2018!$F:$F) -> 64000 | W48: =SUMIF(ALIF_Y2019!$A:$A,$A48,ALIF_Y2019!$F:$F) -> 67999.599 | X48: =SUMIF(ALIF_Y2020!$A:$A,$A48,ALIF_Y2020!$F:$F) -> 67999.599 | Y48: =SUMIF(ALIF_Y2021!$A:$A,$A48,ALIF_Y2021!$F:$F) -> 67999.599 | Z48: =SUMIF(ALIF_Y2022!$A:$A,$A48,ALIF_Y2022!$F:$F) -> 0 | AA48: =SUMIF(ALIF_Y2023!$A:$A,$A48,ALIF_Y2023!$F:$F) -> 0 | AE48: =SUMIF(#REF!,$A48,#REF!) -> #REF! | AF48: =SUMIF(#REF!,$A48,#REF!) -> #REF! | AG48: =SUMIF(#REF!,$A48,#REF!) -> #REF! | AH48: =SUMIF(#REF!,$A48,#REF!) -> #REF! | AI48: =SUMIF(#REF!,$A48,#REF!) -> #REF! | AJ48: =SUMIF(#REF!,$A48,#REF!) -> #REF! | AK48: =SUMIF(#REF!,$A48,#REF!) -> #REF! | AL48: =SUMIF(#REF!,$A48,#REF!) -> #REF! | ... AO48: =SUMIF(#REF!,$A48,#REF!) -> #REF!
... A56: 170021 | B56: PREPAID EXPENSES | C56: =Q56+AE56 -> #REF! | D56: =R56+AF56 -> #REF! | E56: =S56+AG56 -> #REF! | F56: =T56+AH56 -> #REF! | G56: =U56+AI56 -> #REF! | H56: =V56+AJ56 -> #REF! | I56: =W56+AK56 -> #REF! | J56: =X56+AL56 -> #REF! | ... N56: =AB56+AP56 -> 0 | Q56: =SUMIF(#REF!,$A56,#REF!) -> #REF! | R56: =SUMIF(ALIF_Y2014!$A:$A,$A56,ALIF_Y2014!$F:$F) -> 4501835.5 | S56: =SUMIF(ALIF_Y2015!$A:$A,$A56,ALIF_Y2015!$F:$F) -> 3062618 | T56: =SUMIF(ALIF_Y2016!$A:$A,$A56,ALIF_Y2016!$F:$F) -> 4741163.2 | U56: =SUMIF(ALIF_Y2017!$A:$A,$A56,ALIF_Y2017!$F:$F) -> 12679112 | V56: =SUMIF(ALIF_Y2018!$A:$A,$A56,ALIF_Y2018!$F:$F) -> 9600761.3 | W56: =SUMIF(ALIF_Y2019!$A:$A,$A56,ALIF_Y2019!$F:$F) -> 5773707.5 | X56: =SUMIF(ALIF_Y2020!$A:$A,$A56,ALIF_Y2020!$F:$F) -> 2935982.7 | Y56: =SUMIF(ALIF_Y2021!$A:$A,$A56,ALIF_Y2021!$F:$F) -> 2935982.7 | Z56: =SUMIF(ALIF_Y2022!$A:$A,$A56,ALIF_Y2022!$F:$F) -> 0 | AA56: =SUMIF(ALIF_Y2023!$A:$A,$A56,ALIF_Y2023!$F:$F) -> 4054218.4 | AE56: =SUMIF(#REF!,$A56,#REF!) -> #REF! | AF56: =SUMIF(#REF!,$A56,#REF!) -> #REF! | AG56: =SUMIF(#REF!,$A56,#REF!) -> #REF! | AH56: =SUMIF(#REF!,$A56,#REF!) -> #REF! | AI56: =SUMIF(#REF!,$A56,#REF!) -> #REF! | AJ56: =SUMIF(#REF!,$A56,#REF!) -> #REF! | AK56: =SUMIF(#REF!,$A56,#REF!) -> #REF! | AL56: =SUMIF(#REF!,$A56,#REF!) -> #REF! | ... AO56: =SUMIF(#REF!,$A56,#REF!) -> #REF!
C58: =SUM(C37:C57) -> #REF! | D58: =SUM(D37:D57) -> #REF! | E58: =SUM(E37:E57) -> #REF! | F58: =SUM(F37:F57) -> #REF! | G58: =SUM(G37:G57) -> #REF! | H58: =SUM(H37:H57) -> #REF! | I58: =SUM(I37:I57) -> #REF! | J58: =SUM(J37:J57) -> #REF! | ... N58: =SUM(N37:N57) -> 0 | Q58: =SUM(Q37:Q57) -> #REF! | R58: =SUM(R37:R57) -> 8670708.6 | S58: =SUM(S37:S57) -> 7700042.4 | T58: =SUM(T37:T57) -> 6566761.5 | U58: =SUM(U37:U57) -> 13100548 | V58: =SUM(V37:V57) -> 10942639 | W58: =SUM(W37:W57) -> 8522666 | X58: =SUM(X37:X57) -> 3692329.5 | ... AB58: =SUM(AB37:AB57) -> 0 | AE58: =SUM(AE37:AE57) -> #REF! | AF58: =SUM(AF37:AF57) -> #REF! | AG58: =SUM(AG37:AG57) -> #REF! | AH58: =SUM(AH37:AH57) -> #REF! | AI58: =SUM(AI37:AI57) -> #REF! | AJ58: =SUM(AJ37:AJ57) -> #REF! | AK58: =SUM(AK37:AK57) -> #REF! | AL58: =SUM(AL37:AL57) -> #REF! | ... AO58: =SUM(AO37:AO57) -> #REF!
A60: INVENTORIES
A61: 180001 | B61: CONSUMABLES | C61: =Q61+AE61 -> #REF! | D61: =R61+AF61 -> #REF! | E61: =S61+AG61 -> #REF! | F61: =T61+AH61 -> #REF! | G61: =U61+AI61 -> #REF! | H61: =V61+AJ61 -> #REF! | I61: =W61+AK61 -> #REF! | J61: =X61+AL61 -> #REF! | ... N61: =AB61+AP61 -> 0 | Q61: =SUMIF(#REF!,$A61,#REF!) -> #REF! | R61: =SUMIF(ALIF_Y2014!$A:$A,$A61,ALIF_Y2014!$F:$F) -> 156339.99 | S61: =SUMIF(ALIF_Y2015!$A:$A,$A61,ALIF_Y2015!$F:$F) -> 180341.72 | T61: =SUMIF(ALIF_Y2016!$A:$A,$A61,ALIF_Y2016!$F:$F) -> 0 | U61: =SUMIF(ALIF_Y2017!$A:$A,$A61,ALIF_Y2017!$F:$F) -> 0 | V61: =SUMIF(ALIF_Y2018!$A:$A,$A61,ALIF_Y2018!$F:$F) -> 0 | W61: =SUMIF(ALIF_Y2019!$A:$A,$A61,ALIF_Y2019!$F:$F) -> 0 | X61: =SUMIF(ALIF_Y2020!$A:$A,$A61,ALIF_Y2020!$F:$F) -> 460574.58 | Y61: =SUMIF(ALIF_Y2021!$A:$A,$A61,ALIF_Y2021!$F:$F) -> 472084.61 | Z61: =SUMIF(ALIF_Y2022!$A:$A,$A61,ALIF_Y2022!$F:$F) -> 579715.09 | AA61: =SUMIF(ALIF_Y2023!$A:$A,$A61,ALIF_Y2023!$F:$F) -> 393596.77 | AE61: =SUMIF(#REF!,$A61,#REF!) -> #REF! | AF61: =SUMIF(#REF!,$A61,#REF!) -> #REF! | AG61: =SUMIF(#REF!,$A61,#REF!) -> #REF! | AH61: =SUMIF(#REF!,$A61,#REF!) -> #REF! | AI61: =SUMIF(#REF!,$A61,#REF!) -> #REF! | AJ61: =SUMIF(#REF!,$A61,#REF!) -> #REF! | AK61: =SUMIF(#REF!,$A61,#REF!) -> #REF! | AL61: =SUMIF(#REF!,$A61,#REF!) -> #REF! | ... AO61: =SUMIF(#REF!,$A61,#REF!) -> #REF!
A62: 180002 | B62: INDIRECT MATERIAL | C62: =Q62+AE62 -> #REF! | D62: =R62+AF62 -> #REF! | E62: =S62+AG62 -> #REF! | F62: =T62+AH62 -> #REF! | G62: =U62+AI62 -> #REF! | H62: =V62+AJ62 -> #REF! | I62: =W62+AK62 -> #REF! | J62: =X62+AL62 -> #REF! | ... N62: =AB62+AP62 -> 0 | Q62: =SUMIF(#REF!,$A62,#REF!) -> #REF! | R62: =SUMIF(ALIF_Y2014!$A:$A,$A62,ALIF_Y2014!$F:$F) -> 0 | S62: =SUMIF(ALIF_Y2015!$A:$A,$A62,ALIF_Y2015!$F:$F) -> 0 | T62: =SUMIF(ALIF_Y2016!$A:$A,$A62,ALIF_Y2016!$F:$F) -> 0 | U62: =SUMIF(ALIF_Y2017!$A:$A,$A62,ALIF_Y2017!$F:$F) -> 0 | V62: =SUMIF(ALIF_Y2018!$A:$A,$A62,ALIF_Y2018!$F:$F) -> 0 | W62: =SUMIF(ALIF_Y2019!$A:$A,$A62,ALIF_Y2019!$F:$F) -> 0 | X62: =SUMIF(ALIF_Y2020!$A:$A,$A62,ALIF_Y2020!$F:$F) -> 0 | Y62: =SUMIF(ALIF_Y2021!$A:$A,$A62,ALIF_Y2021!$F:$F) -> 0 | Z62: =SUMIF(ALIF_Y2022!$A:$A,$A62,ALIF_Y2022!$F:$F) -> 0 | AA62: =SUMIF(ALIF_Y2023!$A:$A,$A62,ALIF_Y2023!$F:$F) -> 0 | AE62: =SUMIF(#REF!,$A62,#REF!) -> #REF! | AF62: =SUMIF(#REF!,$A62,#REF!) -> #REF! | AG62: =SUMIF(#REF!,$A62,#REF!) -> #REF! | AH62: =SUMIF(#REF!,$A62,#REF!) -> #REF! | AI62: =SUMIF(#REF!,$A62,#REF!) -> #REF! | AJ62: =SUMIF(#REF!,$A62,#REF!) -> #REF! | AK62: =SUMIF(#REF!,$A62,#REF!) -> #REF! | AL62: =SUMIF(#REF!,$A62,#REF!) -> #REF! | ... AO62: =SUMIF(#REF!,$A62,#REF!) -> #REF!
A63: 180003 | B63: SPARE PARTS | C63: =Q63+AE63 -> #REF! | D63: =R63+AF63 -> #REF! | E63: =S63+AG63 -> #REF! | F63: =T63+AH63 -> #REF! | G63: =U63+AI63 -> #REF! | H63: =V63+AJ63 -> #REF! | I63: =W63+AK63 -> #REF! | J63: =X63+AL63 -> #REF! | ... N63: =AB63+AP63 -> 0 | Q63: =SUMIF(#REF!,$A63,#REF!) -> #REF! | R63: =SUMIF(ALIF_Y2014!$A:$A,$A63,ALIF_Y2014!$F:$F) -> 653513.33 | S63: =SUMIF(ALIF_Y2015!$A:$A,$A63,ALIF_Y2015!$F:$F) -> 1662493.5 | T63: =SUMIF(ALIF_Y2016!$A:$A,$A63,ALIF_Y2016!$F:$F) -> 3495512.4 | U63: =SUMIF(ALIF_Y2017!$A:$A,$A63,ALIF_Y2017!$F:$F) -> 3299574 | V63: =SUMIF(ALIF_Y2018!$A:$A,$A63,ALIF_Y2018!$F:$F) -> 6617902 | W63: =SUMIF(ALIF_Y2019!$A:$A,$A63,ALIF_Y2019!$F:$F) -> 9335439.2 | X63: =SUMIF(ALIF_Y2020!$A:$A,$A63,ALIF_Y2020!$F:$F) -> 9861152.8 | Y63: =SUMIF(ALIF_Y2021!$A:$A,$A63,ALIF_Y2021!$F:$F) -> 8204122.4 | Z63: =SUMIF(ALIF_Y2022!$A:$A,$A63,ALIF_Y2022!$F:$F) -> 8453179.4 | AA63: =SUMIF(ALIF_Y2023!$A:$A,$A63,ALIF_Y2023!$F:$F) -> 7034865.1 | AE63: =SUMIF(#REF!,$A63,#REF!) -> #REF! | AF63: =SUMIF(#REF!,$A63,#REF!) -> #REF! | AG63: =SUMIF(#REF!,$A63,#REF!) -> #REF! | AH63: =SUMIF(#REF!,$A63,#REF!) -> #REF! | AI63: =SUMIF(#REF!,$A63,#REF!) -> #REF! | AJ63: =SUMIF(#REF!,$A63,#REF!) -> #REF! | AK63: =SUMIF(#REF!,$A63,#REF!) -> #REF! | AL63: =SUMIF(#REF!,$A63,#REF!) -> #REF! | ... AO63: =SUMIF(#REF!,$A63,#REF!) -> #REF!
A64: 180004 | B64: RAW MAT MAT LOW CARBON | C64: =Q64+AE64 -> #REF! | D64: =R64+AF64 -> #REF! | E64: =S64+AG64 -> #REF! | F64: =T64+AH64 -> #REF! | G64: =U64+AI64 -> #REF! | H64: =V64+AJ64 -> #REF! | I64: =W64+AK64 -> #REF! | J64: =X64+AL64 -> #REF! | ... N64: =AB64+AP64 -> 0 | Q64: =SUMIF(#REF!,$A64,#REF!) -> #REF! | R64: =SUMIF(ALIF_Y2014!$A:$A,$A64,ALIF_Y2014!$F:$F) -> 7043113.4 | S64: =SUMIF(ALIF_Y2015!$A:$A,$A64,ALIF_Y2015!$F:$F) -> 3346088.3 | T64: =SUMIF(ALIF_Y2016!$A:$A,$A64,ALIF_Y2016!$F:$F) -> 2005087.6 | U64: =SUMIF(ALIF_Y2017!$A:$A,$A64,ALIF_Y2017!$F:$F) -> 5349660.4 | V64: =SUMIF(ALIF_Y2018!$A:$A,$A64,ALIF_Y2018!$F:$F) -> 17461291 | W64: =SUMIF(ALIF_Y2019!$A:$A,$A64,ALIF_Y2019!$F:$F) -> 10353609 | X64: =SUMIF(ALIF_Y2020!$A:$A,$A64,ALIF_Y2020!$F:$F) -> 6375063.9 | Y64: =SUMIF(ALIF_Y2021!$A:$A,$A64,ALIF_Y2021!$F:$F) -> 21414672 | Z64: =SUMIF(ALIF_Y2022!$A:$A,$A64,ALIF_Y2022!$F:$F) -> 24628809 | AA64: =SUMIF(ALIF_Y2023!$A:$A,$A64,ALIF_Y2023!$F:$F) -> 12721521 | AE64: =SUMIF(#REF!,$A64,#REF!) -> #REF! | AF64: =SUMIF(#REF!,$A64,#REF!) -> #REF! | AG64: =SUMIF(#REF!,$A64,#REF!) -> #REF! | AH64: =SUMIF(#REF!,$A64,#REF!) -> #REF! | AI64: =SUMIF(#REF!,$A64,#REF!) -> #REF! | AJ64: =SUMIF(#REF!,$A64,#REF!) -> #REF! | AK64: =SUMIF(#REF!,$A64,#REF!) -> #REF! | AL64: =SUMIF(#REF!,$A64,#REF!) -> #REF! | ... AO64: =SUMIF(#REF!,$A64,#REF!) -> #REF!
A65: 180005 | B65: RAW MAT HIGH CARBON | C65: =Q65+AE65 -> #REF! | D65: =R65+AF65 -> #REF! | E65: =S65+AG65 -> #REF! | F65: =T65+AH65 -> #REF! | G65: =U65+AI65 -> #REF! | H65: =V65+AJ65 -> #REF! | I65: =W65+AK65 -> #REF! | J65: =X65+AL65 -> #REF! | ... N65: =AB65+AP65 -> 0 | Q65: =SUMIF(#REF!,$A65,#REF!) -> #REF! | R65: =SUMIF(ALIF_Y2014!$A:$A,$A65,ALIF_Y2014!$F:$F) -> 5804758.6 | S65: =SUMIF(ALIF_Y2015!$A:$A,$A65,ALIF_Y2015!$F:$F) -> 5751580.6 | T65: =SUMIF(ALIF_Y2016!$A:$A,$A65,ALIF_Y2016!$F:$F) -> 1175699.1 | U65: =SUMIF(ALIF_Y2017!$A:$A,$A65,ALIF_Y2017!$F:$F) -> 2403225 | V65: =SUMIF(ALIF_Y2018!$A:$A,$A65,ALIF_Y2018!$F:$F) -> 13671939 | W65: =SUMIF(ALIF_Y2019!$A:$A,$A65,ALIF_Y2019!$F:$F) -> 14923756 | X65: =SUMIF(ALIF_Y2020!$A:$A,$A65,ALIF_Y2020!$F:$F) -> 13945866 | Y65: =SUMIF(ALIF_Y2021!$A:$A,$A65,ALIF_Y2021!$F:$F) -> 10850303 | Z65: =SUMIF(ALIF_Y2022!$A:$A,$A65,ALIF_Y2022!$F:$F) -> 22323654 | AA65: =SUMIF(ALIF_Y2023!$A:$A,$A65,ALIF_Y2023!$F:$F) -> 6421066.5 | AE65: =SUMIF(#REF!,$A65,#REF!) -> #REF! | AF65: =SUMIF(#REF!,$A65,#REF!) -> #REF! | AG65: =SUMIF(#REF!,$A65,#REF!) -> #REF! | AH65: =SUMIF(#REF!,$A65,#REF!) -> #REF! | AI65: =SUMIF(#REF!,$A65,#REF!) -> #REF! | AJ65: =SUMIF(#REF!,$A65,#REF!) -> #REF! | AK65: =SUMIF(#REF!,$A65,#REF!) -> #REF! | AL65: =SUMIF(#REF!,$A65,#REF!) -> #REF! | ... AO65: =SUMIF(#REF!,$A65,#REF!) -> #REF!
A66: 180006 | B66: RAW MAT GI COILS | C66: =Q66+AE66 -> #REF! | D66: =R66+AF66 -> #REF! | E66: =S66+AG66 -> #REF! | F66: =T66+AH66 -> #REF! | G66: =U66+AI66 -> #REF! | H66: =V66+AJ66 -> #REF! | I66: =W66+AK66 -> #REF! | J66: =X66+AL66 -> #REF! | ... N66: =AB66+AP66 -> 0 | Q66: =SUMIF(#REF!,$A66,#REF!) -> #REF! | R66: =SUMIF(ALIF_Y2014!$A:$A,$A66,ALIF_Y2014!$F:$F) -> 673548.34 | S66: =SUMIF(ALIF_Y2015!$A:$A,$A66,ALIF_Y2015!$F:$F) -> 1294747 | T66: =SUMIF(ALIF_Y2016!$A:$A,$A66,ALIF_Y2016!$F:$F) -> 1169679 | U66: =SUMIF(ALIF_Y2017!$A:$A,$A66,ALIF_Y2017!$F:$F) -> 425239.42 | V66: =SUMIF(ALIF_Y2018!$A:$A,$A66,ALIF_Y2018!$F:$F) -> 3405824.1 | W66: =SUMIF(ALIF_Y2019!$A:$A,$A66,ALIF_Y2019!$F:$F) -> 1669803.7 | X66: =SUMIF(ALIF_Y2020!$A:$A,$A66,ALIF_Y2020!$F:$F) -> 378972.3 | Y66: =SUMIF(ALIF_Y2021!$A:$A,$A66,ALIF_Y2021!$F:$F) -> 606029 | Z66: =SUMIF(ALIF_Y2022!$A:$A,$A66,ALIF_Y2022!$F:$F) -> 1300362.8 | AA66: =SUMIF(ALIF_Y2023!$A:$A,$A66,ALIF_Y2023!$F:$F) -> 485139.35 | AE66: =SUMIF(#REF!,$A66,#REF!) -> #REF! | AF66: =SUMIF(#REF!,$A66,#REF!) -> #REF! | AG66: =SUMIF(#REF!,$A66,#REF!) -> #REF! | AH66: =SUMIF(#REF!,$A66,#REF!) -> #REF! | AI66: =SUMIF(#REF!,$A66,#REF!) -> #REF! | AJ66: =SUMIF(#REF!,$A66,#REF!) -> #REF! | AK66: =SUMIF(#REF!,$A66,#REF!) -> #REF! | AL66: =SUMIF(#REF!,$A66,#REF!) -> #REF! | ... AO66: =SUMIF(#REF!,$A66,#REF!) -> #REF!
A67: 180007 | B67: RAW MAT COPPER | C67: =Q67+AE67 -> #REF! | D67: =R67+AF67 -> #REF! | E67: =S67+AG67 -> #REF! | F67: =T67+AH67 -> #REF! | G67: =U67+AI67 -> #REF! | H67: =V67+AJ67 -> #REF! | I67: =W67+AK67 -> #REF! | J67: =X67+AL67 -> #REF! | ... N67: =AB67+AP67 -> 0 | Q67: =SUMIF(#REF!,$A67,#REF!) -> #REF! | R67: =SUMIF(ALIF_Y2014!$A:$A,$A67,ALIF_Y2014!$F:$F) -> 2013760 | S67: =SUMIF(ALIF_Y2015!$A:$A,$A67,ALIF_Y2015!$F:$F) -> 1532382.6 | T67: =SUMIF(ALIF_Y2016!$A:$A,$A67,ALIF_Y2016!$F:$F) -> 2977379.3 | U67: =SUMIF(ALIF_Y2017!$A:$A,$A67,ALIF_Y2017!$F:$F) -> 1090998.2 | V67: =SUMIF(ALIF_Y2018!$A:$A,$A67,ALIF_Y2018!$F:$F) -> 1973924.3 | W67: =SUMIF(ALIF_Y2019!$A:$A,$A67,ALIF_Y2019!$F:$F) -> 4219396.8 | X67: =SUMIF(ALIF_Y2020!$A:$A,$A67,ALIF_Y2020!$F:$F) -> 1119777.1 | Y67: =SUMIF(ALIF_Y2021!$A:$A,$A67,ALIF_Y2021!$F:$F) -> 2466116.9 | Z67: =SUMIF(ALIF_Y2022!$A:$A,$A67,ALIF_Y2022!$F:$F) -> 6583839.9 | AA67: =SUMIF(ALIF_Y2023!$A:$A,$A67,ALIF_Y2023!$F:$F) -> 144366.5 | AE67: =SUMIF(#REF!,$A67,#REF!) -> #REF! | AF67: =SUMIF(#REF!,$A67,#REF!) -> #REF! | AG67: =SUMIF(#REF!,$A67,#REF!) -> #REF! | AH67: =SUMIF(#REF!,$A67,#REF!) -> #REF! | AI67: =SUMIF(#REF!,$A67,#REF!) -> #REF! | AJ67: =SUMIF(#REF!,$A67,#REF!) -> #REF! | AK67: =SUMIF(#REF!,$A67,#REF!) -> #REF! | AL67: =SUMIF(#REF!,$A67,#REF!) -> #REF! | ... AO67: =SUMIF(#REF!,$A67,#REF!) -> #REF!
A68: 180008 | B68: RAW MAT FLAT STEEL | C68: =Q68+AE68 -> #REF! | D68: =R68+AF68 -> #REF! | E68: =S68+AG68 -> #REF! | F68: =T68+AH68 -> #REF! | G68: =U68+AI68 -> #REF! | H68: =V68+AJ68 -> #REF! | I68: =W68+AK68 -> #REF! | J68: =X68+AL68 -> #REF! | ... N68: =AB68+AP68 -> 0 | Q68: =SUMIF(#REF!,$A68,#REF!) -> #REF! | R68: =SUMIF(ALIF_Y2014!$A:$A,$A68,ALIF_Y2014!$F:$F) -> 1442056.2 | S68: =SUMIF(ALIF_Y2015!$A:$A,$A68,ALIF_Y2015!$F:$F) -> 1499877.8 | T68: =SUMIF(ALIF_Y2016!$A:$A,$A68,ALIF_Y2016!$F:$F) -> 1400127.8 | U68: =SUMIF(ALIF_Y2017!$A:$A,$A68,ALIF_Y2017!$F:$F) -> 1568037.8 | V68: =SUMIF(ALIF_Y2018!$A:$A,$A68,ALIF_Y2018!$F:$F) -> 1868994.2 | W68: =SUMIF(ALIF_Y2019!$A:$A,$A68,ALIF_Y2019!$F:$F) -> 1599925.7 | X68: =SUMIF(ALIF_Y2020!$A:$A,$A68,ALIF_Y2020!$F:$F) -> 0 | Y68: =SUMIF(ALIF_Y2021!$A:$A,$A68,ALIF_Y2021!$F:$F) -> 0 | Z68: =SUMIF(ALIF_Y2022!$A:$A,$A68,ALIF_Y2022!$F:$F) -> 0 | AA68: =SUMIF(ALIF_Y2023!$A:$A,$A68,ALIF_Y2023!$F:$F) -> 0 | AE68: =SUMIF(#REF!,$A68,#REF!) -> #REF! | AF68: =SUMIF(#REF!,$A68,#REF!) -> #REF! | AG68: =SUMIF(#REF!,$A68,#REF!) -> #REF! | AH68: =SUMIF(#REF!,$A68,#REF!) -> #REF! | AI68: =SUMIF(#REF!,$A68,#REF!) -> #REF! | AJ68: =SUMIF(#REF!,$A68,#REF!) -> #REF! | AK68: =SUMIF(#REF!,$A68,#REF!) -> #REF! | AL68: =SUMIF(#REF!,$A68,#REF!) -> #REF! | ... AO68: =SUMIF(#REF!,$A68,#REF!) -> #REF!
A69: 180009 | B69: RAW MATERIAL | C69: =Q69+AE69 -> #REF! | D69: =R69+AF69 -> #REF! | E69: =S69+AG69 -> #REF! | F69: =T69+AH69 -> #REF! | G69: =U69+AI69 -> #REF! | H69: =V69+AJ69 -> #REF! | I69: =W69+AK69 -> #REF! | J69: =X69+AL69 -> #REF! | ... N69: =AB69+AP69 -> 0 | Q69: =SUMIF(#REF!,$A69,#REF!) -> #REF! | R69: =SUMIF(ALIF_Y2014!$A:$A,$A69,ALIF_Y2014!$F:$F) -> 1 | S69: =SUMIF(ALIF_Y2015!$A:$A,$A69,ALIF_Y2015!$F:$F) -> 0 | T69: =SUMIF(ALIF_Y2016!$A:$A,$A69,ALIF_Y2016!$F:$F) -> 6916688.3 | U69: =SUMIF(ALIF_Y2017!$A:$A,$A69,ALIF_Y2017!$F:$F) -> -0.02 | V69: =SUMIF(ALIF_Y2018!$A:$A,$A69,ALIF_Y2018!$F:$F) -> -0.004 | W69: =SUMIF(ALIF_Y2019!$A:$A,$A69,ALIF_Y2019!$F:$F) -> 0 | X69: =SUMIF(ALIF_Y2020!$A:$A,$A69,ALIF_Y2020!$F:$F) -> 0 | Y69: =SUMIF(ALIF_Y2021!$A:$A,$A69,ALIF_Y2021!$F:$F) -> 0 | Z69: =SUMIF(ALIF_Y2022!$A:$A,$A69,ALIF_Y2022!$F:$F) -> 0 | AA69: =SUMIF(ALIF_Y2023!$A:$A,$A69,ALIF_Y2023!$F:$F) -> 0 | AE69: =SUMIF(#REF!,$A69,#REF!) -> #REF! | AF69: =SUMIF(#REF!,$A69,#REF!) -> #REF! | AG69: =SUMIF(#REF!,$A69,#REF!) -> #REF! | AH69: =SUMIF(#REF!,$A69,#REF!) -> #REF! | AI69: =SUMIF(#REF!,$A69,#REF!) -> #REF! | AJ69: =SUMIF(#REF!,$A69,#REF!) -> #REF! | AK69: =SUMIF(#REF!,$A69,#REF!) -> #REF! | AL69: =SUMIF(#REF!,$A69,#REF!) -> #REF! | ... AO69: =SUMIF(#REF!,$A69,#REF!) -> #REF!
A70: 180010 | B70: PACKAGING | C70: =Q70+AE70 -> #REF! | D70: =R70+AF70 -> #REF! | E70: =S70+AG70 -> #REF! | F70: =T70+AH70 -> #REF! | G70: =U70+AI70 -> #REF! | H70: =V70+AJ70 -> #REF! | I70: =W70+AK70 -> #REF! | J70: =X70+AL70 -> #REF! | ... N70: =AB70+AP70 -> 0 | Q70: =SUMIF(#REF!,$A70,#REF!) -> #REF! | R70: =SUMIF(ALIF_Y2014!$A:$A,$A70,ALIF_Y2014!$F:$F) -> 1212335.8 | S70: =SUMIF(ALIF_Y2015!$A:$A,$A70,ALIF_Y2015!$F:$F) -> 1327453.8 | T70: =SUMIF(ALIF_Y2016!$A:$A,$A70,ALIF_Y2016!$F:$F) -> 1398956.8 | U70: =SUMIF(ALIF_Y2017!$A:$A,$A70,ALIF_Y2017!$F:$F) -> 1731640.5 | V70: =SUMIF(ALIF_Y2018!$A:$A,$A70,ALIF_Y2018!$F:$F) -> 3284487 | W70: =SUMIF(ALIF_Y2019!$A:$A,$A70,ALIF_Y2019!$F:$F) -> 4243921.4 | X70: =SUMIF(ALIF_Y2020!$A:$A,$A70,ALIF_Y2020!$F:$F) -> 2923428.3 | Y70: =SUMIF(ALIF_Y2021!$A:$A,$A70,ALIF_Y2021!$F:$F) -> 3671446.1 | Z70: =SUMIF(ALIF_Y2022!$A:$A,$A70,ALIF_Y2022!$F:$F) -> 3804138.3 | AA70: =SUMIF(ALIF_Y2023!$A:$A,$A70,ALIF_Y2023!$F:$F) -> 2205127.1 | AE70: =SUMIF(#REF!,$A70,#REF!) -> #REF! | AF70: =SUMIF(#REF!,$A70,#REF!) -> #REF! | AG70: =SUMIF(#REF!,$A70,#REF!) -> #REF! | AH70: =SUMIF(#REF!,$A70,#REF!) -> #REF! | AI70: =SUMIF(#REF!,$A70,#REF!) -> #REF! | AJ70: =SUMIF(#REF!,$A70,#REF!) -> #REF! | AK70: =SUMIF(#REF!,$A70,#REF!) -> #REF! | AL70: =SUMIF(#REF!,$A70,#REF!) -> #REF! | ... AO70: =SUMIF(#REF!,$A70,#REF!) -> #REF!
A71: 180011 | B71: FINISHED GOODS | C71: =Q71+AE71 -> #REF! | D71: =R71+AF71 -> #REF! | E71: =S71+AG71 -> #REF! | F71: =T71+AH71 -> #REF! | G71: =U71+AI71 -> #REF! | H71: =V71+AJ71 -> #REF! | I71: =W71+AK71 -> #REF! | J71: =X71+AL71 -> #REF! | ... N71: =AB71+AP71 -> 0 | Q71: =SUMIF(#REF!,$A71,#REF!) -> #REF! | R71: =SUMIF(ALIF_Y2014!$A:$A,$A71,ALIF_Y2014!$F:$F) -> 5822773.6 | S71: =SUMIF(ALIF_Y2015!$A:$A,$A71,ALIF_Y2015!$F:$F) -> 3798456.9 | T71: =SUMIF(ALIF_Y2016!$A:$A,$A71,ALIF_Y2016!$F:$F) -> 3693398.7 | U71: =SUMIF(ALIF_Y2017!$A:$A,$A71,ALIF_Y2017!$F:$F) -> 3759293.7 | V71: =SUMIF(ALIF_Y2018!$A:$A,$A71,ALIF_Y2018!$F:$F) -> 5990529.9 | W71: =SUMIF(ALIF_Y2019!$A:$A,$A71,ALIF_Y2019!$F:$F) -> 4916872 | X71: =SUMIF(ALIF_Y2020!$A:$A,$A71,ALIF_Y2020!$F:$F) -> 2860145.8 | Y71: =SUMIF(ALIF_Y2021!$A:$A,$A71,ALIF_Y2021!$F:$F) -> 4353614.1 | Z71: =SUMIF(ALIF_Y2022!$A:$A,$A71,ALIF_Y2022!$F:$F) -> 15057739 | AA71: =SUMIF(ALIF_Y2023!$A:$A,$A71,ALIF_Y2023!$F:$F) -> 9655616.8 | AE71: =SUMIF(#REF!,$A71,#REF!) -> #REF! | AF71: =SUMIF(#REF!,$A71,#REF!) -> #REF! | AG71: =SUMIF(#REF!,$A71,#REF!) -> #REF! | AH71: =SUMIF(#REF!,$A71,#REF!) -> #REF! | AI71: =SUMIF(#REF!,$A71,#REF!) -> #REF! | AJ71: =SUMIF(#REF!,$A71,#REF!) -> #REF! | AK71: =SUMIF(#REF!,$A71,#REF!) -> #REF! | AL71: =SUMIF(#REF!,$A71,#REF!) -> #REF! | ... AO71: =SUMIF(#REF!,$A71,#REF!) -> #REF!
A72: 180012 | B72: SEMI FINISHED GOODS | C72: =Q72+AE72 -> #REF! | D72: =R72+AF72 -> #REF! | E72: =S72+AG72 -> #REF! | F72: =T72+AH72 -> #REF! | G72: =U72+AI72 -> #REF! | H72: =V72+AJ72 -> #REF! | I72: =W72+AK72 -> #REF! | J72: =X72+AL72 -> #REF! | ... N72: =AB72+AP72 -> 0 | Q72: =SUMIF(#REF!,$A72,#REF!) -> #REF! | R72: =SUMIF(ALIF_Y2014!$A:$A,$A72,ALIF_Y2014!$F:$F) -> 3491023.6 | S72: =SUMIF(ALIF_Y2015!$A:$A,$A72,ALIF_Y2015!$F:$F) -> 2714442 | T72: =SUMIF(ALIF_Y2016!$A:$A,$A72,ALIF_Y2016!$F:$F) -> 2233950.1 | U72: =SUMIF(ALIF_Y2017!$A:$A,$A72,ALIF_Y2017!$F:$F) -> 1969194.7 | V72: =SUMIF(ALIF_Y2018!$A:$A,$A72,ALIF_Y2018!$F:$F) -> 4155373.4 | W72: =SUMIF(ALIF_Y2019!$A:$A,$A72,ALIF_Y2019!$F:$F) -> 6324009.8 | X72: =SUMIF(ALIF_Y2020!$A:$A,$A72,ALIF_Y2020!$F:$F) -> 3169104.7 | Y72: =SUMIF(ALIF_Y2021!$A:$A,$A72,ALIF_Y2021!$F:$F) -> 3568332.1 | Z72: =SUMIF(ALIF_Y2022!$A:$A,$A72,ALIF_Y2022!$F:$F) -> 5027391.9 | AA72: =SUMIF(ALIF_Y2023!$A:$A,$A72,ALIF_Y2023!$F:$F) -> 1499189.1 | AE72: =SUMIF(#REF!,$A72,#REF!) -> #REF! | AF72: =SUMIF(#REF!,$A72,#REF!) -> #REF! | AG72: =SUMIF(#REF!,$A72,#REF!) -> #REF! | AH72: =SUMIF(#REF!,$A72,#REF!) -> #REF! | AI72: =SUMIF(#REF!,$A72,#REF!) -> #REF! | AJ72: =SUMIF(#REF!,$A72,#REF!) -> #REF! | AK72: =SUMIF(#REF!,$A72,#REF!) -> #REF! | AL72: =SUMIF(#REF!,$A72,#REF!) -> #REF! | ... AO72: =SUMIF(#REF!,$A72,#REF!) -> #REF!
... A79: 260004 | B79: PROVISION FOR DAMAGED & EXPIRED MATERIAL | C79: =Q79+AE79 -> #REF! | D79: =R79+AF79 -> #REF! | E79: =S79+AG79 -> #REF! | F79: =T79+AH79 -> #REF! | G79: =U79+AI79 -> #REF! | H79: =V79+AJ79 -> #REF! | I79: =W79+AK79 -> #REF! | J79: =X79+AL79 -> #REF! | ... N79: =AB79+AP79 -> 0 | Q79: =SUMIF(#REF!,$A79,#REF!) -> #REF! | R79: =SUMIF(ALIF_Y2014!$A:$A,$A79,ALIF_Y2014!$F:$F) -> 0 | S79: =SUMIF(ALIF_Y2015!$A:$A,$A79,ALIF_Y2015!$F:$F) -> 0 | T79: =SUMIF(ALIF_Y2016!$A:$A,$A79,ALIF_Y2016!$F:$F) -> -1121501.4 | U79: =SUMIF(ALIF_Y2017!$A:$A,$A79,ALIF_Y2017!$F:$F) -> -1121501.4 | V79: =SUMIF(ALIF_Y2018!$A:$A,$A79,ALIF_Y2018!$F:$F) -> -1121501.4 | W79: =SUMIF(ALIF_Y2019!$A:$A,$A79,ALIF_Y2019!$F:$F) -> -849296.43 | X79: =SUMIF(ALIF_Y2020!$A:$A,$A79,ALIF_Y2020!$F:$F) -> -2000000 | Y79: =SUMIF(ALIF_Y2021!$A:$A,$A79,ALIF_Y2021!$F:$F) -> 0 | Z79: =SUMIF(ALIF_Y2022!$A:$A,$A79,ALIF_Y2022!$F:$F) -> 0 | AA79: =SUMIF(ALIF_Y2023!$A:$A,$A79,ALIF_Y2023!$F:$F) -> 0 | AE79: =SUMIF(#REF!,$A79,#REF!) -> #REF! | AF79: =SUMIF(#REF!,$A79,#REF!) -> #REF! | AG79: =SUMIF(#REF!,$A79,#REF!) -> #REF! | AH79: =SUMIF(#REF!,$A79,#REF!) -> #REF! | AI79: =SUMIF(#REF!,$A79,#REF!) -> #REF! | AJ79: =SUMIF(#REF!,$A79,#REF!) -> #REF! | AK79: =SUMIF(#REF!,$A79,#REF!) -> #REF! | AL79: =SUMIF(#REF!,$A79,#REF!) -> #REF! | ... AO79: =SUMIF(#REF!,$A79,#REF!) -> #REF!
C81: =SUM(C61:C80) -> #REF! | D81: =SUM(D61:D80) -> #REF! | E81: =SUM(E61:E80) -> #REF! | F81: =SUM(F61:F80) -> #REF! | G81: =SUM(G61:G80) -> #REF! | H81: =SUM(H61:H80) -> #REF! | I81: =SUM(I61:I80) -> #REF! | J81: =SUM(J61:J80) -> #REF! | ... N81: =SUM(N61:N80) -> 0 | Q81: =SUM(Q61:Q80) -> #REF! | R81: =SUM(R61:R80) -> 34065376 | S81: =SUM(S61:S80) -> 28412734 | T81: =SUM(T61:T80) -> 31557771 | U81: =SUM(U61:U80) -> 25847131 | V81: =SUM(V61:V80) -> 65632734 | W81: =SUM(W61:W80) -> 63336468 | X81: =SUM(X61:X80) -> 45810721 | ... AB81: =SUM(AB61:AB80) -> 0 | AE81: =SUM(AE61:AE80) -> #REF! | AF81: =SUM(AF61:AF80) -> #REF! | AG81: =SUM(AG61:AG80) -> #REF! | AH81: =SUM(AH61:AH80) -> #REF! | AI81: =SUM(AI61:AI80) -> #REF! | AJ81: =SUM(AJ61:AJ80) -> #REF! | AK81: =SUM(AK61:AK80) -> #REF! | AL81: =SUM(AL61:AL80) -> #REF! | ... AO81: =SUM(AO61:AO80) -> #REF!
A83: DUE FROM RP
A86: PROPERTY, PLANT AND EQUIPMENT
A87: 110001 | B87: LAND | C87: =Q87+AE87 -> #REF! | D87: =R87+AF87 -> #REF! | E87: =S87+AG87 -> #REF! | F87: =T87+AH87 -> #REF! | G87: =U87+AI87 -> #REF! | H87: =V87+AJ87 -> #REF! | I87: =W87+AK87 -> #REF! | J87: =X87+AL87 -> #REF! | ... N87: =AB87+AP87 -> 0 | Q87: =SUMIF(#REF!,$A87,#REF!) -> #REF! | R87: =SUMIF(ALIF_Y2014!$A:$A,$A87,ALIF_Y2014!$F:$F) -> 0 | S87: =SUMIF(ALIF_Y2015!$A:$A,$A87,ALIF_Y2015!$F:$F) -> 0 | T87: =SUMIF(ALIF_Y2016!$A:$A,$A87,ALIF_Y2016!$F:$F) -> 0 | U87: =SUMIF(ALIF_Y2017!$A:$A,$A87,ALIF_Y2017!$F:$F) -> 0 | V87: =SUMIF(ALIF_Y2018!$A:$A,$A87,ALIF_Y2018!$F:$F) -> 0 | W87: =SUMIF(ALIF_Y2019!$A:$A,$A87,ALIF_Y2019!$F:$F) -> 0 | X87: =SUMIF(ALIF_Y2020!$A:$A,$A87,ALIF_Y2020!$F:$F) -> 0 | Y87: =SUMIF(ALIF_Y2021!$A:$A,$A87,ALIF_Y2021!$F:$F) -> 0 | Z87: =SUMIF(ALIF_Y2022!$A:$A,$A87,ALIF_Y2022!$F:$F) -> 0 | AA87: =SUMIF(ALIF_Y2023!$A:$A,$A87,ALIF_Y2023!$F:$F) -> 0 | AE87: =SUMIF(#REF!,$A87,#REF!) -> #REF! | AF87: =SUMIF(#REF!,$A87,#REF!) -> #REF! | AG87: =SUMIF(#REF!,$A87,#REF!) -> #REF! | AH87: =SUMIF(#REF!,$A87,#REF!) -> #REF! | AI87: =SUMIF(#REF!,$A87,#REF!) -> #REF! | AJ87: =SUMIF(#REF!,$A87,#REF!) -> #REF! | AK87: =SUMIF(#REF!,$A87,#REF!) -> #REF! | AL87: =SUMIF(#REF!,$A87,#REF!) -> #REF! | ... AO87: =SUMIF(#REF!,$A87,#REF!) -> #REF!
A88: 110002 | B88: BUILDINGS | C88: =Q88+AE88 -> #REF! | D88: =R88+AF88 -> #REF! | E88: =S88+AG88 -> #REF! | F88: =T88+AH88 -> #REF! | G88: =U88+AI88 -> #REF! | H88: =V88+AJ88 -> #REF! | I88: =W88+AK88 -> #REF! | J88: =X88+AL88 -> #REF! | ... N88: =AB88+AP88 -> 0 | Q88: =SUMIF(#REF!,$A88,#REF!) -> #REF! | R88: =SUMIF(ALIF_Y2014!$A:$A,$A88,ALIF_Y2014!$F:$F) -> 249682 | S88: =SUMIF(ALIF_Y2015!$A:$A,$A88,ALIF_Y2015!$F:$F) -> 249682 | T88: =SUMIF(ALIF_Y2016!$A:$A,$A88,ALIF_Y2016!$F:$F) -> 249682 | U88: =SUMIF(ALIF_Y2017!$A:$A,$A88,ALIF_Y2017!$F:$F) -> 249682 | V88: =SUMIF(ALIF_Y2018!$A:$A,$A88,ALIF_Y2018!$F:$F) -> 1.06505e+08 | W88: =SUMIF(ALIF_Y2019!$A:$A,$A88,ALIF_Y2019!$F:$F) -> 1.06505e+08 | X88: =SUMIF(ALIF_Y2020!$A:$A,$A88,ALIF_Y2020!$F:$F) -> 1.06505e+08 | Y88: =SUMIF(ALIF_Y2021!$A:$A,$A88,ALIF_Y2021!$F:$F) -> 1.06505e+08 | Z88: =SUMIF(ALIF_Y2022!$A:$A,$A88,ALIF_Y2022!$F:$F) -> 1.06505e+08 | AA88: =SUMIF(ALIF_Y2023!$A:$A,$A88,ALIF_Y2023!$F:$F) -> 1.06505e+08 | AE88: =SUMIF(#REF!,$A88,#REF!) -> #REF! | AF88: =SUMIF(#REF!,$A88,#REF!) -> #REF! | AG88: =SUMIF(#REF!,$A88,#REF!) -> #REF! | AH88: =SUMIF(#REF!,$A88,#REF!) -> #REF! | AI88: =SUMIF(#REF!,$A88,#REF!) -> #REF! | AJ88: =SUMIF(#REF!,$A88,#REF!) -> #REF! | AK88: =SUMIF(#REF!,$A88,#REF!) -> #REF! | AL88: =SUMIF(#REF!,$A88,#REF!) -> #REF! | ... AO88: =SUMIF(#REF!,$A88,#REF!) -> #REF!
A89: 110003 | B89: DECORS AND INSTALLATIONS | C89: =Q89+AE89 -> #REF! | D89: =R89+AF89 -> #REF! | E89: =S89+AG89 -> #REF! | F89: =T89+AH89 -> #REF! | G89: =U89+AI89 -> #REF! | H89: =V89+AJ89 -> #REF! | I89: =W89+AK89 -> #REF! | J89: =X89+AL89 -> #REF! | ... N89: =AB89+AP89 -> 0 | Q89: =SUMIF(#REF!,$A89,#REF!) -> #REF! | R89: =SUMIF(ALIF_Y2014!$A:$A,$A89,ALIF_Y2014!$F:$F) -> 1765393.8 | S89: =SUMIF(ALIF_Y2015!$A:$A,$A89,ALIF_Y2015!$F:$F) -> 1773233.8 | T89: =SUMIF(ALIF_Y2016!$A:$A,$A89,ALIF_Y2016!$F:$F) -> 1773233.8 | U89: =SUMIF(ALIF_Y2017!$A:$A,$A89,ALIF_Y2017!$F:$F) -> 1773233.8 | V89: =SUMIF(ALIF_Y2018!$A:$A,$A89,ALIF_Y2018!$F:$F) -> 1824603.8 | W89: =SUMIF(ALIF_Y2019!$A:$A,$A89,ALIF_Y2019!$F:$F) -> 1920201.8 | X89: =SUMIF(ALIF_Y2020!$A:$A,$A89,ALIF_Y2020!$F:$F) -> 1765393.8 | Y89: =SUMIF(ALIF_Y2021!$A:$A,$A89,ALIF_Y2021!$F:$F) -> 1765393.8 | Z89: =SUMIF(ALIF_Y2022!$A:$A,$A89,ALIF_Y2022!$F:$F) -> 1765393.8 | AA89: =SUMIF(ALIF_Y2023!$A:$A,$A89,ALIF_Y2023!$F:$F) -> 1765393.8 | AE89: =SUMIF(#REF!,$A89,#REF!) -> #REF! | AF89: =SUMIF(#REF!,$A89,#REF!) -> #REF! | AG89: =SUMIF(#REF!,$A89,#REF!) -> #REF! | AH89: =SUMIF(#REF!,$A89,#REF!) -> #REF! | AI89: =SUMIF(#REF!,$A89,#REF!) -> #REF! | AJ89: =SUMIF(#REF!,$A89,#REF!) -> #REF! | AK89: =SUMIF(#REF!,$A89,#REF!) -> #REF! | AL89: =SUMIF(#REF!,$A89,#REF!) -> #REF! | ... AO89: =SUMIF(#REF!,$A89,#REF!) -> #REF!
A90: 110004 | B90: MACHINERY AND EQUIPMENTS | C90: =Q90+AE90 -> #REF! | D90: =R90+AF90 -> #REF! | E90: =S90+AG90 -> #REF! | F90: =T90+AH90 -> #REF! | G90: =U90+AI90 -> #REF! | H90: =V90+AJ90 -> #REF! | I90: =W90+AK90 -> #REF! | J90: =X90+AL90 -> #REF! | ... N90: =AB90+AP90 -> 0 | Q90: =SUMIF(#REF!,$A90,#REF!) -> #REF! | R90: =SUMIF(ALIF_Y2014!$A:$A,$A90,ALIF_Y2014!$F:$F) -> 38561941 | S90: =SUMIF(ALIF_Y2015!$A:$A,$A90,ALIF_Y2015!$F:$F) -> 39518811 | T90: =SUMIF(ALIF_Y2016!$A:$A,$A90,ALIF_Y2016!$F:$F) -> 39914308 | U90: =SUMIF(ALIF_Y2017!$A:$A,$A90,ALIF_Y2017!$F:$F) -> 43898751 | V90: =SUMIF(ALIF_Y2018!$A:$A,$A90,ALIF_Y2018!$F:$F) -> 62879993 | W90: =SUMIF(ALIF_Y2019!$A:$A,$A90,ALIF_Y2019!$F:$F) -> 66375893 | X90: =SUMIF(ALIF_Y2020!$A:$A,$A90,ALIF_Y2020!$F:$F) -> 71133086 | Y90: =SUMIF(ALIF_Y2021!$A:$A,$A90,ALIF_Y2021!$F:$F) -> 72216302 | Z90: =SUMIF(ALIF_Y2022!$A:$A,$A90,ALIF_Y2022!$F:$F) -> 80282872 | AA90: =SUMIF(ALIF_Y2023!$A:$A,$A90,ALIF_Y2023!$F:$F) -> 72478281 | AE90: =SUMIF(#REF!,$A90,#REF!) -> #REF! | AF90: =SUMIF(#REF!,$A90,#REF!) -> #REF! | AG90: =SUMIF(#REF!,$A90,#REF!) -> #REF! | AH90: =SUMIF(#REF!,$A90,#REF!) -> #REF! | AI90: =SUMIF(#REF!,$A90,#REF!) -> #REF! | AJ90: =SUMIF(#REF!,$A90,#REF!) -> #REF! | AK90: =SUMIF(#REF!,$A90,#REF!) -> #REF! | AL90: =SUMIF(#REF!,$A90,#REF!) -> #REF! | ... AO90: =SUMIF(#REF!,$A90,#REF!) -> #REF!
A91: 110006 | B91: VEHICLES | C91: =Q91+AE91 -> #REF! | D91: =R91+AF91 -> #REF! | E91: =S91+AG91 -> #REF! | F91: =T91+AH91 -> #REF! | G91: =U91+AI91 -> #REF! | H91: =V91+AJ91 -> #REF! | I91: =W91+AK91 -> #REF! | J91: =X91+AL91 -> #REF! | ... N91: =AB91+AP91 -> 0 | Q91: =SUMIF(#REF!,$A91,#REF!) -> #REF! | R91: =SUMIF(ALIF_Y2014!$A:$A,$A91,ALIF_Y2014!$F:$F) -> 1446052.1 | S91: =SUMIF(ALIF_Y2015!$A:$A,$A91,ALIF_Y2015!$F:$F) -> 1446052.1 | T91: =SUMIF(ALIF_Y2016!$A:$A,$A91,ALIF_Y2016!$F:$F) -> 1548852.1 | U91: =SUMIF(ALIF_Y2017!$A:$A,$A91,ALIF_Y2017!$F:$F) -> 1891752.1 | V91: =SUMIF(ALIF_Y2018!$A:$A,$A91,ALIF_Y2018!$F:$F) -> 2495208.5 | W91: =SUMIF(ALIF_Y2019!$A:$A,$A91,ALIF_Y2019!$F:$F) -> 2791352.1 | X91: =SUMIF(ALIF_Y2020!$A:$A,$A91,ALIF_Y2020!$F:$F) -> 2602761 | Y91: =SUMIF(ALIF_Y2021!$A:$A,$A91,ALIF_Y2021!$F:$F) -> 2675451 | Z91: =SUMIF(ALIF_Y2022!$A:$A,$A91,ALIF_Y2022!$F:$F) -> 3033459.7 | AA91: =SUMIF(ALIF_Y2023!$A:$A,$A91,ALIF_Y2023!$F:$F) -> 3090755.7 | AE91: =SUMIF(#REF!,$A91,#REF!) -> #REF! | AF91: =SUMIF(#REF!,$A91,#REF!) -> #REF! | AG91: =SUMIF(#REF!,$A91,#REF!) -> #REF! | AH91: =SUMIF(#REF!,$A91,#REF!) -> #REF! | AI91: =SUMIF(#REF!,$A91,#REF!) -> #REF! | AJ91: =SUMIF(#REF!,$A91,#REF!) -> #REF! | AK91: =SUMIF(#REF!,$A91,#REF!) -> #REF! | AL91: =SUMIF(#REF!,$A91,#REF!) -> #REF! | ... AO91: =SUMIF(#REF!,$A91,#REF!) -> #REF!
A92: 110007 | B92: OFFICE EQUIPMENTS& COMPUTR PROGRAMS INSTALLATIONS | C92: =Q92+AE92 -> #REF! | D92: =R92+AF92 -> #REF! | E92: =S92+AG92 -> #REF! | F92: =T92+AH92 -> #REF! | G92: =U92+AI92 -> #REF! | H92: =V92+AJ92 -> #REF! | I92: =W92+AK92 -> #REF! | J92: =X92+AL92 -> #REF! | ... N92: =AB92+AP92 -> 0 | Q92: =SUMIF(#REF!,$A92,#REF!) -> #REF! | R92: =SUMIF(ALIF_Y2014!$A:$A,$A92,ALIF_Y2014!$F:$F) -> 798523.45 | S92: =SUMIF(ALIF_Y2015!$A:$A,$A92,ALIF_Y2015!$F:$F) -> 798523.45 | T92: =SUMIF(ALIF_Y2016!$A:$A,$A92,ALIF_Y2016!$F:$F) -> 798523.45 | U92: =SUMIF(ALIF_Y2017!$A:$A,$A92,ALIF_Y2017!$F:$F) -> 798523.45 | V92: =SUMIF(ALIF_Y2018!$A:$A,$A92,ALIF_Y2018!$F:$F) -> 876515.95 | W92: =SUMIF(ALIF_Y2019!$A:$A,$A92,ALIF_Y2019!$F:$F) -> 876515.95 | X92: =SUMIF(ALIF_Y2020!$A:$A,$A92,ALIF_Y2020!$F:$F) -> 1191638.9 | Y92: =SUMIF(ALIF_Y2021!$A:$A,$A92,ALIF_Y2021!$F:$F) -> 2056841.1 | Z92: =SUMIF(ALIF_Y2022!$A:$A,$A92,ALIF_Y2022!$F:$F) -> 2100287.9 | AA92: =SUMIF(ALIF_Y2023!$A:$A,$A92,ALIF_Y2023!$F:$F) -> 2100287.9 | AE92: =SUMIF(#REF!,$A92,#REF!) -> #REF! | AF92: =SUMIF(#REF!,$A92,#REF!) -> #REF! | AG92: =SUMIF(#REF!,$A92,#REF!) -> #REF! | AH92: =SUMIF(#REF!,$A92,#REF!) -> #REF! | AI92: =SUMIF(#REF!,$A92,#REF!) -> #REF! | AJ92: =SUMIF(#REF!,$A92,#REF!) -> #REF! | AK92: =SUMIF(#REF!,$A92,#REF!) -> #REF! | AL92: =SUMIF(#REF!,$A92,#REF!) -> #REF! | ... AO92: =SUMIF(#REF!,$A92,#REF!) -> #REF!
A93: 110008 | B93: FURNITURE AND FITTINGS | C93: =Q93+AE93 -> #REF! | D93: =R93+AF93 -> #REF! | E93: =S93+AG93 -> #REF! | F93: =T93+AH93 -> #REF! | G93: =U93+AI93 -> #REF! | H93: =V93+AJ93 -> #REF! | I93: =W93+AK93 -> #REF! | J93: =X93+AL93 -> #REF! | ... N93: =AB93+AP93 -> 0 | Q93: =SUMIF(#REF!,$A93,#REF!) -> #REF! | R93: =SUMIF(ALIF_Y2014!$A:$A,$A93,ALIF_Y2014!$F:$F) -> 191765.4 | S93: =SUMIF(ALIF_Y2015!$A:$A,$A93,ALIF_Y2015!$F:$F) -> 191765.4 | T93: =SUMIF(ALIF_Y2016!$A:$A,$A93,ALIF_Y2016!$F:$F) -> 191765.4 | U93: =SUMIF(ALIF_Y2017!$A:$A,$A93,ALIF_Y2017!$F:$F) -> 191765.4 | V93: =SUMIF(ALIF_Y2018!$A:$A,$A93,ALIF_Y2018!$F:$F) -> 533547.4 | W93: =SUMIF(ALIF_Y2019!$A:$A,$A93,ALIF_Y2019!$F:$F) -> 616788.35 | X93: =SUMIF(ALIF_Y2020!$A:$A,$A93,ALIF_Y2020!$F:$F) -> 961301.68 | Y93: =SUMIF(ALIF_Y2021!$A:$A,$A93,ALIF_Y2021!$F:$F) -> 1015678.5 | Z93: =SUMIF(ALIF_Y2022!$A:$A,$A93,ALIF_Y2022!$F:$F) -> 1101801 | AA93: =SUMIF(ALIF_Y2023!$A:$A,$A93,ALIF_Y2023!$F:$F) -> 1101801 | AE93: =SUMIF(#REF!,$A93,#REF!) -> #REF! | AF93: =SUMIF(#REF!,$A93,#REF!) -> #REF! | AG93: =SUMIF(#REF!,$A93,#REF!) -> #REF! | AH93: =SUMIF(#REF!,$A93,#REF!) -> #REF! | AI93: =SUMIF(#REF!,$A93,#REF!) -> #REF! | AJ93: =SUMIF(#REF!,$A93,#REF!) -> #REF! | AK93: =SUMIF(#REF!,$A93,#REF!) -> #REF! | AL93: =SUMIF(#REF!,$A93,#REF!) -> #REF! | ... AO93: =SUMIF(#REF!,$A93,#REF!) -> #REF!
C95: =SUM(C87:C94) -> #REF! | D95: =SUM(D87:D94) -> #REF! | E95: =SUM(E87:E94) -> #REF! | F95: =SUM(F87:F94) -> #REF! | G95: =SUM(G87:G94) -> #REF! | H95: =SUM(H87:H94) -> #REF! | I95: =SUM(I87:I94) -> #REF! | J95: =SUM(J87:J94) -> #REF! | ... N95: =SUM(N87:N94) -> 0 | Q95: =SUM(Q87:Q94) -> #REF! | R95: =SUM(R87:R94) -> 43013358 | S95: =SUM(S87:S94) -> 43978068 | T95: =SUM(T87:T94) -> 44476365 | U95: =SUM(U87:U94) -> 48803708 | V95: =SUM(V87:V94) -> 1.7511486e+08 | W95: =SUM(W87:W94) -> 1.7908575e+08 | X95: =SUM(X87:X94) -> 1.8415918e+08 | ... AB95: =SUM(AB87:AB94) -> 0 | AE95: =SUM(AE87:AE94) -> #REF! | AF95: =SUM(AF87:AF94) -> #REF! | AG95: =SUM(AG87:AG94) -> #REF! | AH95: =SUM(AH87:AH94) -> #REF! | AI95: =SUM(AI87:AI94) -> #REF! | AJ95: =SUM(AJ87:AJ94) -> #REF! | AK95: =SUM(AK87:AK94) -> #REF! | AL95: =SUM(AL87:AL94) -> #REF! | ... AP95: =SUM(AP87:AP94) -> 0
A97: 120001 | B97: ACCUM DEPR BUILDINGS | C97: =Q97+AE97 -> #REF! | D97: =R97+AF97 -> #REF! | E97: =S97+AG97 -> #REF! | F97: =T97+AH97 -> #REF! | G97: =U97+AI97 -> #REF! | H97: =V97+AJ97 -> #REF! | I97: =W97+AK97 -> #REF! | J97: =X97+AL97 -> #REF! | ... N97: =AB97+AP97 -> 0 | Q97: =SUMIF(#REF!,$A97,#REF!) -> #REF! | R97: =SUMIF(ALIF_Y2014!$A:$A,$A97,ALIF_Y2014!$F:$F) -> -227682.83 | S97: =SUMIF(ALIF_Y2015!$A:$A,$A97,ALIF_Y2015!$F:$F) -> -242695.31 | T97: =SUMIF(ALIF_Y2016!$A:$A,$A97,ALIF_Y2016!$F:$F) -> -249150.34 | U97: =SUMIF(ALIF_Y2017!$A:$A,$A97,ALIF_Y2017!$F:$F) -> -249682.01 | V97: =SUMIF(ALIF_Y2018!$A:$A,$A97,ALIF_Y2018!$F:$F) -> -694867.69 | W97: =SUMIF(ALIF_Y2019!$A:$A,$A97,ALIF_Y2019!$F:$F) -> -2186446.3 | X97: =SUMIF(ALIF_Y2020!$A:$A,$A97,ALIF_Y2020!$F:$F) -> -3753290.5 | Y97: =SUMIF(ALIF_Y2021!$A:$A,$A97,ALIF_Y2021!$F:$F) -> -5320134.7 | Z97: =SUMIF(ALIF_Y2022!$A:$A,$A97,ALIF_Y2022!$F:$F) -> -6886978.9 | AA97: =SUMIF(ALIF_Y2023!$A:$A,$A97,ALIF_Y2023!$F:$F) -> -8453823.1 | AE97: =SUMIF(#REF!,$A97,#REF!) -> #REF! | AF97: =SUMIF(#REF!,$A97,#REF!) -> #REF! | AG97: =SUMIF(#REF!,$A97,#REF!) -> #REF! | AH97: =SUMIF(#REF!,$A97,#REF!) -> #REF! | AI97: =SUMIF(#REF!,$A97,#REF!) -> #REF! | AJ97: =SUMIF(#REF!,$A97,#REF!) -> #REF! | AK97: =SUMIF(#REF!,$A97,#REF!) -> #REF! | AL97: =SUMIF(#REF!,$A97,#REF!) -> #REF! | ... AO97: =SUMIF(#REF!,$A97,#REF!) -> #REF!
A98: 120002 | B98: ACCUM DEPR DECORS | C98: =Q98+AE98 -> #REF! | D98: =R98+AF98 -> #REF! | E98: =S98+AG98 -> #REF! | F98: =T98+AH98 -> #REF! | G98: =U98+AI98 -> #REF! | H98: =V98+AJ98 -> #REF! | I98: =W98+AK98 -> #REF! | J98: =X98+AL98 -> #REF! | ... N98: =AB98+AP98 -> 0 | Q98: =SUMIF(#REF!,$A98,#REF!) -> #REF! | R98: =SUMIF(ALIF_Y2014!$A:$A,$A98,ALIF_Y2014!$F:$F) -> -1715968.2 | S98: =SUMIF(ALIF_Y2015!$A:$A,$A98,ALIF_Y2015!$F:$F) -> -1760034 | T98: =SUMIF(ALIF_Y2016!$A:$A,$A98,ALIF_Y2016!$F:$F) -> -1767394 | U98: =SUMIF(ALIF_Y2017!$A:$A,$A98,ALIF_Y2017!$F:$F) -> -1769803.9 | V98: =SUMIF(ALIF_Y2018!$A:$A,$A98,ALIF_Y2018!$F:$F) -> -1782181.4 | W98: =SUMIF(ALIF_Y2019!$A:$A,$A98,ALIF_Y2019!$F:$F) -> -1796679.8 | X98: =SUMIF(ALIF_Y2020!$A:$A,$A98,ALIF_Y2020!$F:$F) -> -1765393.8 | Y98: =SUMIF(ALIF_Y2021!$A:$A,$A98,ALIF_Y2021!$F:$F) -> -1765393.8 | Z98: =SUMIF(ALIF_Y2022!$A:$A,$A98,ALIF_Y2022!$F:$F) -> -1765393.8 | AA98: =SUMIF(ALIF_Y2023!$A:$A,$A98,ALIF_Y2023!$F:$F) -> -1765393.8 | AE98: =SUMIF(#REF!,$A98,#REF!) -> #REF! | AF98: =SUMIF(#REF!,$A98,#REF!) -> #REF! | AG98: =SUMIF(#REF!,$A98,#REF!) -> #REF! | AH98: =SUMIF(#REF!,$A98,#REF!) -> #REF! | AI98: =SUMIF(#REF!,$A98,#REF!) -> #REF! | AJ98: =SUMIF(#REF!,$A98,#REF!) -> #REF! | AK98: =SUMIF(#REF!,$A98,#REF!) -> #REF! | AL98: =SUMIF(#REF!,$A98,#REF!) -> #REF! | ... AO98: =SUMIF(#REF!,$A98,#REF!) -> #REF!
A99: 120003 | B99: ACCUM DEPR M AND E | C99: =Q99+AE99 -> #REF! | D99: =R99+AF99 -> #REF! | E99: =S99+AG99 -> #REF! | F99: =T99+AH99 -> #REF! | G99: =U99+AI99 -> #REF! | H99: =V99+AJ99 -> #REF! | I99: =W99+AK99 -> #REF! | J99: =X99+AL99 -> #REF! | ... N99: =AB99+AP99 -> 0 | Q99: =SUMIF(#REF!,$A99,#REF!) -> #REF! | R99: =SUMIF(ALIF_Y2014!$A:$A,$A99,ALIF_Y2014!$F:$F) -> -20403680 | S99: =SUMIF(ALIF_Y2015!$A:$A,$A99,ALIF_Y2015!$F:$F) -> -23854971 | T99: =SUMIF(ALIF_Y2016!$A:$A,$A99,ALIF_Y2016!$F:$F) -> -27289887 | U99: =SUMIF(ALIF_Y2017!$A:$A,$A99,ALIF_Y2017!$F:$F) -> -30823322 | V99: =SUMIF(ALIF_Y2018!$A:$A,$A99,ALIF_Y2018!$F:$F) -> -34787312 | W99: =SUMIF(ALIF_Y2019!$A:$A,$A99,ALIF_Y2019!$F:$F) -> -38426516 | X99: =SUMIF(ALIF_Y2020!$A:$A,$A99,ALIF_Y2020!$F:$F) -> -36593196 | Y99: =SUMIF(ALIF_Y2021!$A:$A,$A99,ALIF_Y2021!$F:$F) -> -40039866 | Z99: =SUMIF(ALIF_Y2022!$A:$A,$A99,ALIF_Y2022!$F:$F) -> -43870448 | AA99: =SUMIF(ALIF_Y2023!$A:$A,$A99,ALIF_Y2023!$F:$F) -> -41530055 | AE99: =SUMIF(#REF!,$A99,#REF!) -> #REF! | AF99: =SUMIF(#REF!,$A99,#REF!) -> #REF! | AG99: =SUMIF(#REF!,$A99,#REF!) -> #REF! | AH99: =SUMIF(#REF!,$A99,#REF!) -> #REF! | AI99: =SUMIF(#REF!,$A99,#REF!) -> #REF! | AJ99: =SUMIF(#REF!,$A99,#REF!) -> #REF! | AK99: =SUMIF(#REF!,$A99,#REF!) -> #REF! | AL99: =SUMIF(#REF!,$A99,#REF!) -> #REF! | ... AO99: =SUMIF(#REF!,$A99,#REF!) -> #REF!
A100: 120005 | B100: ACCUM DEPR VEHICLES | C100: =Q100+AE100 -> #REF! | D100: =R100+AF100 -> #REF! | E100: =S100+AG100 -> #REF! | F100: =T100+AH100 -> #REF! | G100: =U100+AI100 -> #REF! | H100: =V100+AJ100 -> #REF! | I100: =W100+AK100 -> #REF! | J100: =X100+AL100 -> #REF! | ... N100: =AB100+AP100 -> 0 | Q100: =SUMIF(#REF!,$A100,#REF!) -> #REF! | R100: =SUMIF(ALIF_Y2014!$A:$A,$A100,ALIF_Y2014!$F:$F) -> -1053780.6 | S100: =SUMIF(ALIF_Y2015!$A:$A,$A100,ALIF_Y2015!$F:$F) -> -1243716 | T100: =SUMIF(ALIF_Y2016!$A:$A,$A100,ALIF_Y2016!$F:$F) -> -1332799.3 | U100: =SUMIF(ALIF_Y2017!$A:$A,$A100,ALIF_Y2017!$F:$F) -> -1421470.1 | V100: =SUMIF(ALIF_Y2018!$A:$A,$A100,ALIF_Y2018!$F:$F) -> -1571590.6 | W100: =SUMIF(ALIF_Y2019!$A:$A,$A100,ALIF_Y2019!$F:$F) -> -1767726 | X100: =SUMIF(ALIF_Y2020!$A:$A,$A100,ALIF_Y2020!$F:$F) -> -1917847.1 | Y100: =SUMIF(ALIF_Y2021!$A:$A,$A100,ALIF_Y2021!$F:$F) -> -2024836.4 | Z100: =SUMIF(ALIF_Y2022!$A:$A,$A100,ALIF_Y2022!$F:$F) -> -2184859.5 | AA100: =SUMIF(ALIF_Y2023!$A:$A,$A100,ALIF_Y2023!$F:$F) -> -2378006.8 | AE100: =SUMIF(#REF!,$A100,#REF!) -> #REF! | AF100: =SUMIF(#REF!,$A100,#REF!) -> #REF! | AG100: =SUMIF(#REF!,$A100,#REF!) -> #REF! | AH100: =SUMIF(#REF!,$A100,#REF!) -> #REF! | AI100: =SUMIF(#REF!,$A100,#REF!) -> #REF! | AJ100: =SUMIF(#REF!,$A100,#REF!) -> #REF! | AK100: =SUMIF(#REF!,$A100,#REF!) -> #REF! | AL100: =SUMIF(#REF!,$A100,#REF!) -> #REF! | ... AO100: =SUMIF(#REF!,$A100,#REF!) -> #REF!
A101: 120006 | B101: ACCUM DEPR OE | C101: =Q101+AE101 -> #REF! | D101: =R101+AF101 -> #REF! | E101: =S101+AG101 -> #REF! | F101: =T101+AH101 -> #REF! | G101: =U101+AI101 -> #REF! | H101: =V101+AJ101 -> #REF! | I101: =W101+AK101 -> #REF! | J101: =X101+AL101 -> #REF! | ... N101: =AB101+AP101 -> 0 | Q101: =SUMIF(#REF!,$A101,#REF!) -> #REF! | R101: =SUMIF(ALIF_Y2014!$A:$A,$A101,ALIF_Y2014!$F:$F) -> -69116.08 | S101: =SUMIF(ALIF_Y2015!$A:$A,$A101,ALIF_Y2015!$F:$F) -> -255844.21 | T101: =SUMIF(ALIF_Y2016!$A:$A,$A101,ALIF_Y2016!$F:$F) -> -439911.34 | U101: =SUMIF(ALIF_Y2017!$A:$A,$A101,ALIF_Y2017!$F:$F) -> -619613.8 | V101: =SUMIF(ALIF_Y2018!$A:$A,$A101,ALIF_Y2018!$F:$F) -> -812734.49 | W101: =SUMIF(ALIF_Y2019!$A:$A,$A101,ALIF_Y2019!$F:$F) -> -832232.89 | X101: =SUMIF(ALIF_Y2020!$A:$A,$A101,ALIF_Y2020!$F:$F) -> -928574.01 | Y101: =SUMIF(ALIF_Y2021!$A:$A,$A101,ALIF_Y2021!$F:$F) -> -1048090.1 | Z101: =SUMIF(ALIF_Y2022!$A:$A,$A101,ALIF_Y2022!$F:$F) -> -1338351.8 | AA101: =SUMIF(ALIF_Y2023!$A:$A,$A101,ALIF_Y2023!$F:$F) -> -1629306.5 | AE101: =SUMIF(#REF!,$A101,#REF!) -> #REF! | AF101: =SUMIF(#REF!,$A101,#REF!) -> #REF! | AG101: =SUMIF(#REF!,$A101,#REF!) -> #REF! | AH101: =SUMIF(#REF!,$A101,#REF!) -> #REF! | AI101: =SUMIF(#REF!,$A101,#REF!) -> #REF! | AJ101: =SUMIF(#REF!,$A101,#REF!) -> #REF! | AK101: =SUMIF(#REF!,$A101,#REF!) -> #REF! | AL101: =SUMIF(#REF!,$A101,#REF!) -> #REF! | ... AO101: =SUMIF(#REF!,$A101,#REF!) -> #REF!
A102: 120007 | B102: ACCUM DEPR F AND F | C102: =Q102+AE102 -> #REF! | D102: =R102+AF102 -> #REF! | E102: =S102+AG102 -> #REF! | F102: =T102+AH102 -> #REF! | G102: =U102+AI102 -> #REF! | H102: =V102+AJ102 -> #REF! | I102: =W102+AK102 -> #REF! | J102: =X102+AL102 -> #REF! | ... N102: =AB102+AP102 -> 0 | Q102: =SUMIF(#REF!,$A102,#REF!) -> #REF! | R102: =SUMIF(ALIF_Y2014!$A:$A,$A102,ALIF_Y2014!$F:$F) -> -154323.32 | S102: =SUMIF(ALIF_Y2015!$A:$A,$A102,ALIF_Y2015!$F:$F) -> -167396.32 | T102: =SUMIF(ALIF_Y2016!$A:$A,$A102,ALIF_Y2016!$F:$F) -> -176382.9 | U102: =SUMIF(ALIF_Y2017!$A:$A,$A102,ALIF_Y2017!$F:$F) -> -182314.43 | V102: =SUMIF(ALIF_Y2018!$A:$A,$A102,ALIF_Y2018!$F:$F) -> -221019.98 | W102: =SUMIF(ALIF_Y2019!$A:$A,$A102,ALIF_Y2019!$F:$F) -> -264210.01 | X102: =SUMIF(ALIF_Y2020!$A:$A,$A102,ALIF_Y2020!$F:$F) -> -320357.62 | Y102: =SUMIF(ALIF_Y2021!$A:$A,$A102,ALIF_Y2021!$F:$F) -> -396808.4 | Z102: =SUMIF(ALIF_Y2022!$A:$A,$A102,ALIF_Y2022!$F:$F) -> -479538.73 | AA102: =SUMIF(ALIF_Y2023!$A:$A,$A102,ALIF_Y2023!$F:$F) -> -567470.5 | AE102: =SUMIF(#REF!,$A102,#REF!) -> #REF! | AF102: =SUMIF(#REF!,$A102,#REF!) -> #REF! | AG102: =SUMIF(#REF!,$A102,#REF!) -> #REF! | AH102: =SUMIF(#REF!,$A102,#REF!) -> #REF! | AI102: =SUMIF(#REF!,$A102,#REF!) -> #REF! | AJ102: =SUMIF(#REF!,$A102,#REF!) -> #REF! | AK102: =SUMIF(#REF!,$A102,#REF!) -> #REF! | AL102: =SUMIF(#REF!,$A102,#REF!) -> #REF! | ... AO102: =SUMIF(#REF!,$A102,#REF!) -> #REF!
